Workbook

Sheet PORTADA
C3: ANEXO D
C4: MATRIZ DE ANÁLISIS DE BRECHAS
C8: Permite identificar y evaluar las diferencias entre el estado actual de cumplimiento y el estado esperado, facilitando la priorización de acciones correctivas y oportunidades de mejora en materia de protección de datos personales.
C11: ESTUDIANTES
C12: Armijos Montoya María Milady Leiva Pazmiño Christian Andrés Valverde Vargas Pedro Eduardo
C16: Maestría en Seguridad Informática — Trabajo de Titulación

Sheet RESUMEN ANEXO
B2: ANEXO D · MATRIZ DE ANÁLISIS DE BRECHAS
B4: Objeto | C4: Identificar, priorizar y asignar responsables a las brechas de cumplimiento normativo (LOPDP/RGLOPDP), madurez institucional y gobernanza tecnológica detectadas en la autoevaluación de las cuatro instituciones educativas participantes (Institución A, B, C y D), con el fin de orientar su cierre hasta alcanzar el 100% de cumplimiento de la LOPDP.
B5: Marco de referencia | C5: Ley Orgánica de Protección de Datos Personales (LOPDP) y su Reglamento General; ISO/IEC 27001:2022 (Sistema de Gestión de Seguridad de la Información y Anexo A de controles); ISO/IEC 27701 (gestión de la privacidad); Esquema Gubernamental de Seguridad de la Información (EGSI).
B6: Fuentes de información | C6: Instrumento de Autoevaluación Institucional (Módulos 1, 2 y 3) e Informes Ejecutivos de las cuatro instituciones educativas evaluadas.
B7: Elaborado por | C7: Equipo de investigación — enfoque de seguridad de la información aplicado a la LOPDP (Ecuador).
B8: Alcance | C8: 82 criterios/dimensiones evaluados: 29 de cumplimiento normativo (Módulo 1), 25 de madurez institucional (Módulo 2) y 28 de gobernanza tecnológica (Módulo 3).
B10: METODOLOGÍA DE PRIORIZACIÓN
B11: • Cada criterio recibe un puntaje de brecha (0 a 8) que suma la situación de las 4 instituciones: No = 2 pts · Parcial = 1 pt · Sí = 0 pts (Módulos 1 y 3); Nivel de madurez 1 = 2 pts · 2 = 1.5 · 3 = 1 · 4 = 0.5 · 5 = 0 pts (Módulo 2).
B12: • Prioridad: CRÍTICA (puntaje ≥ 6) · ALTA (≥ 4) · MEDIA (≥ 2) · BAJA (< 2).
B13: • Plazo sugerido: CRÍTICA 0-3 meses · ALTA 3-6 meses · MEDIA 6-9 meses · BAJA 9-12 meses.
B14: • Cada criterio se mapea a su control correspondiente del Anexo A de ISO/IEC 27001:2022 (u otra cláusula del SGSI) y a su base legal en la LOPDP, de forma que el cierre de la brecha sea a la vez jurídicamente exigible y técnicamente auditable.
B16: CONTENIDO DEL LIBRO
B17: Matriz Consolidada | C17: Los 82 criterios con estado por institución, control ISO 27001, riesgo, acción correctiva, prioridad y plazo.
B18: Resumen Ejecutivo | C18: Tablero con brechas por módulo/institución e índice actual vs. meta de 100%.
B19: Hoja de Ruta_100pct | C19: Cronograma consolidado (0-3, 3-6, 6-9, 9-12 meses) para cerrar todas las brechas.
B20: Mapa ISO27001 | C20: Trazabilidad entre criterios LOPDP y controles del Anexo A de ISO/IEC 27001:2022.
B21: Plan_Institucion_A..D | C21: Plan de cierre de brechas específico y priorizado para cada institución.

Sheet Matriz Consolidada
B2: MATRIZ DE ANÁLISIS DE BRECHAS — DETALLE DE 82 CRITERIOS (MÓDULOS 1, 2 Y 3)
B3: Módulo | C3: ID | D3: Sección | E3: Criterio / Dimensión | F3: Base legal / Marco | G3: Control ISO/IEC 27001:2022 (Anexo A / cláusula) | H3: Estado A | I3: Estado B | J3: Estado C | K3: Estado D | L3: Pts A | M3: Pts B | N3: Pts C | O3: Pts D | P3: N° instituciones con brecha | Q3: Puntaje de brecha (0-8) | R3: Prioridad | S3: Plazo sugerido | T3: Instituciones con brecha | U3: Riesgo si no se corrige | V3: Acción correctiva recomendada | W3: Responsable sugerido | X3: Meta (100% LOPDP)
B4: M1 · Cumplimiento LOPDP/RGLOPDP | C4: A1 | D4: A. Inventario y bases de datos | E4: Identificación y registro de todas las bases de datos que contienen datos personales | F4: Art. 26, 11 y 37 LOPDP | G4: A.5.9 Inventario de información y otros activos asociados | H4: Parcial | I4: Sí | J4: Sí | K4: No | L4: =IF(ISNUMBER(H4),MAX(0,2-(H4-1)*0.5),IF(H4="No",2,IF(H4="Parcial",1,0))) -> 1 | M4: =IF(ISNUMBER(I4),MAX(0,2-(I4-1)*0.5),IF(I4="No",2,IF(I4="Parcial",1,0))) -> 0 | N4: =IF(ISNUMBER(J4),MAX(0,2-(J4-1)*0.5),IF(J4="No",2,IF(J4="Parcial",1,0))) -> 0 | O4: =IF(ISNUMBER(K4),MAX(0,2-(K4-1)*0.5),IF(K4="No",2,IF(K4="Parcial",1,0))) -> 2 | P4: =COUNTIF(L4:O4,">=1") -> 2 | Q4: =SUM(L4:O4) -> 3 | R4: =IF(Q4>=6,"CRÍTICA",IF(Q4>=4,"ALTA",IF(Q4>=2,"MEDIA","BAJA"))) -> MEDIA | S4: =IF(R4="CRÍTICA","0-3 meses",IF(R4="ALTA","3-6 meses",IF(R4="MEDIA","6-9 meses","9-12 meses"))) -> 6-9 meses | T4: A, D | U4: Sin inventario no es posible acreditar qué se trata, dónde reside ni protegerlo; imposibilita atender requerimientos de la Superintendencia y derechos ARCO+. | V4: Levantar y mantener un inventario único de bases de datos con responsable, finalidad, base de legitimación y ubicación (Registro de Actividades de Tratamiento, RAT). | W4: DPD + Secretaría/áreas dueñas de la información | X4: Sí / Cumple
B5: M1 · Cumplimiento LOPDP/RGLOPDP | C5: A2 | D5: A. Inventario y bases de datos | E5: Finalidad específica definida para cada tratamiento | F5: Art. 11 LOPDP | G5: A.5.12 Clasificación de la información | H5: Sí | I5: Sí | J5: Sí | K5: Parcial | L5: =IF(ISNUMBER(H5),MAX(0,2-(H5-1)*0.5),IF(H5="No",2,IF(H5="Parcial",1,0))) -> 0 | M5: =IF(ISNUMBER(I5),MAX(0,2-(I5-1)*0.5),IF(I5="No",2,IF(I5="Parcial",1,0))) -> 0 | N5: =IF(ISNUMBER(J5),MAX(0,2-(J5-1)*0.5),IF(J5="No",2,IF(J5="Parcial",1,0))) -> 0 | O5: =IF(ISNUMBER(K5),MAX(0,2-(K5-1)*0.5),IF(K5="No",2,IF(K5="Parcial",1,0))) -> 1 | P5: =COUNTIF(L5:O5,">=1") -> 1 | Q5: =SUM(L5:O5) -> 1 | R5: =IF(Q5>=6,"CRÍTICA",IF(Q5>=4,"ALTA",IF(Q5>=2,"MEDIA","BAJA"))) -> BAJA | S5: =IF(R5="CRÍTICA","0-3 meses",IF(R5="ALTA","3-6 meses",IF(R5="MEDIA","6-9 meses","9-12 meses"))) -> 9-12 meses | T5: D | U5: El tratamiento sin finalidad explícita habilita el uso desviado de datos (function creep) y vulnera el principio de finalidad. | V5: Documentar la finalidad de cada tratamiento en el RAT y en los avisos de privacidad correspondientes. | W5: DPD + áreas dueñas de la información | X5: Sí / Cumple
B6: M1 · Cumplimiento LOPDP/RGLOPDP | C6: A3 | D6: A. Inventario y bases de datos | E6: Documentación del período de conservación conforme a minimización y proporcionalidad | F6: Art. 10, 12 LOPDP | G6: A.5.33 Protección de los registros | H6: Sí | I6: Sí | J6: Parcial | K6: No | L6: =IF(ISNUMBER(H6),MAX(0,2-(H6-1)*0.5),IF(H6="No",2,IF(H6="Parcial",1,0))) -> 0 | M6: =IF(ISNUMBER(I6),MAX(0,2-(I6-1)*0.5),IF(I6="No",2,IF(I6="Parcial",1,0))) -> 0 | N6: =IF(ISNUMBER(J6),MAX(0,2-(J6-1)*0.5),IF(J6="No",2,IF(J6="Parcial",1,0))) -> 1 | O6: =IF(ISNUMBER(K6),MAX(0,2-(K6-1)*0.5),IF(K6="No",2,IF(K6="Parcial",1,0))) -> 2 | P6: =COUNTIF(L6:O6,">=1") -> 2 | Q6: =SUM(L6:O6) -> 3 | R6: =IF(Q6>=6,"CRÍTICA",IF(Q6>=4,"ALTA",IF(Q6>=2,"MEDIA","BAJA"))) -> MEDIA | S6: =IF(R6="CRÍTICA","0-3 meses",IF(R6="ALTA","3-6 meses",IF(R6="MEDIA","6-9 meses","9-12 meses"))) -> 6-9 meses | T6: C, D | U6: La retención indefinida de datos incrementa la superficie de exposición ante incidentes y contraviene el principio de conservación limitada. | V6: Definir y publicar una tabla de retención y eliminación de datos personales por tipo de dato y proceso. | W6: DPD + Archivo/Secretaría | X6: Sí / Cumple
B7: M1 · Cumplimiento LOPDP/RGLOPDP | C7: A4 | D7: A. Inventario y bases de datos | E7: Inventario actualizado de flujos de datos (quién recibe, quién envía, con qué propósito) | F7: Art. 26 LOPDP | G7: A.5.9 / A.8.1 Dispositivos de usuario final | H7: No | I7: No | J7: Parcial | K7: No | L7: =IF(ISNUMBER(H7),MAX(0,2-(H7-1)*0.5),IF(H7="No",2,IF(H7="Parcial",1,0))) -> 2 | M7: =IF(ISNUMBER(I7),MAX(0,2-(I7-1)*0.5),IF(I7="No",2,IF(I7="Parcial",1,0))) -> 2 | N7: =IF(ISNUMBER(J7),MAX(0,2-(J7-1)*0.5),IF(J7="No",2,IF(J7="Parcial",1,0))) -> 1 | O7: =IF(ISNUMBER(K7),MAX(0,2-(K7-1)*0.5),IF(K7="No",2,IF(K7="Parcial",1,0))) -> 2 | P7: =COUNTIF(L7:O7,">=1") -> 4 | Q7: =SUM(L7:O7) -> 7 | R7: =IF(Q7>=6,"CRÍTICA",IF(Q7>=4,"ALTA",IF(Q7>=2,"MEDIA","BAJA"))) -> CRÍTICA | S7: =IF(R7="CRÍTICA","0-3 meses",IF(R7="ALTA","3-6 meses",IF(R7="MEDIA","6-9 meses","9-12 meses"))) -> 0-3 meses | T7: A, B, C, D | U7: Sin mapa de flujos no se detectan transferencias no autorizadas a terceros o a la nube, ni se puede evaluar el riesgo de transferencias internacionales. | V7: Elaborar un diagrama de flujos de datos personales (origen, destino, medio, finalidad) y mantenerlo actualizado. | W7: DPD + TI | X7: Sí / Cumple
B8: M1 · Cumplimiento LOPDP/RGLOPDP | C8: B1 | D8: B. Consentimiento e información al titular | E8: Información al titular sobre qué datos se recopilan, cómo se usan y con quién se comparten | F8: Art. 14, 15 LOPDP | G8: A.5.34 Privacidad y protección de datos personales (PII) | H8: Sí | I8: No | J8: Parcial | K8: No | L8: =IF(ISNUMBER(H8),MAX(0,2-(H8-1)*0.5),IF(H8="No",2,IF(H8="Parcial",1,0))) -> 0 | M8: =IF(ISNUMBER(I8),MAX(0,2-(I8-1)*0.5),IF(I8="No",2,IF(I8="Parcial",1,0))) -> 2 | N8: =IF(ISNUMBER(J8),MAX(0,2-(J8-1)*0.5),IF(J8="No",2,IF(J8="Parcial",1,0))) -> 1 | O8: =IF(ISNUMBER(K8),MAX(0,2-(K8-1)*0.5),IF(K8="No",2,IF(K8="Parcial",1,0))) -> 2 | P8: =COUNTIF(L8:O8,">=1") -> 3 | Q8: =SUM(L8:O8) -> 5 | R8: =IF(Q8>=6,"CRÍTICA",IF(Q8>=4,"ALTA",IF(Q8>=2,"MEDIA","BAJA"))) -> ALTA | S8: =IF(R8="CRÍTICA","0-3 meses",IF(R8="ALTA","3-6 meses",IF(R8="MEDIA","6-9 meses","9-12 meses"))) -> 3-6 meses | T8: B, C, D | U8: La falta de información transparente impide el consentimiento válido e informado y expone a sanciones por falta de transparencia. | V8: Publicar avisos de privacidad claros y accesibles (portal web, matrícula, carteleras) para cada finalidad de tratamiento. | W8: DPD + Comunicación/Secretaría | X8: Sí / Cumple
B9: M1 · Cumplimiento LOPDP/RGLOPDP | C9: B2 | D9: B. Consentimiento e información al titular | E9: Obtención de consentimiento explícito antes de recopilar o procesar datos personales | F9: Art. 9 LOPDP | G9: A.5.34 Privacidad y protección de datos personales (PII) | H9: Sí | I9: No | J9: Parcial | K9: No | L9: =IF(ISNUMBER(H9),MAX(0,2-(H9-1)*0.5),IF(H9="No",2,IF(H9="Parcial",1,0))) -> 0 | M9: =IF(ISNUMBER(I9),MAX(0,2-(I9-1)*0.5),IF(I9="No",2,IF(I9="Parcial",1,0))) -> 2 | N9: =IF(ISNUMBER(J9),MAX(0,2-(J9-1)*0.5),IF(J9="No",2,IF(J9="Parcial",1,0))) -> 1 | O9: =IF(ISNUMBER(K9),MAX(0,2-(K9-1)*0.5),IF(K9="No",2,IF(K9="Parcial",1,0))) -> 2 | P9: =COUNTIF(L9:O9,">=1") -> 3 | Q9: =SUM(L9:O9) -> 5 | R9: =IF(Q9>=6,"CRÍTICA",IF(Q9>=4,"ALTA",IF(Q9>=2,"MEDIA","BAJA"))) -> ALTA | S9: =IF(R9="CRÍTICA","0-3 meses",IF(R9="ALTA","3-6 meses",IF(R9="MEDIA","6-9 meses","9-12 meses"))) -> 3-6 meses | T9: B, C, D | U9: El tratamiento sin consentimiento válido (o sin otra base de legitimación) constituye una infracción directa y es la causal más común de sanción. | V9: Implementar un formato de consentimiento informado (físico o digital) con registro de evidencia, diferenciado por finalidad. | W9: DPD + Secretaría | X9: Sí / Cumple
B10: M1 · Cumplimiento LOPDP/RGLOPDP | C10: B3 | D10: B. Consentimiento e información al titular | E10: Política de privacidad clara, accesible y revisada periódicamente | F10: Art. 14 LOPDP | G10: A.5.1 Políticas de seguridad de la información | H10: Parcial | I10: Sí | J10: No | K10: Parcial | L10: =IF(ISNUMBER(H10),MAX(0,2-(H10-1)*0.5),IF(H10="No",2,IF(H10="Parcial",1,0))) -> 1 | M10: =IF(ISNUMBER(I10),MAX(0,2-(I10-1)*0.5),IF(I10="No",2,IF(I10="Parcial",1,0))) -> 0 | N10: =IF(ISNUMBER(J10),MAX(0,2-(J10-1)*0.5),IF(J10="No",2,IF(J10="Parcial",1,0))) -> 2 | O10: =IF(ISNUMBER(K10),MAX(0,2-(K10-1)*0.5),IF(K10="No",2,IF(K10="Parcial",1,0))) -> 1 | P10: =COUNTIF(L10:O10,">=1") -> 3 | Q10: =SUM(L10:O10) -> 4 | R10: =IF(Q10>=6,"CRÍTICA",IF(Q10>=4,"ALTA",IF(Q10>=2,"MEDIA","BAJA"))) -> ALTA | S10: =IF(R10="CRÍTICA","0-3 meses",IF(R10="ALTA","3-6 meses",IF(R10="MEDIA","6-9 meses","9-12 meses"))) -> 3-6 meses | T10: A, C, D | U10: Una política ausente o desactualizada deja sin marco de referencia a la comunidad educativa y al personal encargado del tratamiento. | V10: Redactar, aprobar y publicar la política institucional de protección de datos personales; revisarla al menos una vez al año. | W10: Dirección + DPD | X10: Sí / Cumple
B11: M1 · Cumplimiento LOPDP/RGLOPDP | C11: B4 | D11: B. Consentimiento e información al titular | E11: Información a los titulares sobre cómo ejercer sus derechos ARCO+ | F11: Art. 19-25 LOPDP | G11: A.5.34 Privacidad y protección de datos personales (PII) | H11: No | I11: Sí | J11: No | K11: Parcial | L11: =IF(ISNUMBER(H11),MAX(0,2-(H11-1)*0.5),IF(H11="No",2,IF(H11="Parcial",1,0))) -> 2 | M11: =IF(ISNUMBER(I11),MAX(0,2-(I11-1)*0.5),IF(I11="No",2,IF(I11="Parcial",1,0))) -> 0 | N11: =IF(ISNUMBER(J11),MAX(0,2-(J11-1)*0.5),IF(J11="No",2,IF(J11="Parcial",1,0))) -> 2 | O11: =IF(ISNUMBER(K11),MAX(0,2-(K11-1)*0.5),IF(K11="No",2,IF(K11="Parcial",1,0))) -> 1 | P11: =COUNTIF(L11:O11,">=1") -> 3 | Q11: =SUM(L11:O11) -> 5 | R11: =IF(Q11>=6,"CRÍTICA",IF(Q11>=4,"ALTA",IF(Q11>=2,"MEDIA","BAJA"))) -> ALTA | S11: =IF(R11="CRÍTICA","0-3 meses",IF(R11="ALTA","3-6 meses",IF(R11="MEDIA","6-9 meses","9-12 meses"))) -> 3-6 meses | T11: A, C, D | U11: Los titulares no pueden ejercer derechos que desconocen, lo que perpetúa el uso de datos sin control del titular. | V11: Incluir en avisos de privacidad y canales institucionales el procedimiento y medios para ejercer derechos ARCO+. | W11: DPD + Comunicación | X11: Sí / Cumple
B12: M1 · Cumplimiento LOPDP/RGLOPDP | C12: B5 | D12: B. Consentimiento e información al titular | E12: Política de uso de cookies con consentimiento informado | F12: Art. 8, 9 y 14 LOPDP | G12: A.5.34 Privacidad y protección de datos personales (PII) | H12: No | I12: No | J12: No | K12: No | L12: =IF(ISNUMBER(H12),MAX(0,2-(H12-1)*0.5),IF(H12="No",2,IF(H12="Parcial",1,0))) -> 2 | M12: =IF(ISNUMBER(I12),MAX(0,2-(I12-1)*0.5),IF(I12="No",2,IF(I12="Parcial",1,0))) -> 2 | N12: =IF(ISNUMBER(J12),MAX(0,2-(J12-1)*0.5),IF(J12="No",2,IF(J12="Parcial",1,0))) -> 2 | O12: =IF(ISNUMBER(K12),MAX(0,2-(K12-1)*0.5),IF(K12="No",2,IF(K12="Parcial",1,0))) -> 2 | P12: =COUNTIF(L12:O12,">=1") -> 4 | Q12: =SUM(L12:O12) -> 8 | R12: =IF(Q12>=6,"CRÍTICA",IF(Q12>=4,"ALTA",IF(Q12>=2,"MEDIA","BAJA"))) -> CRÍTICA | S12: =IF(R12="CRÍTICA","0-3 meses",IF(R12="ALTA","3-6 meses",IF(R12="MEDIA","6-9 meses","9-12 meses"))) -> 0-3 meses | T12: A, B, C, D | U12: El uso de cookies o rastreo sin consentimiento en plataformas institucionales expone a tratamiento no autorizado de datos de navegación. | V12: Implementar aviso/banner de cookies con opciones de aceptación granular en los sitios y plataformas institucionales. | W12: TI + DPD | X12: Sí / Cumple
B13: M1 · Cumplimiento LOPDP/RGLOPDP | C13: C1 | D13: C. Derechos de los titulares (ARCO+) | E13: Mecanismo formal para atender solicitudes de Acceso a datos personales | F13: Art. 19 LOPDP | G13: A.5.34 Privacidad y protección de datos personales (PII) | H13: Parcial | I13: Sí | J13: Parcial | K13: No | L13: =IF(ISNUMBER(H13),MAX(0,2-(H13-1)*0.5),IF(H13="No",2,IF(H13="Parcial",1,0))) -> 1 | M13: =IF(ISNUMBER(I13),MAX(0,2-(I13-1)*0.5),IF(I13="No",2,IF(I13="Parcial",1,0))) -> 0 | N13: =IF(ISNUMBER(J13),MAX(0,2-(J13-1)*0.5),IF(J13="No",2,IF(J13="Parcial",1,0))) -> 1 | O13: =IF(ISNUMBER(K13),MAX(0,2-(K13-1)*0.5),IF(K13="No",2,IF(K13="Parcial",1,0))) -> 2 | P13: =COUNTIF(L13:O13,">=1") -> 3 | Q13: =SUM(L13:O13) -> 4 | R13: =IF(Q13>=6,"CRÍTICA",IF(Q13>=4,"ALTA",IF(Q13>=2,"MEDIA","BAJA"))) -> ALTA | S13: =IF(R13="CRÍTICA","0-3 meses",IF(R13="ALTA","3-6 meses",IF(R13="MEDIA","6-9 meses","9-12 meses"))) -> 3-6 meses | T13: A, C, D | U13: La ausencia de canal formal deriva en respuestas informales, fuera de plazo o inexistentes, con riesgo de sanción y pérdida de confianza. | V13: Crear un procedimiento documentado (formulario, canal y plazos) para solicitudes de acceso. | W13: DPD + Secretaría | X13: Sí / Cumple
B14: M1 · Cumplimiento LOPDP/RGLOPDP | C14: C2 | D14: C. Derechos de los titulares (ARCO+) | E14: Mecanismo formal para solicitudes de Rectificación de datos | F14: Art. 20 LOPDP | G14: A.5.34 Privacidad y protección de datos personales (PII) | H14: Parcial | I14: Sí | J14: Parcial | K14: No | L14: =IF(ISNUMBER(H14),MAX(0,2-(H14-1)*0.5),IF(H14="No",2,IF(H14="Parcial",1,0))) -> 1 | M14: =IF(ISNUMBER(I14),MAX(0,2-(I14-1)*0.5),IF(I14="No",2,IF(I14="Parcial",1,0))) -> 0 | N14: =IF(ISNUMBER(J14),MAX(0,2-(J14-1)*0.5),IF(J14="No",2,IF(J14="Parcial",1,0))) -> 1 | O14: =IF(ISNUMBER(K14),MAX(0,2-(K14-1)*0.5),IF(K14="No",2,IF(K14="Parcial",1,0))) -> 2 | P14: =COUNTIF(L14:O14,">=1") -> 3 | Q14: =SUM(L14:O14) -> 4 | R14: =IF(Q14>=6,"CRÍTICA",IF(Q14>=4,"ALTA",IF(Q14>=2,"MEDIA","BAJA"))) -> ALTA | S14: =IF(R14="CRÍTICA","0-3 meses",IF(R14="ALTA","3-6 meses",IF(R14="MEDIA","6-9 meses","9-12 meses"))) -> 3-6 meses | T14: A, C, D | U14: Datos inexactos no corregidos afectan decisiones académicas/administrativas y vulneran el derecho de rectificación. | V14: Extender el procedimiento de derechos ARCO+ para incluir rectificación con verificación de identidad y trazabilidad del cambio. | W14: DPD + Secretaría | X14: Sí / Cumple
B15: M1 · Cumplimiento LOPDP/RGLOPDP | C15: C3 | D15: C. Derechos de los titulares (ARCO+) | E15: Mecanismo formal para solicitudes de Cancelación / Supresión de datos | F15: Art. 21 LOPDP | G15: A.5.34 Privacidad y protección de datos personales (PII) | H15: No | I15: No | J15: Parcial | K15: No | L15: =IF(ISNUMBER(H15),MAX(0,2-(H15-1)*0.5),IF(H15="No",2,IF(H15="Parcial",1,0))) -> 2 | M15: =IF(ISNUMBER(I15),MAX(0,2-(I15-1)*0.5),IF(I15="No",2,IF(I15="Parcial",1,0))) -> 2 | N15: =IF(ISNUMBER(J15),MAX(0,2-(J15-1)*0.5),IF(J15="No",2,IF(J15="Parcial",1,0))) -> 1 | O15: =IF(ISNUMBER(K15),MAX(0,2-(K15-1)*0.5),IF(K15="No",2,IF(K15="Parcial",1,0))) -> 2 | P15: =COUNTIF(L15:O15,">=1") -> 4 | Q15: =SUM(L15:O15) -> 7 | R15: =IF(Q15>=6,"CRÍTICA",IF(Q15>=4,"ALTA",IF(Q15>=2,"MEDIA","BAJA"))) -> CRÍTICA | S15: =IF(R15="CRÍTICA","0-3 meses",IF(R15="ALTA","3-6 meses",IF(R15="MEDIA","6-9 meses","9-12 meses"))) -> 0-3 meses | T15: A, B, C, D | U15: Sin procedimiento de supresión, los datos se conservan más allá de lo necesario incluso cuando el titular lo solicita. | V15: Definir el procedimiento y las excepciones legales de conservación aplicables a la supresión de datos. | W15: DPD + Secretaría/Archivo | X15: Sí / Cumple
... B32: M1 · Cumplimiento LOPDP/RGLOPDP | C32: F4 | D32: F. Auditoría, capacitación y mejora continua | E32: Pruebas de penetración o análisis de seguridad informática | F32: Art. 37 y 40 LOPDP | G32: A.8.29 Pruebas de seguridad en el desarrollo y aceptación / A.5.36 Cumplimiento de políticas | H32: Sí | I32: Parcial | J32: No | K32: No | L32: =IF(ISNUMBER(H32),MAX(0,2-(H32-1)*0.5),IF(H32="No",2,IF(H32="Parcial",1,0))) -> 0 | M32: =IF(ISNUMBER(I32),MAX(0,2-(I32-1)*0.5),IF(I32="No",2,IF(I32="Parcial",1,0))) -> 1 | N32: =IF(ISNUMBER(J32),MAX(0,2-(J32-1)*0.5),IF(J32="No",2,IF(J32="Parcial",1,0))) -> 2 | O32: =IF(ISNUMBER(K32),MAX(0,2-(K32-1)*0.5),IF(K32="No",2,IF(K32="Parcial",1,0))) -> 2 | P32: =COUNTIF(L32:O32,">=1") -> 3 | Q32: =SUM(L32:O32) -> 5 | R32: =IF(Q32>=6,"CRÍTICA",IF(Q32>=4,"ALTA",IF(Q32>=2,"MEDIA","BAJA"))) -> ALTA | S32: =IF(R32="CRÍTICA","0-3 meses",IF(R32="ALTA","3-6 meses",IF(R32="MEDIA","6-9 meses","9-12 meses"))) -> 3-6 meses | T32: B, C, D | U32: Sin pruebas de seguridad periódicas, las vulnerabilidades explotables permanecen sin detectar hasta que ocurre un incidente real. | V32: Contratar o ejecutar pruebas de seguridad (pentesting/vulnerability assessment) al menos una vez al año sobre sistemas críticos. | W32: TI | X32: Sí / Cumple
B33: M2 · Madurez Institucional | C33: G1 | D33: I. Gobernanza y liderazgo en datos | E33: Estructura de gobierno de datos con roles y responsabilidades definidos (Responsable, DPD, Encargados) | F33: Art. 47-50 LOPDP | G33: A.5.2 Roles y responsabilidades de seguridad de la información | H33: 1 | I33: 1 | J33: 1 | K33: 1 | L33: =IF(ISNUMBER(H33),MAX(0,2-(H33-1)*0.5),IF(H33="No",2,IF(H33="Parcial",1,0))) -> 2 | M33: =IF(ISNUMBER(I33),MAX(0,2-(I33-1)*0.5),IF(I33="No",2,IF(I33="Parcial",1,0))) -> 2 | N33: =IF(ISNUMBER(J33),MAX(0,2-(J33-1)*0.5),IF(J33="No",2,IF(J33="Parcial",1,0))) -> 2 | O33: =IF(ISNUMBER(K33),MAX(0,2-(K33-1)*0.5),IF(K33="No",2,IF(K33="Parcial",1,0))) -> 2 | P33: =COUNTIF(L33:O33,">=1") -> 4 | Q33: =SUM(L33:O33) -> 8 | R33: =IF(Q33>=6,"CRÍTICA",IF(Q33>=4,"ALTA",IF(Q33>=2,"MEDIA","BAJA"))) -> CRÍTICA | S33: =IF(R33="CRÍTICA","0-3 meses",IF(R33="ALTA","3-6 meses",IF(R33="MEDIA","6-9 meses","9-12 meses"))) -> 0-3 meses | T33: A, B, C, D | U33: Sin estructura de gobierno, nadie es responsable formal de decisiones sobre datos personales, dificultando la rendición de cuentas. | V33: Definir y aprobar formalmente el organigrama de gobierno de datos (RACI) con Responsable, DPD y Encargados. | W33: Dirección | X33: Nivel 5 / Optimizado
B34: M2 · Madurez Institucional | C34: G2 | D34: I. Gobernanza y liderazgo en datos | E34: Liderazgo y compromiso de la alta dirección con el cumplimiento normativo | F34: Art. 47-50 LOPDP | G34: Cláusula 5.1 Liderazgo y compromiso | H34: 3 | I34: 1 | J34: 2 | K34: 2 | L34: =IF(ISNUMBER(H34),MAX(0,2-(H34-1)*0.5),IF(H34="No",2,IF(H34="Parcial",1,0))) -> 1 | M34: =IF(ISNUMBER(I34),MAX(0,2-(I34-1)*0.5),IF(I34="No",2,IF(I34="Parcial",1,0))) -> 2 | N34: =IF(ISNUMBER(J34),MAX(0,2-(J34-1)*0.5),IF(J34="No",2,IF(J34="Parcial",1,0))) -> 1.5 | O34: =IF(ISNUMBER(K34),MAX(0,2-(K34-1)*0.5),IF(K34="No",2,IF(K34="Parcial",1,0))) -> 1.5 | P34: =COUNTIF(L34:O34,">=1") -> 4 | Q34: =SUM(L34:O34) -> 6 | R34: =IF(Q34>=6,"CRÍTICA",IF(Q34>=4,"ALTA",IF(Q34>=2,"MEDIA","BAJA"))) -> CRÍTICA | S34: =IF(R34="CRÍTICA","0-3 meses",IF(R34="ALTA","3-6 meses",IF(R34="MEDIA","6-9 meses","9-12 meses"))) -> 0-3 meses | T34: A, B, C, D | U34: Sin patrocinio directivo, las iniciativas de cumplimiento carecen de recursos y prioridad institucional. | V34: Incluir la protección de datos como punto permanente en la planificación estratégica y en los comités de dirección. | W34: Rectorado/Dirección | X34: Nivel 5 / Optimizado
B35: M2 · Madurez Institucional | C35: G3 | D35: I. Gobernanza y liderazgo en datos | E35: Políticas institucionales formalizadas sobre privacidad y protección de datos personales | F35: Art. 14 LOPDP | G35: A.5.1 Políticas de seguridad de la información | H35: 1 | I35: 3 | J35: 2 | K35: 1 | L35: =IF(ISNUMBER(H35),MAX(0,2-(H35-1)*0.5),IF(H35="No",2,IF(H35="Parcial",1,0))) -> 2 | M35: =IF(ISNUMBER(I35),MAX(0,2-(I35-1)*0.5),IF(I35="No",2,IF(I35="Parcial",1,0))) -> 1 | N35: =IF(ISNUMBER(J35),MAX(0,2-(J35-1)*0.5),IF(J35="No",2,IF(J35="Parcial",1,0))) -> 1.5 | O35: =IF(ISNUMBER(K35),MAX(0,2-(K35-1)*0.5),IF(K35="No",2,IF(K35="Parcial",1,0))) -> 2 | P35: =COUNTIF(L35:O35,">=1") -> 4 | Q35: =SUM(L35:O35) -> 6.5 | R35: =IF(Q35>=6,"CRÍTICA",IF(Q35>=4,"ALTA",IF(Q35>=2,"MEDIA","BAJA"))) -> CRÍTICA | S35: =IF(R35="CRÍTICA","0-3 meses",IF(R35="ALTA","3-6 meses",IF(R35="MEDIA","6-9 meses","9-12 meses"))) -> 0-3 meses | T35: A, B, C, D | U35: La falta de política formal deja los criterios de protección de datos a decisiones ad hoc, inconsistentes entre áreas. | V35: Aprobar y difundir la política institucional de protección de datos personales. | W35: Dirección + DPD | X35: Nivel 5 / Optimizado
B36: M2 · Madurez Institucional | C36: G4 | D36: I. Gobernanza y liderazgo en datos | E36: Presupuesto asignado para actividades de cumplimiento y protección de datos | F36: Art. 47-50 LOPDP | G36: Cláusula 7.1 Recursos | H36: 5 | I36: 2 | J36: 1 | K36: 1 | L36: =IF(ISNUMBER(H36),MAX(0,2-(H36-1)*0.5),IF(H36="No",2,IF(H36="Parcial",1,0))) -> 0 | M36: =IF(ISNUMBER(I36),MAX(0,2-(I36-1)*0.5),IF(I36="No",2,IF(I36="Parcial",1,0))) -> 1.5 | N36: =IF(ISNUMBER(J36),MAX(0,2-(J36-1)*0.5),IF(J36="No",2,IF(J36="Parcial",1,0))) -> 2 | O36: =IF(ISNUMBER(K36),MAX(0,2-(K36-1)*0.5),IF(K36="No",2,IF(K36="Parcial",1,0))) -> 2 | P36: =COUNTIF(L36:O36,">=1") -> 3 | Q36: =SUM(L36:O36) -> 5.5 | R36: =IF(Q36>=6,"CRÍTICA",IF(Q36>=4,"ALTA",IF(Q36>=2,"MEDIA","BAJA"))) -> ALTA | S36: =IF(R36="CRÍTICA","0-3 meses",IF(R36="ALTA","3-6 meses",IF(R36="MEDIA","6-9 meses","9-12 meses"))) -> 3-6 meses | T36: B, C, D | U36: Sin presupuesto, ninguna de las acciones correctivas de este plan es sostenible en el tiempo. | V36: Asignar una partida presupuestaria anual específica para protección de datos y seguridad de la información. | W36: Dirección/Financiero | X36: Nivel 5 / Optimizado
B37: M2 · Madurez Institucional | C37: P1 | D37: II. Gestión de procesos y procedimientos | E37: Procesos de tratamiento de datos documentados, aprobados y comunicados al personal | F37: Art. 37 LOPDP | G37: A.5.37 Procedimientos operativos documentados | H37: 1 | I37: 2 | J37: 2 | K37: 1 | L37: =IF(ISNUMBER(H37),MAX(0,2-(H37-1)*0.5),IF(H37="No",2,IF(H37="Parcial",1,0))) -> 2 | M37: =IF(ISNUMBER(I37),MAX(0,2-(I37-1)*0.5),IF(I37="No",2,IF(I37="Parcial",1,0))) -> 1.5 | N37: =IF(ISNUMBER(J37),MAX(0,2-(J37-1)*0.5),IF(J37="No",2,IF(J37="Parcial",1,0))) -> 1.5 | O37: =IF(ISNUMBER(K37),MAX(0,2-(K37-1)*0.5),IF(K37="No",2,IF(K37="Parcial",1,0))) -> 2 | P37: =COUNTIF(L37:O37,">=1") -> 4 | Q37: =SUM(L37:O37) -> 7 | R37: =IF(Q37>=6,"CRÍTICA",IF(Q37>=4,"ALTA",IF(Q37>=2,"MEDIA","BAJA"))) -> CRÍTICA | S37: =IF(R37="CRÍTICA","0-3 meses",IF(R37="ALTA","3-6 meses",IF(R37="MEDIA","6-9 meses","9-12 meses"))) -> 0-3 meses | T37: A, B, C, D | U37: Procesos no documentados dependen de la memoria de personas concretas, generando inconsistencia y pérdida de conocimiento ante rotación de personal. | V37: Documentar y aprobar los procedimientos clave de tratamiento de datos y capacitar al personal en su aplicación. | W37: DPD + dueños de proceso | X37: Nivel 5 / Optimizado
B38: M2 · Madurez Institucional | C38: P2 | D38: II. Gestión de procesos y procedimientos | E38: Registro de Actividades de Tratamiento (RAT) actualizado | F38: Art. 26 LOPDP | G38: A.5.9 Inventario de información y otros activos asociados | H38: 1 | I38: 1 | J38: 1 | K38: 1 | L38: =IF(ISNUMBER(H38),MAX(0,2-(H38-1)*0.5),IF(H38="No",2,IF(H38="Parcial",1,0))) -> 2 | M38: =IF(ISNUMBER(I38),MAX(0,2-(I38-1)*0.5),IF(I38="No",2,IF(I38="Parcial",1,0))) -> 2 | N38: =IF(ISNUMBER(J38),MAX(0,2-(J38-1)*0.5),IF(J38="No",2,IF(J38="Parcial",1,0))) -> 2 | O38: =IF(ISNUMBER(K38),MAX(0,2-(K38-1)*0.5),IF(K38="No",2,IF(K38="Parcial",1,0))) -> 2 | P38: =COUNTIF(L38:O38,">=1") -> 4 | Q38: =SUM(L38:O38) -> 8 | R38: =IF(Q38>=6,"CRÍTICA",IF(Q38>=4,"ALTA",IF(Q38>=2,"MEDIA","BAJA"))) -> CRÍTICA | S38: =IF(R38="CRÍTICA","0-3 meses",IF(R38="ALTA","3-6 meses",IF(R38="MEDIA","6-9 meses","9-12 meses"))) -> 0-3 meses | T38: A, B, C, D | U38: Un RAT desactualizado o inexistente impide demostrar cumplimiento ante la autoridad de control. | V38: Levantar el RAT y establecer una revisión periódica (al menos semestral) para mantenerlo vigente. | W38: DPD | X38: Nivel 5 / Optimizado
B39: M2 · Madurez Institucional | C39: P3 | D39: II. Gestión de procesos y procedimientos | E39: Procedimientos formales para responder derechos ARCO+ de los titulares | F39: Art. 19-25 LOPDP | G39: A.5.34 Privacidad y protección de datos personales (PII) | H39: 1 | I39: 1 | J39: 1 | K39: 1 | L39: =IF(ISNUMBER(H39),MAX(0,2-(H39-1)*0.5),IF(H39="No",2,IF(H39="Parcial",1,0))) -> 2 | M39: =IF(ISNUMBER(I39),MAX(0,2-(I39-1)*0.5),IF(I39="No",2,IF(I39="Parcial",1,0))) -> 2 | N39: =IF(ISNUMBER(J39),MAX(0,2-(J39-1)*0.5),IF(J39="No",2,IF(J39="Parcial",1,0))) -> 2 | O39: =IF(ISNUMBER(K39),MAX(0,2-(K39-1)*0.5),IF(K39="No",2,IF(K39="Parcial",1,0))) -> 2 | P39: =COUNTIF(L39:O39,">=1") -> 4 | Q39: =SUM(L39:O39) -> 8 | R39: =IF(Q39>=6,"CRÍTICA",IF(Q39>=4,"ALTA",IF(Q39>=2,"MEDIA","BAJA"))) -> CRÍTICA | S39: =IF(R39="CRÍTICA","0-3 meses",IF(R39="ALTA","3-6 meses",IF(R39="MEDIA","6-9 meses","9-12 meses"))) -> 0-3 meses | T39: A, B, C, D | U39: La ausencia de procedimiento formal deriva en respuestas inconsistentes o fuera de plazo a los titulares. | V39: Formalizar el procedimiento único de atención de derechos ARCO+ (ver Módulo 1, sección C). | W39: DPD | X39: Nivel 5 / Optimizado
B40: M2 · Madurez Institucional | C40: P4 | D40: II. Gestión de procesos y procedimientos | E40: Procedimientos para gestión de incidentes y brechas de datos | F40: Art. 42 y 44 LOPDP | G40: A.5.24 Planificación y preparación de la gestión de incidentes | H40: 3 | I40: 1 | J40: 1 | K40: 1 | L40: =IF(ISNUMBER(H40),MAX(0,2-(H40-1)*0.5),IF(H40="No",2,IF(H40="Parcial",1,0))) -> 1 | M40: =IF(ISNUMBER(I40),MAX(0,2-(I40-1)*0.5),IF(I40="No",2,IF(I40="Parcial",1,0))) -> 2 | N40: =IF(ISNUMBER(J40),MAX(0,2-(J40-1)*0.5),IF(J40="No",2,IF(J40="Parcial",1,0))) -> 2 | O40: =IF(ISNUMBER(K40),MAX(0,2-(K40-1)*0.5),IF(K40="No",2,IF(K40="Parcial",1,0))) -> 2 | P40: =COUNTIF(L40:O40,">=1") -> 4 | Q40: =SUM(L40:O40) -> 7 | R40: =IF(Q40>=6,"CRÍTICA",IF(Q40>=4,"ALTA",IF(Q40>=2,"MEDIA","BAJA"))) -> CRÍTICA | S40: =IF(R40="CRÍTICA","0-3 meses",IF(R40="ALTA","3-6 meses",IF(R40="MEDIA","6-9 meses","9-12 meses"))) -> 0-3 meses | T40: A, B, C, D | U40: Sin procedimiento, la respuesta ante una brecha real será improvisada, tardía y con mayor impacto legal y reputacional. | V40: Aprobar el procedimiento de gestión de incidentes de seguridad de la información con roles y tiempos de respuesta. | W40: TI + DPD | X40: Nivel 5 / Optimizado
B41: M2 · Madurez Institucional | C41: P5 | D41: II. Gestión de procesos y procedimientos | E41: Proceso de revisión y mejora continua de los procedimientos de protección de datos | F41: Art. 47 LOPDP | G41: Cláusula 10.1 Mejora continua | H41: 1 | I41: 1 | J41: 1 | K41: 1 | L41: =IF(ISNUMBER(H41),MAX(0,2-(H41-1)*0.5),IF(H41="No",2,IF(H41="Parcial",1,0))) -> 2 | M41: =IF(ISNUMBER(I41),MAX(0,2-(I41-1)*0.5),IF(I41="No",2,IF(I41="Parcial",1,0))) -> 2 | N41: =IF(ISNUMBER(J41),MAX(0,2-(J41-1)*0.5),IF(J41="No",2,IF(J41="Parcial",1,0))) -> 2 | O41: =IF(ISNUMBER(K41),MAX(0,2-(K41-1)*0.5),IF(K41="No",2,IF(K41="Parcial",1,0))) -> 2 | P41: =COUNTIF(L41:O41,">=1") -> 4 | Q41: =SUM(L41:O41) -> 8 | R41: =IF(Q41>=6,"CRÍTICA",IF(Q41>=4,"ALTA",IF(Q41>=2,"MEDIA","BAJA"))) -> CRÍTICA | S41: =IF(R41="CRÍTICA","0-3 meses",IF(R41="ALTA","3-6 meses",IF(R41="MEDIA","6-9 meses","9-12 meses"))) -> 0-3 meses | T41: A, B, C, D | U41: Procedimientos que no se revisan quedan obsoletos frente a cambios normativos, tecnológicos u organizacionales. | V41: Establecer un ciclo anual de revisión de procedimientos de protección de datos, con responsable y fecha de revisión. | W41: DPD | X41: Nivel 5 / Optimizado
B42: M2 · Madurez Institucional | C42: CC1 | D42: III. Cultura y capacitación organizacional | E42: Conocimiento básico del personal sobre la LOPDP y sus obligaciones | F42: Art. 37 LOPDP | G42: A.6.3 Concienciación, educación y formación en seguridad de la información | H42: 3 | I42: 2 | J42: 2 | K42: 1 | L42: =IF(ISNUMBER(H42),MAX(0,2-(H42-1)*0.5),IF(H42="No",2,IF(H42="Parcial",1,0))) -> 1 | M42: =IF(ISNUMBER(I42),MAX(0,2-(I42-1)*0.5),IF(I42="No",2,IF(I42="Parcial",1,0))) -> 1.5 | N42: =IF(ISNUMBER(J42),MAX(0,2-(J42-1)*0.5),IF(J42="No",2,IF(J42="Parcial",1,0))) -> 1.5 | O42: =IF(ISNUMBER(K42),MAX(0,2-(K42-1)*0.5),IF(K42="No",2,IF(K42="Parcial",1,0))) -> 2 | P42: =COUNTIF(L42:O42,">=1") -> 4 | Q42: =SUM(L42:O42) -> 6 | R42: =IF(Q42>=6,"CRÍTICA",IF(Q42>=4,"ALTA",IF(Q42>=2,"MEDIA","BAJA"))) -> CRÍTICA | S42: =IF(R42="CRÍTICA","0-3 meses",IF(R42="ALTA","3-6 meses",IF(R42="MEDIA","6-9 meses","9-12 meses"))) -> 0-3 meses | T42: A, B, C, D | U42: Personal sin conocimiento básico de la ley no puede identificar ni prevenir incumplimientos en su labor diaria. | V42: Difundir una guía básica de LOPDP a todo el personal como parte de la inducción institucional. | W42: Talento Humano | X42: Nivel 5 / Optimizado
B43: M2 · Madurez Institucional | C43: CC2 | D43: III. Cultura y capacitación organizacional | E43: Capacitaciones formales y periódicas sobre protección de datos a todos los niveles | F43: Art. 37 LOPDP | G43: A.6.3 Concienciación, educación y formación en seguridad de la información | H43: 1 | I43: 1 | J43: 2 | K43: 1 | L43: =IF(ISNUMBER(H43),MAX(0,2-(H43-1)*0.5),IF(H43="No",2,IF(H43="Parcial",1,0))) -> 2 | M43: =IF(ISNUMBER(I43),MAX(0,2-(I43-1)*0.5),IF(I43="No",2,IF(I43="Parcial",1,0))) -> 2 | N43: =IF(ISNUMBER(J43),MAX(0,2-(J43-1)*0.5),IF(J43="No",2,IF(J43="Parcial",1,0))) -> 1.5 | O43: =IF(ISNUMBER(K43),MAX(0,2-(K43-1)*0.5),IF(K43="No",2,IF(K43="Parcial",1,0))) -> 2 | P43: =COUNTIF(L43:O43,">=1") -> 4 | Q43: =SUM(L43:O43) -> 7.5 | R43: =IF(Q43>=6,"CRÍTICA",IF(Q43>=4,"ALTA",IF(Q43>=2,"MEDIA","BAJA"))) -> CRÍTICA | S43: =IF(R43="CRÍTICA","0-3 meses",IF(R43="ALTA","3-6 meses",IF(R43="MEDIA","6-9 meses","9-12 meses"))) -> 0-3 meses | T43: A, B, C, D | U43: La capacitación puntual o inexistente hace que el conocimiento se pierda y las malas prácticas se perpetúen. | V43: Implementar un plan de capacitación anual, con registro de asistencia y evaluación de efectividad. | W43: Talento Humano + DPD | X43: Nivel 5 / Optimizado
B44: M2 · Madurez Institucional | C44: CC3 | D44: III. Cultura y capacitación organizacional | E44: Cultura de privacidad por diseño en el desarrollo de nuevos proyectos o sistemas | F44: Art. 47 LOPDP | G44: A.8.25 Ciclo de vida de desarrollo seguro / A.5.34 | H44: 3 | I44: 1 | J44: 5 | K44: 1 | L44: =IF(ISNUMBER(H44),MAX(0,2-(H44-1)*0.5),IF(H44="No",2,IF(H44="Parcial",1,0))) -> 1 | M44: =IF(ISNUMBER(I44),MAX(0,2-(I44-1)*0.5),IF(I44="No",2,IF(I44="Parcial",1,0))) -> 2 | N44: =IF(ISNUMBER(J44),MAX(0,2-(J44-1)*0.5),IF(J44="No",2,IF(J44="Parcial",1,0))) -> 0 | O44: =IF(ISNUMBER(K44),MAX(0,2-(K44-1)*0.5),IF(K44="No",2,IF(K44="Parcial",1,0))) -> 2 | P44: =COUNTIF(L44:O44,">=1") -> 3 | Q44: =SUM(L44:O44) -> 5 | R44: =IF(Q44>=6,"CRÍTICA",IF(Q44>=4,"ALTA",IF(Q44>=2,"MEDIA","BAJA"))) -> ALTA | S44: =IF(R44="CRÍTICA","0-3 meses",IF(R44="ALTA","3-6 meses",IF(R44="MEDIA","6-9 meses","9-12 meses"))) -> 3-6 meses | T44: A, B, D | U44: Sin privacidad desde el diseño, los nuevos sistemas o proyectos incorporan riesgos de protección de datos evitables desde su concepción. | V44: Incluir una lista de verificación de privacidad por diseño en la adquisición o desarrollo de todo nuevo sistema. | W44: TI + DPD | X44: Nivel 5 / Optimizado
... B57: M2 · Madurez Institucional | C57: A4 | D57: VI. Auditoría, monitoreo y mejora continua | E57: Aplicación de un ciclo de mejora continua (PHVA) en la gestión de datos personales | F57: Art. 47 LOPDP | G57: Cláusula 10.1 Mejora continua | H57: 3 | I57: 1 | J57: 1 | K57: 1 | L57: =IF(ISNUMBER(H57),MAX(0,2-(H57-1)*0.5),IF(H57="No",2,IF(H57="Parcial",1,0))) -> 1 | M57: =IF(ISNUMBER(I57),MAX(0,2-(I57-1)*0.5),IF(I57="No",2,IF(I57="Parcial",1,0))) -> 2 | N57: =IF(ISNUMBER(J57),MAX(0,2-(J57-1)*0.5),IF(J57="No",2,IF(J57="Parcial",1,0))) -> 2 | O57: =IF(ISNUMBER(K57),MAX(0,2-(K57-1)*0.5),IF(K57="No",2,IF(K57="Parcial",1,0))) -> 2 | P57: =COUNTIF(L57:O57,">=1") -> 4 | Q57: =SUM(L57:O57) -> 7 | R57: =IF(Q57>=6,"CRÍTICA",IF(Q57>=4,"ALTA",IF(Q57>=2,"MEDIA","BAJA"))) -> CRÍTICA | S57: =IF(R57="CRÍTICA","0-3 meses",IF(R57="ALTA","3-6 meses",IF(R57="MEDIA","6-9 meses","9-12 meses"))) -> 0-3 meses | T57: A, B, C, D | U57: Sin ciclo PHVA, el sistema de gestión de protección de datos se estanca y no se adapta a nuevos riesgos o requisitos. | V57: Adoptar formalmente el ciclo Planificar-Hacer-Verificar-Actuar como método de gestión del sistema de protección de datos. | W57: DPD + Dirección | X57: Nivel 5 / Optimizado
B58: M3 · Gobernanza Tecnológica | C58: TG1 | D58: I. Estrategia y gobernanza TI | E58: Plan estratégico de tecnología de la información (PETI) vigente y alineado al plan institucional | F58: EGSI / buenas prácticas de gobierno TI | G58: Cláusula 5.2 Política / A.5.1 Políticas de seguridad de la información | H58: Sí | I58: Parcial | J58: No | K58: No | L58: =IF(ISNUMBER(H58),MAX(0,2-(H58-1)*0.5),IF(H58="No",2,IF(H58="Parcial",1,0))) -> 0 | M58: =IF(ISNUMBER(I58),MAX(0,2-(I58-1)*0.5),IF(I58="No",2,IF(I58="Parcial",1,0))) -> 1 | N58: =IF(ISNUMBER(J58),MAX(0,2-(J58-1)*0.5),IF(J58="No",2,IF(J58="Parcial",1,0))) -> 2 | O58: =IF(ISNUMBER(K58),MAX(0,2-(K58-1)*0.5),IF(K58="No",2,IF(K58="Parcial",1,0))) -> 2 | P58: =COUNTIF(L58:O58,">=1") -> 3 | Q58: =SUM(L58:O58) -> 5 | R58: =IF(Q58>=6,"CRÍTICA",IF(Q58>=4,"ALTA",IF(Q58>=2,"MEDIA","BAJA"))) -> ALTA | S58: =IF(R58="CRÍTICA","0-3 meses",IF(R58="ALTA","3-6 meses",IF(R58="MEDIA","6-9 meses","9-12 meses"))) -> 3-6 meses | T58: B, C, D | U58: Sin PETI, las inversiones y decisiones tecnológicas se toman de forma reactiva y desalineada de los objetivos institucionales. | V58: Elaborar un PETI a 2-3 años alineado al plan educativo institucional, incluyendo protección de datos como eje. | W58: Dirección + TI | X58: Sí / Cumple
B59: M3 · Gobernanza Tecnológica | C59: TG2 | D59: I. Estrategia y gobernanza TI | E59: Unidad o responsable formal de TI con funciones y presupuesto definidos | F59: EGSI | G59: A.5.2 Roles y responsabilidades de seguridad de la información | H59: Sí | I59: Sí | J59: Parcial | K59: No | L59: =IF(ISNUMBER(H59),MAX(0,2-(H59-1)*0.5),IF(H59="No",2,IF(H59="Parcial",1,0))) -> 0 | M59: =IF(ISNUMBER(I59),MAX(0,2-(I59-1)*0.5),IF(I59="No",2,IF(I59="Parcial",1,0))) -> 0 | N59: =IF(ISNUMBER(J59),MAX(0,2-(J59-1)*0.5),IF(J59="No",2,IF(J59="Parcial",1,0))) -> 1 | O59: =IF(ISNUMBER(K59),MAX(0,2-(K59-1)*0.5),IF(K59="No",2,IF(K59="Parcial",1,0))) -> 2 | P59: =COUNTIF(L59:O59,">=1") -> 2 | Q59: =SUM(L59:O59) -> 3 | R59: =IF(Q59>=6,"CRÍTICA",IF(Q59>=4,"ALTA",IF(Q59>=2,"MEDIA","BAJA"))) -> MEDIA | S59: =IF(R59="CRÍTICA","0-3 meses",IF(R59="ALTA","3-6 meses",IF(R59="MEDIA","6-9 meses","9-12 meses"))) -> 6-9 meses | T59: C, D | U59: Sin responsable formal de TI, la gestión tecnológica queda fragmentada y sin rendición de cuentas. | V59: Formalizar la unidad o responsable de TI, con funciones, dependencia jerárquica y presupuesto asignado. | W59: Dirección | X59: Sí / Cumple
B60: M3 · Gobernanza Tecnológica | C60: TG3 | D60: I. Estrategia y gobernanza TI | E60: Comité o instancia de toma de decisiones tecnológicas | F60: EGSI | G60: Cláusula 5.1 Liderazgo y compromiso | H60: Sí | I60: Sí | J60: No | K60: No | L60: =IF(ISNUMBER(H60),MAX(0,2-(H60-1)*0.5),IF(H60="No",2,IF(H60="Parcial",1,0))) -> 0 | M60: =IF(ISNUMBER(I60),MAX(0,2-(I60-1)*0.5),IF(I60="No",2,IF(I60="Parcial",1,0))) -> 0 | N60: =IF(ISNUMBER(J60),MAX(0,2-(J60-1)*0.5),IF(J60="No",2,IF(J60="Parcial",1,0))) -> 2 | O60: =IF(ISNUMBER(K60),MAX(0,2-(K60-1)*0.5),IF(K60="No",2,IF(K60="Parcial",1,0))) -> 2 | P60: =COUNTIF(L60:O60,">=1") -> 2 | Q60: =SUM(L60:O60) -> 4 | R60: =IF(Q60>=6,"CRÍTICA",IF(Q60>=4,"ALTA",IF(Q60>=2,"MEDIA","BAJA"))) -> ALTA | S60: =IF(R60="CRÍTICA","0-3 meses",IF(R60="ALTA","3-6 meses",IF(R60="MEDIA","6-9 meses","9-12 meses"))) -> 3-6 meses | T60: C, D | U60: Decisiones tecnológicas sin instancia formal de decisión generan inversiones inconsistentes y sin trazabilidad. | V60: Crear un comité de TI/seguridad de la información con reuniones periódicas documentadas. | W60: Dirección + TI | X60: Sí / Cumple
B61: M3 · Gobernanza Tecnológica | C61: TG4 | D61: I. Estrategia y gobernanza TI | E61: Aplicación de un marco de referencia de gobernanza TI (COBIT, ITIL, ISO 38500, ISO/IEC 27001 u otro) | F61: EGSI / mejores prácticas | G61: Cláusula 4.1-4.4 Contexto de la organización y alcance del SGSI | H61: Sí | I61: Sí | J61: Sí | K61: No | L61: =IF(ISNUMBER(H61),MAX(0,2-(H61-1)*0.5),IF(H61="No",2,IF(H61="Parcial",1,0))) -> 0 | M61: =IF(ISNUMBER(I61),MAX(0,2-(I61-1)*0.5),IF(I61="No",2,IF(I61="Parcial",1,0))) -> 0 | N61: =IF(ISNUMBER(J61),MAX(0,2-(J61-1)*0.5),IF(J61="No",2,IF(J61="Parcial",1,0))) -> 0 | O61: =IF(ISNUMBER(K61),MAX(0,2-(K61-1)*0.5),IF(K61="No",2,IF(K61="Parcial",1,0))) -> 2 | P61: =COUNTIF(L61:O61,">=1") -> 1 | Q61: =SUM(L61:O61) -> 2 | R61: =IF(Q61>=6,"CRÍTICA",IF(Q61>=4,"ALTA",IF(Q61>=2,"MEDIA","BAJA"))) -> MEDIA | S61: =IF(R61="CRÍTICA","0-3 meses",IF(R61="ALTA","3-6 meses",IF(R61="MEDIA","6-9 meses","9-12 meses"))) -> 6-9 meses | T61: D | U61: Sin marco de referencia, la gestión de TI carece de un lenguaje y estructura de controles comunes y comparables. | V61: Adoptar ISO/IEC 27001:2022 como marco de referencia principal y mapear controles existentes contra su Anexo A. | W61: TI + DPD | X61: Sí / Cumple
B62: M3 · Gobernanza Tecnológica | C62: TA1 | D62: II. Inventario y gestión de activos tecnológicos | E62: Inventario actualizado de hardware (equipos, servidores, dispositivos de red) | F62: EGSI | G62: A.5.9 Inventario de información y otros activos asociados | H62: Sí | I62: Parcial | J62: No | K62: Parcial | L62: =IF(ISNUMBER(H62),MAX(0,2-(H62-1)*0.5),IF(H62="No",2,IF(H62="Parcial",1,0))) -> 0 | M62: =IF(ISNUMBER(I62),MAX(0,2-(I62-1)*0.5),IF(I62="No",2,IF(I62="Parcial",1,0))) -> 1 | N62: =IF(ISNUMBER(J62),MAX(0,2-(J62-1)*0.5),IF(J62="No",2,IF(J62="Parcial",1,0))) -> 2 | O62: =IF(ISNUMBER(K62),MAX(0,2-(K62-1)*0.5),IF(K62="No",2,IF(K62="Parcial",1,0))) -> 1 | P62: =COUNTIF(L62:O62,">=1") -> 3 | Q62: =SUM(L62:O62) -> 4 | R62: =IF(Q62>=6,"CRÍTICA",IF(Q62>=4,"ALTA",IF(Q62>=2,"MEDIA","BAJA"))) -> ALTA | S62: =IF(R62="CRÍTICA","0-3 meses",IF(R62="ALTA","3-6 meses",IF(R62="MEDIA","6-9 meses","9-12 meses"))) -> 3-6 meses | T62: B, C, D | U62: Sin inventario de hardware no se puede garantizar que todos los equipos que procesan datos personales estén protegidos y controlados. | V62: Levantar y mantener un inventario de hardware con responsable, ubicación y criticidad. | W62: TI | X62: Sí / Cumple
B63: M3 · Gobernanza Tecnológica | C63: TA2 | D63: II. Inventario y gestión de activos tecnológicos | E63: Inventario actualizado de software y licencias | F63: EGSI | G63: A.5.9 Inventario de información y otros activos asociados / A.8.19 Instalación de software | H63: No | I63: Parcial | J63: No | K63: No | L63: =IF(ISNUMBER(H63),MAX(0,2-(H63-1)*0.5),IF(H63="No",2,IF(H63="Parcial",1,0))) -> 2 | M63: =IF(ISNUMBER(I63),MAX(0,2-(I63-1)*0.5),IF(I63="No",2,IF(I63="Parcial",1,0))) -> 1 | N63: =IF(ISNUMBER(J63),MAX(0,2-(J63-1)*0.5),IF(J63="No",2,IF(J63="Parcial",1,0))) -> 2 | O63: =IF(ISNUMBER(K63),MAX(0,2-(K63-1)*0.5),IF(K63="No",2,IF(K63="Parcial",1,0))) -> 2 | P63: =COUNTIF(L63:O63,">=1") -> 4 | Q63: =SUM(L63:O63) -> 7 | R63: =IF(Q63>=6,"CRÍTICA",IF(Q63>=4,"ALTA",IF(Q63>=2,"MEDIA","BAJA"))) -> CRÍTICA | S63: =IF(R63="CRÍTICA","0-3 meses",IF(R63="ALTA","3-6 meses",IF(R63="MEDIA","6-9 meses","9-12 meses"))) -> 0-3 meses | T63: A, B, C, D | U63: Software no inventariado puede estar sin licencia, sin actualizar o ser una puerta de entrada no controlada a los sistemas. | V63: Levantar y mantener un inventario de software y licencias, con control de instalación autorizada. | W63: TI | X63: Sí / Cumple
B64: M3 · Gobernanza Tecnológica | C64: TA3 | D64: II. Inventario y gestión de activos tecnológicos | E64: Identificación y clasificación de los sistemas de información por criticidad | F64: EGSI | G64: A.5.12 Clasificación de la información | H64: Sí | I64: Parcial | J64: No | K64: No | L64: =IF(ISNUMBER(H64),MAX(0,2-(H64-1)*0.5),IF(H64="No",2,IF(H64="Parcial",1,0))) -> 0 | M64: =IF(ISNUMBER(I64),MAX(0,2-(I64-1)*0.5),IF(I64="No",2,IF(I64="Parcial",1,0))) -> 1 | N64: =IF(ISNUMBER(J64),MAX(0,2-(J64-1)*0.5),IF(J64="No",2,IF(J64="Parcial",1,0))) -> 2 | O64: =IF(ISNUMBER(K64),MAX(0,2-(K64-1)*0.5),IF(K64="No",2,IF(K64="Parcial",1,0))) -> 2 | P64: =COUNTIF(L64:O64,">=1") -> 3 | Q64: =SUM(L64:O64) -> 5 | R64: =IF(Q64>=6,"CRÍTICA",IF(Q64>=4,"ALTA",IF(Q64>=2,"MEDIA","BAJA"))) -> ALTA | S64: =IF(R64="CRÍTICA","0-3 meses",IF(R64="ALTA","3-6 meses",IF(R64="MEDIA","6-9 meses","9-12 meses"))) -> 3-6 meses | T64: B, C, D | U64: Sin clasificación por criticidad, se asignan los mismos (o insuficientes) controles a sistemas con muy distinto nivel de riesgo. | V64: Clasificar los sistemas de información según criticidad e impacto en caso de indisponibilidad o compromiso. | W64: TI | X64: Sí / Cumple
B65: M3 · Gobernanza Tecnológica | C65: TA4 | D65: II. Inventario y gestión de activos tecnológicos | E65: Gestión del ciclo de vida de los activos tecnológicos (adquisición, operación, baja) | F65: EGSI | G65: A.5.10 Uso aceptable de los activos / A.5.11 Devolución de activos / A.7.14 Eliminación segura de equipos | H65: Sí | I65: No | J65: Parcial | K65: No | L65: =IF(ISNUMBER(H65),MAX(0,2-(H65-1)*0.5),IF(H65="No",2,IF(H65="Parcial",1,0))) -> 0 | M65: =IF(ISNUMBER(I65),MAX(0,2-(I65-1)*0.5),IF(I65="No",2,IF(I65="Parcial",1,0))) -> 2 | N65: =IF(ISNUMBER(J65),MAX(0,2-(J65-1)*0.5),IF(J65="No",2,IF(J65="Parcial",1,0))) -> 1 | O65: =IF(ISNUMBER(K65),MAX(0,2-(K65-1)*0.5),IF(K65="No",2,IF(K65="Parcial",1,0))) -> 2 | P65: =COUNTIF(L65:O65,">=1") -> 3 | Q65: =SUM(L65:O65) -> 5 | R65: =IF(Q65>=6,"CRÍTICA",IF(Q65>=4,"ALTA",IF(Q65>=2,"MEDIA","BAJA"))) -> ALTA | S65: =IF(R65="CRÍTICA","0-3 meses",IF(R65="ALTA","3-6 meses",IF(R65="MEDIA","6-9 meses","9-12 meses"))) -> 3-6 meses | T65: B, C, D | U65: Equipos dados de baja sin procedimiento seguro pueden filtrar datos personales almacenados en ellos. | V65: Definir el procedimiento de ciclo de vida de activos, incluyendo borrado seguro previo a la baja o reasignación. | W65: TI | X65: Sí / Cumple
B66: M3 · Gobernanza Tecnológica | C66: SI1 | D66: III. Sistemas de información y bases de datos | E66: Sistemas de información documentados (arquitectura, flujos de datos, usuarios) | F66: EGSI | G66: A.5.9 / A.8.9 Gestión de la configuración | H66: Sí | I66: Parcial | J66: No | K66: No | L66: =IF(ISNUMBER(H66),MAX(0,2-(H66-1)*0.5),IF(H66="No",2,IF(H66="Parcial",1,0))) -> 0 | M66: =IF(ISNUMBER(I66),MAX(0,2-(I66-1)*0.5),IF(I66="No",2,IF(I66="Parcial",1,0))) -> 1 | N66: =IF(ISNUMBER(J66),MAX(0,2-(J66-1)*0.5),IF(J66="No",2,IF(J66="Parcial",1,0))) -> 2 | O66: =IF(ISNUMBER(K66),MAX(0,2-(K66-1)*0.5),IF(K66="No",2,IF(K66="Parcial",1,0))) -> 2 | P66: =COUNTIF(L66:O66,">=1") -> 3 | Q66: =SUM(L66:O66) -> 5 | R66: =IF(Q66>=6,"CRÍTICA",IF(Q66>=4,"ALTA",IF(Q66>=2,"MEDIA","BAJA"))) -> ALTA | S66: =IF(R66="CRÍTICA","0-3 meses",IF(R66="ALTA","3-6 meses",IF(R66="MEDIA","6-9 meses","9-12 meses"))) -> 3-6 meses | T66: B, C, D | U66: Sistemas no documentados dependen del conocimiento tácito de una persona y son difíciles de asegurar o auditar. | V66: Documentar la arquitectura, flujos de datos y usuarios de los sistemas de información institucionales. | W66: TI | X66: Sí / Cumple
B67: M3 · Gobernanza Tecnológica | C67: SI2 | D67: III. Sistemas de información y bases de datos | E67: Integración entre los sistemas de información documentada | F67: EGSI | G67: A.8.9 Gestión de la configuración / A.5.9 | H67: No | I67: Parcial | J67: Parcial | K67: No | L67: =IF(ISNUMBER(H67),MAX(0,2-(H67-1)*0.5),IF(H67="No",2,IF(H67="Parcial",1,0))) -> 2 | M67: =IF(ISNUMBER(I67),MAX(0,2-(I67-1)*0.5),IF(I67="No",2,IF(I67="Parcial",1,0))) -> 1 | N67: =IF(ISNUMBER(J67),MAX(0,2-(J67-1)*0.5),IF(J67="No",2,IF(J67="Parcial",1,0))) -> 1 | O67: =IF(ISNUMBER(K67),MAX(0,2-(K67-1)*0.5),IF(K67="No",2,IF(K67="Parcial",1,0))) -> 2 | P67: =COUNTIF(L67:O67,">=1") -> 4 | Q67: =SUM(L67:O67) -> 6 | R67: =IF(Q67>=6,"CRÍTICA",IF(Q67>=4,"ALTA",IF(Q67>=2,"MEDIA","BAJA"))) -> CRÍTICA | S67: =IF(R67="CRÍTICA","0-3 meses",IF(R67="ALTA","3-6 meses",IF(R67="MEDIA","6-9 meses","9-12 meses"))) -> 0-3 meses | T67: A, B, C, D | U67: Integraciones no documentadas generan puntos ciegos de seguridad y dificultan detectar fugas de datos entre sistemas. | V67: Documentar las integraciones existentes (APIs, exportaciones, sincronizaciones) entre sistemas. | W67: TI | X67: Sí / Cumple
B68: M3 · Gobernanza Tecnológica | C68: SI3 | D68: III. Sistemas de información y bases de datos | E68: Controles de acceso basados en roles (RBAC) o perfiles de usuario | F68: EGSI | G68: A.5.15 Control de acceso / A.8.2 Derechos de acceso privilegiado / A.8.3 Restricción de acceso a la información | H68: Parcial | I68: No | J68: No | K68: No | L68: =IF(ISNUMBER(H68),MAX(0,2-(H68-1)*0.5),IF(H68="No",2,IF(H68="Parcial",1,0))) -> 1 | M68: =IF(ISNUMBER(I68),MAX(0,2-(I68-1)*0.5),IF(I68="No",2,IF(I68="Parcial",1,0))) -> 2 | N68: =IF(ISNUMBER(J68),MAX(0,2-(J68-1)*0.5),IF(J68="No",2,IF(J68="Parcial",1,0))) -> 2 | O68: =IF(ISNUMBER(K68),MAX(0,2-(K68-1)*0.5),IF(K68="No",2,IF(K68="Parcial",1,0))) -> 2 | P68: =COUNTIF(L68:O68,">=1") -> 4 | Q68: =SUM(L68:O68) -> 7 | R68: =IF(Q68>=6,"CRÍTICA",IF(Q68>=4,"ALTA",IF(Q68>=2,"MEDIA","BAJA"))) -> CRÍTICA | S68: =IF(R68="CRÍTICA","0-3 meses",IF(R68="ALTA","3-6 meses",IF(R68="MEDIA","6-9 meses","9-12 meses"))) -> 0-3 meses | T68: A, B, C, D | U68: Sin control de acceso basado en roles, cualquier usuario puede ver o modificar datos personales fuera de su función, violando el principio de mínimo privilegio. | V68: Implementar perfiles de acceso por rol en todos los sistemas que traten datos personales, con revisión periódica de permisos. | W68: TI | X68: Sí / Cumple
B69: M3 · Gobernanza Tecnológica | C69: SI4 | D69: III. Sistemas de información y bases de datos | E69: Registro de logs de auditoría en los sistemas de información (accesos, cambios, consultas) | F69: EGSI | G69: A.8.15 Registro (logging) / A.8.16 Actividades de monitoreo | H69: Sí | I69: Parcial | J69: Parcial | K69: No | L69: =IF(ISNUMBER(H69),MAX(0,2-(H69-1)*0.5),IF(H69="No",2,IF(H69="Parcial",1,0))) -> 0 | M69: =IF(ISNUMBER(I69),MAX(0,2-(I69-1)*0.5),IF(I69="No",2,IF(I69="Parcial",1,0))) -> 1 | N69: =IF(ISNUMBER(J69),MAX(0,2-(J69-1)*0.5),IF(J69="No",2,IF(J69="Parcial",1,0))) -> 1 | O69: =IF(ISNUMBER(K69),MAX(0,2-(K69-1)*0.5),IF(K69="No",2,IF(K69="Parcial",1,0))) -> 2 | P69: =COUNTIF(L69:O69,">=1") -> 3 | Q69: =SUM(L69:O69) -> 4 | R69: =IF(Q69>=6,"CRÍTICA",IF(Q69>=4,"ALTA",IF(Q69>=2,"MEDIA","BAJA"))) -> ALTA | S69: =IF(R69="CRÍTICA","0-3 meses",IF(R69="ALTA","3-6 meses",IF(R69="MEDIA","6-9 meses","9-12 meses"))) -> 3-6 meses | T69: B, C, D | U69: Sin logs, ante un incidente es imposible determinar qué datos fueron accedidos, por quién y cuándo. | V69: Habilitar el registro de logs de acceso y cambios en los sistemas críticos, con retención y revisión periódica. | W69: TI | X69: Sí / Cumple
... B85: M3 · Gobernanza Tecnológica | C85: CN4 | D85: VI. Normativa y cumplimiento tecnológico nacional | E85: Revisión periódica del cumplimiento normativo tecnológico (auditorías TI) | F85: EGSI / LOPDP | G85: Cláusula 9.2 Auditoría interna | H85: No | I85: Sí | J85: Parcial | K85: No | L85: =IF(ISNUMBER(H85),MAX(0,2-(H85-1)*0.5),IF(H85="No",2,IF(H85="Parcial",1,0))) -> 2 | M85: =IF(ISNUMBER(I85),MAX(0,2-(I85-1)*0.5),IF(I85="No",2,IF(I85="Parcial",1,0))) -> 0 | N85: =IF(ISNUMBER(J85),MAX(0,2-(J85-1)*0.5),IF(J85="No",2,IF(J85="Parcial",1,0))) -> 1 | O85: =IF(ISNUMBER(K85),MAX(0,2-(K85-1)*0.5),IF(K85="No",2,IF(K85="Parcial",1,0))) -> 2 | P85: =COUNTIF(L85:O85,">=1") -> 3 | Q85: =SUM(L85:O85) -> 5 | R85: =IF(Q85>=6,"CRÍTICA",IF(Q85>=4,"ALTA",IF(Q85>=2,"MEDIA","BAJA"))) -> ALTA | S85: =IF(R85="CRÍTICA","0-3 meses",IF(R85="ALTA","3-6 meses",IF(R85="MEDIA","6-9 meses","9-12 meses"))) -> 3-6 meses | T85: A, C, D | U85: Sin auditoría TI periódica, el cumplimiento tecnológico se deteriora silenciosamente entre autoevaluaciones. | V85: Incluir el componente tecnológico dentro del plan anual de auditoría interna de cumplimiento (ver Módulo 1, F2). | W85: TI + Auditoría/Dirección | X85: Sí / Cumple

Sheet Resumen Ejecutivo
B2: RESUMEN EJECUTIVO DE BRECHAS
B4: 1. BRECHAS POR MÓDULO Y PRIORIDAD
B5: Módulo | C5: CRÍTICA | D5: ALTA | E5: MEDIA | F5: BAJA | G5: Total criterios
B6: M1 · Cumplimiento LOPDP/RGLOPDP | C6: =COUNTIFS('Matriz Consolidada'!$B$4:$B$85,$B6,'Matriz Consolidada'!$R$4:$R$85,C$5) -> 14 | D6: =COUNTIFS('Matriz Consolidada'!$B$4:$B$85,$B6,'Matriz Consolidada'!$R$4:$R$85,D$5) -> 11 | E6: =COUNTIFS('Matriz Consolidada'!$B$4:$B$85,$B6,'Matriz Consolidada'!$R$4:$R$85,E$5) -> 3 | F6: =COUNTIFS('Matriz Consolidada'!$B$4:$B$85,$B6,'Matriz Consolidada'!$R$4:$R$85,F$5) -> 1 | G6: =SUM(C6:F6) -> 29
B7: M2 · Madurez Institucional | C7: =COUNTIFS('Matriz Consolidada'!$B$4:$B$85,$B7,'Matriz Consolidada'!$R$4:$R$85,C$5) -> 17 | D7: =COUNTIFS('Matriz Consolidada'!$B$4:$B$85,$B7,'Matriz Consolidada'!$R$4:$R$85,D$5) -> 8 | E7: =COUNTIFS('Matriz Consolidada'!$B$4:$B$85,$B7,'Matriz Consolidada'!$R$4:$R$85,E$5) -> 0 | F7: =COUNTIFS('Matriz Consolidada'!$B$4:$B$85,$B7,'Matriz Consolidada'!$R$4:$R$85,F$5) -> 0 | G7: =SUM(C7:F7) -> 25
B8: M3 · Gobernanza Tecnológica | C8: =COUNTIFS('Matriz Consolidada'!$B$4:$B$85,$B8,'Matriz Consolidada'!$R$4:$R$85,C$5) -> 10 | D8: =COUNTIFS('Matriz Consolidada'!$B$4:$B$85,$B8,'Matriz Consolidada'!$R$4:$R$85,D$5) -> 15 | E8: =COUNTIFS('Matriz Consolidada'!$B$4:$B$85,$B8,'Matriz Consolidada'!$R$4:$R$85,E$5) -> 3 | F8: =COUNTIFS('Matriz Consolidada'!$B$4:$B$85,$B8,'Matriz Consolidada'!$R$4:$R$85,F$5) -> 0 | G8: =SUM(C8:F8) -> 28
B9: TOTAL | C9: =SUM(C6:C8) -> 41 | D9: =SUM(D6:D8) -> 34 | E9: =SUM(E6:E8) -> 6 | F9: =SUM(F6:F8) -> 1 | G9: =SUM(G6:G8) -> 82
B12: 2. BRECHAS ABIERTAS POR INSTITUCIÓN Y MÓDULO (criterios con Pts ≥ 1)
B13: Módulo | C13: Institución A | D13: Institución B | E13: Institución C | F13: Institución D | G13: Total criterios del módulo
B14: M1 · Cumplimiento LOPDP/RGLOPDP | C14: =COUNTIFS('Matriz Consolidada'!$B$4:$B$85,$B14,'Matriz Consolidada'!$L$4:$L$85,">=1") -> 20 | D14: =COUNTIFS('Matriz Consolidada'!$B$4:$B$85,$B14,'Matriz Consolidada'!$M$4:$M$85,">=1") -> 21 | E14: =COUNTIFS('Matriz Consolidada'!$B$4:$B$85,$B14,'Matriz Consolidada'!$N$4:$N$85,">=1") -> 27 | F14: =COUNTIFS('Matriz Consolidada'!$B$4:$B$85,$B14,'Matriz Consolidada'!$O$4:$O$85,">=1") -> 27 | G14: =COUNTIF('Matriz Consolidada'!$B$4:$B$85,$B14) -> 29
B15: M2 · Madurez Institucional | C15: =COUNTIFS('Matriz Consolidada'!$B$4:$B$85,$B15,'Matriz Consolidada'!$L$4:$L$85,">=1") -> 19 | D15: =COUNTIFS('Matriz Consolidada'!$B$4:$B$85,$B15,'Matriz Consolidada'!$M$4:$M$85,">=1") -> 25 | E15: =COUNTIFS('Matriz Consolidada'!$B$4:$B$85,$B15,'Matriz Consolidada'!$N$4:$N$85,">=1") -> 23 | F15: =COUNTIFS('Matriz Consolidada'!$B$4:$B$85,$B15,'Matriz Consolidada'!$O$4:$O$85,">=1") -> 25 | G15: =COUNTIF('Matriz Consolidada'!$B$4:$B$85,$B15) -> 25
B16: M3 · Gobernanza Tecnológica | C16: =COUNTIFS('Matriz Consolidada'!$B$4:$B$85,$B16,'Matriz Consolidada'!$L$4:$L$85,">=1") -> 10 | D16: =COUNTIFS('Matriz Consolidada'!$B$4:$B$85,$B16,'Matriz Consolidada'!$M$4:$M$85,">=1") -> 22 | E16: =COUNTIFS('Matriz Consolidada'!$B$4:$B$85,$B16,'Matriz Consolidada'!$N$4:$N$85,">=1") -> 27 | F16: =COUNTIFS('Matriz Consolidada'!$B$4:$B$85,$B16,'Matriz Consolidada'!$O$4:$O$85,">=1") -> 28 | G16: =COUNTIF('Matriz Consolidada'!$B$4:$B$85,$B16) -> 28
B19: 3. ÍNDICE DE CUMPLIMIENTO ACTUAL VS. META (100% LOPDP)
B20: Institución | C20: Módulo 1 (% actual) | D20: Módulo 2 (% madurez) | E20: Módulo 3 (% actual) | F20: Índice global (% actual) | G20: Meta | H20: Brecha a cerrar (pts %)
B21: Institución A | C21: 0.44827586 | D21: 0.488 | E21: 0.71428571 | F21: 0.55018719 | G21: 1 | H21: =G21-F21 -> 0.44981281
B22: Institución B | C22: 0.31034483 | D22: 0.328 | E22: 0.42857143 | F22: 0.35563875 | G22: 1 | H22: =G22-F22 -> 0.64436125
B23: Institución C | C23: 0.31034483 | D23: 0.376 | E23: 0.26785714 | F23: 0.31806732 | G23: 1 | H23: =G23-F23 -> 0.68193268
B24: Institución D | C24: 0.12068966 | D24: 0.216 | E24: 0.017857143 | F24: 0.11818227 | G24: 1 | H24: =G24-F24 -> 0.88181773

Sheet Hoja de Ruta_100pct
B2: HOJA DE RUTA CONSOLIDADA HACIA EL 100% DE CUMPLIMIENTO LOPDP
B3: Cronograma de cierre de brechas por tramo de prioridad, para las 4 instituciones evaluadas
B5: TOTAL DE CRITERIOS EVALUADOS POR EL MODELO | C5: 82
B7: Tramo (plazo sugerido) | C7: Criterios a cerrar Institución A | D7: Criterios a cerrar Institución B | E7: Criterios a cerrar Institución C | F7: Criterios a cerrar Institución D | G7: % cumplimiento proyectado (promedio 4 instituciones)
B8: 0-3 meses (prioridad CRÍTICA) | C8: =COUNTIFS('Matriz Consolidada'!$S$4:$S$85,"0-3 meses",'Matriz Consolidada'!$L$4:$L$85,">=1") -> 38 | D8: =COUNTIFS('Matriz Consolidada'!$S$4:$S$85,"0-3 meses",'Matriz Consolidada'!$M$4:$M$85,">=1") -> 41 | E8: =COUNTIFS('Matriz Consolidada'!$S$4:$S$85,"0-3 meses",'Matriz Consolidada'!$N$4:$N$85,">=1") -> 41 | F8: =COUNTIFS('Matriz Consolidada'!$S$4:$S$85,"0-3 meses",'Matriz Consolidada'!$O$4:$O$85,">=1") -> 40 | G8: =AVERAGE(((82-(SUM('Resumen Ejecutivo'!C14:C16)-SUM(C$8:C8)))/82),((82-(SUM('Resumen Ejecutivo'!D14:D16)-SUM(D$8:D8)))/82),((82-(SUM('Resumen Ejecutivo'!E14:E16)-SUM(E$8:E8)))/82),((82-(SUM('Resumen Ejecutivo'!F14:F16)-SUM(F$8:F8)))/82)) -> 0.65243902
B9: 3-6 meses (prioridad ALTA) | C9: =COUNTIFS('Matriz Consolidada'!$S$4:$S$85,"3-6 meses",'Matriz Consolidada'!$L$4:$L$85,">=1") -> 10 | D9: =COUNTIFS('Matriz Consolidada'!$S$4:$S$85,"3-6 meses",'Matriz Consolidada'!$M$4:$M$85,">=1") -> 27 | E9: =COUNTIFS('Matriz Consolidada'!$S$4:$S$85,"3-6 meses",'Matriz Consolidada'!$N$4:$N$85,">=1") -> 32 | F9: =COUNTIFS('Matriz Consolidada'!$S$4:$S$85,"3-6 meses",'Matriz Consolidada'!$O$4:$O$85,">=1") -> 33 | G9: =AVERAGE(((82-(SUM('Resumen Ejecutivo'!C14:C16)-SUM(C$8:C9)))/82),((82-(SUM('Resumen Ejecutivo'!D14:D16)-SUM(D$8:D9)))/82),((82-(SUM('Resumen Ejecutivo'!E14:E16)-SUM(E$8:E9)))/82),((82-(SUM('Resumen Ejecutivo'!F14:F16)-SUM(F$8:F9)))/82)) -> 0.96341463
B10: 6-9 meses (prioridad MEDIA) | C10: =COUNTIFS('Matriz Consolidada'!$S$4:$S$85,"6-9 meses",'Matriz Consolidada'!$L$4:$L$85,">=1") -> 1 | D10: =COUNTIFS('Matriz Consolidada'!$S$4:$S$85,"6-9 meses",'Matriz Consolidada'!$M$4:$M$85,">=1") -> 0 | E10: =COUNTIFS('Matriz Consolidada'!$S$4:$S$85,"6-9 meses",'Matriz Consolidada'!$N$4:$N$85,">=1") -> 4 | F10: =COUNTIFS('Matriz Consolidada'!$S$4:$S$85,"6-9 meses",'Matriz Consolidada'!$O$4:$O$85,">=1") -> 6 | G10: =AVERAGE(((82-(SUM('Resumen Ejecutivo'!C14:C16)-SUM(C$8:C10)))/82),((82-(SUM('Resumen Ejecutivo'!D14:D16)-SUM(D$8:D10)))/82),((82-(SUM('Resumen Ejecutivo'!E14:E16)-SUM(E$8:E10)))/82),((82-(SUM('Resumen Ejecutivo'!F14:F16)-SUM(F$8:F10)))/82)) -> 0.99695122
B11: 9-12 meses (prioridad BAJA) | C11: =COUNTIFS('Matriz Consolidada'!$S$4:$S$85,"9-12 meses",'Matriz Consolidada'!$L$4:$L$85,">=1") -> 0 | D11: =COUNTIFS('Matriz Consolidada'!$S$4:$S$85,"9-12 meses",'Matriz Consolidada'!$M$4:$M$85,">=1") -> 0 | E11: =COUNTIFS('Matriz Consolidada'!$S$4:$S$85,"9-12 meses",'Matriz Consolidada'!$N$4:$N$85,">=1") -> 0 | F11: =COUNTIFS('Matriz Consolidada'!$S$4:$S$85,"9-12 meses",'Matriz Consolidada'!$O$4:$O$85,">=1") -> 1 | G11: =AVERAGE(((82-(SUM('Resumen Ejecutivo'!C14:C16)-SUM(C$8:C11)))/82),((82-(SUM('Resumen Ejecutivo'!D14:D16)-SUM(D$8:D11)))/82),((82-(SUM('Resumen Ejecutivo'!E14:E16)-SUM(E$8:E11)))/82),((82-(SUM('Resumen Ejecutivo'!F14:F16)-SUM(F$8:F11)))/82)) -> 1

Sheet Mapa ISO27001
B2: TRAZABILIDAD LOPDP - ISO/IEC 27001:2022
B4: Control ISO/IEC 27001:2022 (Anexo A / cláusula) | C4: N° criterios asociados | D4: Inst. A con brecha | E4: Inst. B con brecha | F4: Inst. C con brecha | G4: Inst. D con brecha
B5: A.5.9 Inventario de información y otros activos asociados | C5: =COUNTIF('Matriz Consolidada'!$G$4:$G$85,"A.5.9 Inventario de información y otros activos asociados") -> 3 | D5: =COUNTIFS('Matriz Consolidada'!$G$4:$G$85,"A.5.9 Inventario de información y otros activos asociados",'Matriz Consolidada'!$L$4:$L$85,">=1") -> 2 | E5: =COUNTIFS('Matriz Consolidada'!$G$4:$G$85,"A.5.9 Inventario de información y otros activos asociados",'Matriz Consolidada'!$M$4:$M$85,">=1") -> 2 | F5: =COUNTIFS('Matriz Consolidada'!$G$4:$G$85,"A.5.9 Inventario de información y otros activos asociados",'Matriz Consolidada'!$N$4:$N$85,">=1") -> 2 | G5: =COUNTIFS('Matriz Consolidada'!$G$4:$G$85,"A.5.9 Inventario de información y otros activos asociados",'Matriz Consolidada'!$O$4:$O$85,">=1") -> 3
B6: A.5.12 Clasificación de la información | C6: =COUNTIF('Matriz Consolidada'!$G$4:$G$85,"A.5.12 Clasificación de la información") -> 2 | D6: =COUNTIFS('Matriz Consolidada'!$G$4:$G$85,"A.5.12 Clasificación de la información",'Matriz Consolidada'!$L$4:$L$85,">=1") -> 0 | E6: =COUNTIFS('Matriz Consolidada'!$G$4:$G$85,"A.5.12 Clasificación de la información",'Matriz Consolidada'!$M$4:$M$85,">=1") -> 1 | F6: =COUNTIFS('Matriz Consolidada'!$G$4:$G$85,"A.5.12 Clasificación de la información",'Matriz Consolidada'!$N$4:$N$85,">=1") -> 1 | G6: =COUNTIFS('Matriz Consolidada'!$G$4:$G$85,"A.5.12 Clasificación de la información",'Matriz Consolidada'!$O$4:$O$85,">=1") -> 2
B7: A.5.33 Protección de los registros | C7: =COUNTIF('Matriz Consolidada'!$G$4:$G$85,"A.5.33 Protección de los registros") -> 1 | D7: =COUNTIFS('Matriz Consolidada'!$G$4:$G$85,"A.5.33 Protección de los registros",'Matriz Consolidada'!$L$4:$L$85,">=1") -> 0 | E7: =COUNTIFS('Matriz Consolidada'!$G$4:$G$85,"A.5.33 Protección de los registros",'Matriz Consolidada'!$M$4:$M$85,">=1") -> 0 | F7: =COUNTIFS('Matriz Consolidada'!$G$4:$G$85,"A.5.33 Protección de los registros",'Matriz Consolidada'!$N$4:$N$85,">=1") -> 1 | G7: =COUNTIFS('Matriz Consolidada'!$G$4:$G$85,"A.5.33 Protección de los registros",'Matriz Consolidada'!$O$4:$O$85,">=1") -> 1
B8: A.5.9 / A.8.1 Dispositivos de usuario final | C8: =COUNTIF('Matriz Consolidada'!$G$4:$G$85,"A.5.9 / A.8.1 Dispositivos de usuario final") -> 1 | D8: =COUNTIFS('Matriz Consolidada'!$G$4:$G$85,"A.5.9 / A.8.1 Dispositivos de usuario final",'Matriz Consolidada'!$L$4:$L$85,">=1") -> 1 | E8: =COUNTIFS('Matriz Consolidada'!$G$4:$G$85,"A.5.9 / A.8.1 Dispositivos de usuario final",'Matriz Consolidada'!$M$4:$M$85,">=1") -> 1 | F8: =COUNTIFS('Matriz Consolidada'!$G$4:$G$85,"A.5.9 / A.8.1 Dispositivos de usuario final",'Matriz Consolidada'!$N$4:$N$85,">=1") -> 1 | G8: =COUNTIFS('Matriz Consolidada'!$G$4:$G$85,"A.5.9 / A.8.1 Dispositivos de usuario final",'Matriz Consolidada'!$O$4:$O$85,">=1") -> 1
B9: A.5.34 Privacidad y protección de datos personales (PII) | C9: =COUNTIF('Matriz Consolidada'!$G$4:$G$85,"A.5.34 Privacidad y protección de datos personales (PII)") -> 9 | D9: =COUNTIFS('Matriz Consolidada'!$G$4:$G$85,"A.5.34 Privacidad y protección de datos personales (PII)",'Matriz Consolidada'!$L$4:$L$85,">=1") -> 7 | E9: =COUNTIFS('Matriz Consolidada'!$G$4:$G$85,"A.5.34 Privacidad y protección de datos personales (PII)",'Matriz Consolidada'!$M$4:$M$85,">=1") -> 6 | F9: =COUNTIFS('Matriz Consolidada'!$G$4:$G$85,"A.5.34 Privacidad y protección de datos personales (PII)",'Matriz Consolidada'!$N$4:$N$85,">=1") -> 9 | G9: =COUNTIFS('Matriz Consolidada'!$G$4:$G$85,"A.5.34 Privacidad y protección de datos personales (PII)",'Matriz Consolidada'!$O$4:$O$85,">=1") -> 9
B10: A.5.1 Políticas de seguridad de la información | C10: =COUNTIF('Matriz Consolidada'!$G$4:$G$85,"A.5.1 Políticas de seguridad de la información") -> 3 | D10: =COUNTIFS('Matriz Consolidada'!$G$4:$G$85,"A.5.1 Políticas de seguridad de la información",'Matriz Consolidada'!$L$4:$L$85,">=1") -> 3 | E10: =COUNTIFS('Matriz Consolidada'!$G$4:$G$85,"A.5.1 Políticas de seguridad de la información",'Matriz Consolidada'!$M$4:$M$85,">=1") -> 1 | F10: =COUNTIFS('Matriz Consolidada'!$G$4:$G$85,"A.5.1 Políticas de seguridad de la información",'Matriz Consolidada'!$N$4:$N$85,">=1") -> 3 | G10: =COUNTIFS('Matriz Consolidada'!$G$4:$G$85,"A.5.1 Políticas de seguridad de la información",'Matriz Consolidada'!$O$4:$O$85,">=1") -> 3
B11: A.5.34 / A.9.1 Monitoreo, medición, análisis y evaluación (cláusula 9.1) | C11: =COUNTIF('Matriz Consolidada'!$G$4:$G$85,"A.5.34 / A.9.1 Monitoreo, medición, análisis y evaluación (cláusula 9.1)") -> 1 | D11: =COUNTIFS('Matriz Consolidada'!$G$4:$G$85,"A.5.34 / A.9.1 Monitoreo, medición, análisis y evaluación (cláusula 9.1)",'Matriz Consolidada'!$L$4:$L$85,">=1") -> 1 | E11: =COUNTIFS('Matriz Consolidada'!$G$4:$G$85,"A.5.34 / A.9.1 Monitoreo, medición, análisis y evaluación (cláusula 9.1)",'Matriz Consolidada'!$M$4:$M$85,">=1") -> 1 | F11: =COUNTIFS('Matriz Consolidada'!$G$4:$G$85,"A.5.34 / A.9.1 Monitoreo, medición, análisis y evaluación (cláusula 9.1)",'Matriz Consolidada'!$N$4:$N$85,">=1") -> 1 | G11: =COUNTIFS('Matriz Consolidada'!$G$4:$G$85,"A.5.34 / A.9.1 Monitoreo, medición, análisis y evaluación (cláusula 9.1)",'Matriz Consolidada'!$O$4:$O$85,">=1") -> 0
B12: A.5.2 Roles y responsabilidades de seguridad de la información | C12: =COUNTIF('Matriz Consolidada'!$G$4:$G$85,"A.5.2 Roles y responsabilidades de seguridad de la información") -> 3 | D12: =COUNTIFS('Matriz Consolidada'!$G$4:$G$85,"A.5.2 Roles y responsabilidades de seguridad de la información",'Matriz Consolidada'!$L$4:$L$85,">=1") -> 2 | E12: =COUNTIFS('Matriz Consolidada'!$G$4:$G$85,"A.5.2 Roles y responsabilidades de seguridad de la información",'Matriz Consolidada'!$M$4:$M$85,">=1") -> 2 | F12: =COUNTIFS('Matriz Consolidada'!$G$4:$G$85,"A.5.2 Roles y responsabilidades de seguridad de la información",'Matriz Consolidada'!$N$4:$N$85,">=1") -> 3 | G12: =COUNTIFS('Matriz Consolidada'!$G$4:$G$85,"A.5.2 Roles y responsabilidades de seguridad de la información",'Matriz Consolidada'!$O$4:$O$85,">=1") -> 2
B13: A.5.20 Abordar la seguridad de la información en los acuerdos con proveedores | C13: =COUNTIF('Matriz Consolidada'!$G$4:$G$85,"A.5.20 Abordar la seguridad de la información en los acuerdos con proveedores") -> 3 | D13: =COUNTIFS('Matriz Consolidada'!$G$4:$G$85,"A.5.20 Abordar la seguridad de la información en los acuerdos con proveedores",'Matriz Consolidada'!$L$4:$L$85,">=1") -> 1 | E13: =COUNTIFS('Matriz Consolidada'!$G$4:$G$85,"A.5.20 Abordar la seguridad de la información en los acuerdos con proveedores",'Matriz Consolidada'!$M$4:$M$85,">=1") -> 3 | F13: =COUNTIFS('Matriz Consolidada'!$G$4:$G$85,"A.5.20 Abordar la seguridad de la información en los acuerdos con proveedores",'Matriz Consolidada'!$N$4:$N$85,">=1") -> 3 | G13: =COUNTIFS('Matriz Consolidada'!$G$4:$G$85,"A.5.20 Abordar la seguridad de la información en los acuerdos con proveedores",'Matriz Consolidada'!$O$4:$O$85,">=1") -> 3
B14: A.6.6 Acuerdos de confidencialidad o no divulgación | C14: =COUNTIF('Matriz Consolidada'!$G$4:$G$85,"A.6.6 Acuerdos de confidencialidad o no divulgación") -> 1 | D14: =COUNTIFS('Matriz Consolidada'!$G$4:$G$85,"A.6.6 Acuerdos de confidencialidad o no divulgación",'Matriz Consolidada'!$L$4:$L$85,">=1") -> 0 | E14: =COUNTIFS('Matriz Consolidada'!$G$4:$G$85,"A.6.6 Acuerdos de confidencialidad o no divulgación",'Matriz Consolidada'!$M$4:$M$85,">=1") -> 0 | F14: =COUNTIFS('Matriz Consolidada'!$G$4:$G$85,"A.6.6 Acuerdos de confidencialidad o no divulgación",'Matriz Consolidada'!$N$4:$N$85,">=1") -> 1 | G14: =COUNTIFS('Matriz Consolidada'!$G$4:$G$85,"A.6.6 Acuerdos de confidencialidad o no divulgación",'Matriz Consolidada'!$O$4:$O$85,">=1") -> 1
B15: A.5.22 Seguimiento, revisión y gestión de cambios en los servicios de proveedores | C15: =COUNTIF('Matriz Consolidada'!$G$4:$G$85,"A.5.22 Seguimiento, revisión y gestión de cambios en los servicios de proveedores") -> 2 | D15: =COUNTIFS('Matriz Consolidada'!$G$4:$G$85,"A.5.22 Seguimiento, revisión y gestión de cambios en los servicios de proveedores",'Matriz Consolidada'!$L$4:$L$85,">=1") -> 0 | E15: =COUNTIFS('Matriz Consolidada'!$G$4:$G$85,"A.5.22 Seguimiento, revisión y gestión de cambios en los servicios de proveedores",'Matriz Consolidada'!$M$4:$M$85,">=1") -> 2 | F15: =COUNTIFS('Matriz Consolidada'!$G$4:$G$85,"A.5.22 Seguimiento, revisión y gestión de cambios en los servicios de proveedores",'Matriz Consolidada'!$N$4:$N$85,">=1") -> 2 | G15: =COUNTIFS('Matriz Consolidada'!$G$4:$G$85,"A.5.22 Seguimiento, revisión y gestión de cambios en los servicios de proveedores",'Matriz Consolidada'!$O$4:$O$85,">=1") -> 2
B16: A.5.1 Políticas de seguridad de la información / Cláusula 8 Operación | C16: =COUNTIF('Matriz Consolidada'!$G$4:$G$85,"A.5.1 Políticas de seguridad de la información / Cláusula 8 Operación") -> 1 | D16: =COUNTIFS('Matriz Consolidada'!$G$4:$G$85,"A.5.1 Políticas de seguridad de la información / Cláusula 8 Operación",'Matriz Consolidada'!$L$4:$L$85,">=1") -> 0 | E16: =COUNTIFS('Matriz Consolidada'!$G$4:$G$85,"A.5.1 Políticas de seguridad de la información / Cláusula 8 Operación",'Matriz Consolidada'!$M$4:$M$85,">=1") -> 1 | F16: =COUNTIFS('Matriz Consolidada'!$G$4:$G$85,"A.5.1 Políticas de seguridad de la información / Cláusula 8 Operación",'Matriz Consolidada'!$N$4:$N$85,">=1") -> 1 | G16: =COUNTIFS('Matriz Consolidada'!$G$4:$G$85,"A.5.1 Políticas de seguridad de la información / Cláusula 8 Operación",'Matriz Consolidada'!$O$4:$O$85,">=1") -> 1
B17: Cláusula 6.1 / 8.2 Evaluación de riesgos de seguridad de la información | C17: =COUNTIF('Matriz Consolidada'!$G$4:$G$85,"Cláusula 6.1 / 8.2 Evaluación de riesgos de seguridad de la información") -> 2 | D17: =COUNTIFS('Matriz Consolidada'!$G$4:$G$85,"Cláusula 6.1 / 8.2 Evaluación de riesgos de seguridad de la información",'Matriz Consolidada'!$L$4:$L$85,">=1") -> 1 | E17: =COUNTIFS('Matriz Consolidada'!$G$4:$G$85,"Cláusula 6.1 / 8.2 Evaluación de riesgos de seguridad de la información",'Matriz Consolidada'!$M$4:$M$85,">=1") -> 2 | F17: =COUNTIFS('Matriz Consolidada'!$G$4:$G$85,"Cláusula 6.1 / 8.2 Evaluación de riesgos de seguridad de la información",'Matriz Consolidada'!$N$4:$N$85,">=1") -> 2 | G17: =COUNTIFS('Matriz Consolidada'!$G$4:$G$85,"Cláusula 6.1 / 8.2 Evaluación de riesgos de seguridad de la información",'Matriz Consolidada'!$O$4:$O$85,">=1") -> 2
B18: Cláusula 8.2 Evaluación de riesgos de seguridad de la información | C18: =COUNTIF('Matriz Consolidada'!$G$4:$G$85,"Cláusula 8.2 Evaluación de riesgos de seguridad de la información") -> 2 | D18: =COUNTIFS('Matriz Consolidada'!$G$4:$G$85,"Cláusula 8.2 Evaluación de riesgos de seguridad de la información",'Matriz Consolidada'!$L$4:$L$85,">=1") -> 2 | E18: =COUNTIFS('Matriz Consolidada'!$G$4:$G$85,"Cláusula 8.2 Evaluación de riesgos de seguridad de la información",'Matriz Consolidada'!$M$4:$M$85,">=1") -> 2 | F18: =COUNTIFS('Matriz Consolidada'!$G$4:$G$85,"Cláusula 8.2 Evaluación de riesgos de seguridad de la información",'Matriz Consolidada'!$N$4:$N$85,">=1") -> 2 | G18: =COUNTIFS('Matriz Consolidada'!$G$4:$G$85,"Cláusula 8.2 Evaluación de riesgos de seguridad de la información",'Matriz Consolidada'!$O$4:$O$85,">=1") -> 2
B19: A.5.24 Planificación y preparación de la gestión de incidentes / A.6.8 Reporte de eventos | C19: =COUNTIF('Matriz Consolidada'!$G$4:$G$85,"A.5.24 Planificación y preparación de la gestión de incidentes / A.6.8 Reporte de eventos") -> 1 | D19: =COUNTIFS('Matriz Consolidada'!$G$4:$G$85,"A.5.24 Planificación y preparación de la gestión de incidentes / A.6.8 Reporte de eventos",'Matriz Consolidada'!$L$4:$L$85,">=1") -> 1 | E19: =COUNTIFS('Matriz Consolidada'!$G$4:$G$85,"A.5.24 Planificación y preparación de la gestión de incidentes / A.6.8 Reporte de eventos",'Matriz Consolidada'!$M$4:$M$85,">=1") -> 1 | F19: =COUNTIFS('Matriz Consolidada'!$G$4:$G$85,"A.5.24 Planificación y preparación de la gestión de incidentes / A.6.8 Reporte de eventos",'Matriz Consolidada'!$N$4:$N$85,">=1") -> 1 | G19: =COUNTIFS('Matriz Consolidada'!$G$4:$G$85,"A.5.24 Planificación y preparación de la gestión de incidentes / A.6.8 Reporte de eventos",'Matriz Consolidada'!$O$4:$O$85,">=1") -> 1
B20: A.8.8 Gestión de vulnerabilidades técnicas | C20: =COUNTIF('Matriz Consolidada'!$G$4:$G$85,"A.8.8 Gestión de vulnerabilidades técnicas") -> 2 | D20: =COUNTIFS('Matriz Consolidada'!$G$4:$G$85,"A.8.8 Gestión de vulnerabilidades técnicas",'Matriz Consolidada'!$L$4:$L$85,">=1") -> 1 | E20: =COUNTIFS('Matriz Consolidada'!$G$4:$G$85,"A.8.8 Gestión de vulnerabilidades técnicas",'Matriz Consolidada'!$M$4:$M$85,">=1") -> 2 | F20: =COUNTIFS('Matriz Consolidada'!$G$4:$G$85,"A.8.8 Gestión de vulnerabilidades técnicas",'Matriz Consolidada'!$N$4:$N$85,">=1") -> 2 | G20: =COUNTIFS('Matriz Consolidada'!$G$4:$G$85,"A.8.8 Gestión de vulnerabilidades técnicas",'Matriz Consolidada'!$O$4:$O$85,">=1") -> 2
B21: A.8.24 Uso de criptografía / A.8.10 Eliminación de la información | C21: =COUNTIF('Matriz Consolidada'!$G$4:$G$85,"A.8.24 Uso de criptografía / A.8.10 Eliminación de la información") -> 1 | D21: =COUNTIFS('Matriz Consolidada'!$G$4:$G$85,"A.8.24 Uso de criptografía / A.8.10 Eliminación de la información",'Matriz Consolidada'!$L$4:$L$85,">=1") -> 1 | E21: =COUNTIFS('Matriz Consolidada'!$G$4:$G$85,"A.8.24 Uso de criptografía / A.8.10 Eliminación de la información",'Matriz Consolidada'!$M$4:$M$85,">=1") -> 1 | F21: =COUNTIFS('Matriz Consolidada'!$G$4:$G$85,"A.8.24 Uso de criptografía / A.8.10 Eliminación de la información",'Matriz Consolidada'!$N$4:$N$85,">=1") -> 1 | G21: =COUNTIFS('Matriz Consolidada'!$G$4:$G$85,"A.8.24 Uso de criptografía / A.8.10 Eliminación de la información",'Matriz Consolidada'!$O$4:$O$85,">=1") -> 1
B22: A.7.4 Monitoreo de seguridad física | C22: =COUNTIF('Matriz Consolidada'!$G$4:$G$85,"A.7.4 Monitoreo de seguridad física") -> 1 | D22: =COUNTIFS('Matriz Consolidada'!$G$4:$G$85,"A.7.4 Monitoreo de seguridad física",'Matriz Consolidada'!$L$4:$L$85,">=1") -> 1 | E22: =COUNTIFS('Matriz Consolidada'!$G$4:$G$85,"A.7.4 Monitoreo de seguridad física",'Matriz Consolidada'!$M$4:$M$85,">=1") -> 1 | F22: =COUNTIFS('Matriz Consolidada'!$G$4:$G$85,"A.7.4 Monitoreo de seguridad física",'Matriz Consolidada'!$N$4:$N$85,">=1") -> 1 | G22: =COUNTIFS('Matriz Consolidada'!$G$4:$G$85,"A.7.4 Monitoreo de seguridad física",'Matriz Consolidada'!$O$4:$O$85,">=1") -> 1
B23: A.6.3 Concienciación, educación y formación en seguridad de la información | C23: =COUNTIF('Matriz Consolidada'!$G$4:$G$85,"A.6.3 Concienciación, educación y formación en seguridad de la información") -> 3 | D23: =COUNTIFS('Matriz Consolidada'!$G$4:$G$85,"A.6.3 Concienciación, educación y formación en seguridad de la información",'Matriz Consolidada'!$L$4:$L$85,">=1") -> 3 | E23: =COUNTIFS('Matriz Consolidada'!$G$4:$G$85,"A.6.3 Concienciación, educación y formación en seguridad de la información",'Matriz Consolidada'!$M$4:$M$85,">=1") -> 3 | F23: =COUNTIFS('Matriz Consolidada'!$G$4:$G$85,"A.6.3 Concienciación, educación y formación en seguridad de la información",'Matriz Consolidada'!$N$4:$N$85,">=1") -> 3 | G23: =COUNTIFS('Matriz Consolidada'!$G$4:$G$85,"A.6.3 Concienciación, educación y formación en seguridad de la información",'Matriz Consolidada'!$O$4:$O$85,">=1") -> 3
B24: Cláusula 9.2 Auditoría interna | C24: =COUNTIF('Matriz Consolidada'!$G$4:$G$85,"Cláusula 9.2 Auditoría interna") -> 3 | D24: =COUNTIFS('Matriz Consolidada'!$G$4:$G$85,"Cláusula 9.2 Auditoría interna",'Matriz Consolidada'!$L$4:$L$85,">=1") -> 3 | E24: =COUNTIFS('Matriz Consolidada'!$G$4:$G$85,"Cláusula 9.2 Auditoría interna",'Matriz Consolidada'!$M$4:$M$85,">=1") -> 2 | F24: =COUNTIFS('Matriz Consolidada'!$G$4:$G$85,"Cláusula 9.2 Auditoría interna",'Matriz Consolidada'!$N$4:$N$85,">=1") -> 3 | G24: =COUNTIFS('Matriz Consolidada'!$G$4:$G$85,"Cláusula 9.2 Auditoría interna",'Matriz Consolidada'!$O$4:$O$85,">=1") -> 3
B25: A.5.33 Protección de los registros / A.8.10 Eliminación de la información | C25: =COUNTIF('Matriz Consolidada'!$G$4:$G$85,"A.5.33 Protección de los registros / A.8.10 Eliminación de la información") -> 1 | D25: =COUNTIFS('Matriz Consolidada'!$G$4:$G$85,"A.5.33 Protección de los registros / A.8.10 Eliminación de la información",'Matriz Consolidada'!$L$4:$L$85,">=1") -> 1 | E25: =COUNTIFS('Matriz Consolidada'!$G$4:$G$85,"A.5.33 Protección de los registros / A.8.10 Eliminación de la información",'Matriz Consolidada'!$M$4:$M$85,">=1") -> 1 | F25: =COUNTIFS('Matriz Consolidada'!$G$4:$G$85,"A.5.33 Protección de los registros / A.8.10 Eliminación de la información",'Matriz Consolidada'!$N$4:$N$85,">=1") -> 1 | G25: =COUNTIFS('Matriz Consolidada'!$G$4:$G$85,"A.5.33 Protección de los registros / A.8.10 Eliminación de la información",'Matriz Consolidada'!$O$4:$O$85,">=1") -> 1
B26: A.8.29 Pruebas de seguridad en el desarrollo y aceptación / A.5.36 Cumplimiento de políticas | C26: =COUNTIF('Matriz Consolidada'!$G$4:$G$85,"A.8.29 Pruebas de seguridad en el desarrollo y aceptación / A.5.36 Cumplimiento de políticas") -> 1 | D26: =COUNTIFS('Matriz Consolidada'!$G$4:$G$85,"A.8.29 Pruebas de seguridad en el desarrollo y aceptación / A.5.36 Cumplimiento de políticas",'Matriz Consolidada'!$L$4:$L$85,">=1") -> 0 | E26: =COUNTIFS('Matriz Consolidada'!$G$4:$G$85,"A.8.29 Pruebas de seguridad en el desarrollo y aceptación / A.5.36 Cumplimiento de políticas",'Matriz Consolidada'!$M$4:$M$85,">=1") -> 1 | F26: =COUNTIFS('Matriz Consolidada'!$G$4:$G$85,"A.8.29 Pruebas de seguridad en el desarrollo y aceptación / A.5.36 Cumplimiento de políticas",'Matriz Consolidada'!$N$4:$N$85,">=1") -> 1 | G26: =COUNTIFS('Matriz Consolidada'!$G$4:$G$85,"A.8.29 Pruebas de seguridad en el desarrollo y aceptación / A.5.36 Cumplimiento de políticas",'Matriz Consolidada'!$O$4:$O$85,">=1") -> 1
B27: Cláusula 5.1 Liderazgo y compromiso | C27: =COUNTIF('Matriz Consolidada'!$G$4:$G$85,"Cláusula 5.1 Liderazgo y compromiso") -> 2 | D27: =COUNTIFS('Matriz Consolidada'!$G$4:$G$85,"Cláusula 5.1 Liderazgo y compromiso",'Matriz Consolidada'!$L$4:$L$85,">=1") -> 1 | E27: =COUNTIFS('Matriz Consolidada'!$G$4:$G$85,"Cláusula 5.1 Liderazgo y compromiso",'Matriz Consolidada'!$M$4:$M$85,">=1") -> 1 | F27: =COUNTIFS('Matriz Consolidada'!$G$4:$G$85,"Cláusula 5.1 Liderazgo y compromiso",'Matriz Consolidada'!$N$4:$N$85,">=1") -> 2 | G27: =COUNTIFS('Matriz Consolidada'!$G$4:$G$85,"Cláusula 5.1 Liderazgo y compromiso",'Matriz Consolidada'!$O$4:$O$85,">=1") -> 2
B28: Cláusula 7.1 Recursos | C28: =COUNTIF('Matriz Consolidada'!$G$4:$G$85,"Cláusula 7.1 Recursos") -> 1 | D28: =COUNTIFS('Matriz Consolidada'!$G$4:$G$85,"Cláusula 7.1 Recursos",'Matriz Consolidada'!$L$4:$L$85,">=1") -> 0 | E28: =COUNTIFS('Matriz Consolidada'!$G$4:$G$85,"Cláusula 7.1 Recursos",'Matriz Consolidada'!$M$4:$M$85,">=1") -> 1 | F28: =COUNTIFS('Matriz Consolidada'!$G$4:$G$85,"Cláusula 7.1 Recursos",'Matriz Consolidada'!$N$4:$N$85,">=1") -> 1 | G28: =COUNTIFS('Matriz Consolidada'!$G$4:$G$85,"Cláusula 7.1 Recursos",'Matriz Consolidada'!$O$4:$O$85,">=1") -> 1
B29: A.5.37 Procedimientos operativos documentados | C29: =COUNTIF('Matriz Consolidada'!$G$4:$G$85,"A.5.37 Procedimientos operativos documentados") -> 1 | D29: =COUNTIFS('Matriz Consolidada'!$G$4:$G$85,"A.5.37 Procedimientos operativos documentados",'Matriz Consolidada'!$L$4:$L$85,">=1") -> 1 | E29: =COUNTIFS('Matriz Consolidada'!$G$4:$G$85,"A.5.37 Procedimientos operativos documentados",'Matriz Consolidada'!$M$4:$M$85,">=1") -> 1 | F29: =COUNTIFS('Matriz Consolidada'!$G$4:$G$85,"A.5.37 Procedimientos operativos documentados",'Matriz Consolidada'!$N$4:$N$85,">=1") -> 1 | G29: =COUNTIFS('Matriz Consolidada'!$G$4:$G$85,"A.5.37 Procedimientos operativos documentados",'Matriz Consolidada'!$O$4:$O$85,">=1") -> 1
B30: A.5.24 Planificación y preparación de la gestión de incidentes | C30: =COUNTIF('Matriz Consolidada'!$G$4:$G$85,"A.5.24 Planificación y preparación de la gestión de incidentes") -> 2 | D30: =COUNTIFS('Matriz Consolidada'!$G$4:$G$85,"A.5.24 Planificación y preparación de la gestión de incidentes",'Matriz Consolidada'!$L$4:$L$85,">=1") -> 1 | E30: =COUNTIFS('Matriz Consolidada'!$G$4:$G$85,"A.5.24 Planificación y preparación de la gestión de incidentes",'Matriz Consolidada'!$M$4:$M$85,">=1") -> 2 | F30: =COUNTIFS('Matriz Consolidada'!$G$4:$G$85,"A.5.24 Planificación y preparación de la gestión de incidentes",'Matriz Consolidada'!$N$4:$N$85,">=1") -> 2 | G30: =COUNTIFS('Matriz Consolidada'!$G$4:$G$85,"A.5.24 Planificación y preparación de la gestión de incidentes",'Matriz Consolidada'!$O$4:$O$85,">=1") -> 2
B31: Cláusula 10.1 Mejora continua | C31: =COUNTIF('Matriz Consolidada'!$G$4:$G$85,"Cláusula 10.1 Mejora continua") -> 3 | D31: =COUNTIFS('Matriz Consolidada'!$G$4:$G$85,"Cláusula 10.1 Mejora continua",'Matriz Consolidada'!$L$4:$L$85,">=1") -> 3 | E31: =COUNTIFS('Matriz Consolidada'!$G$4:$G$85,"Cláusula 10.1 Mejora continua",'Matriz Consolidada'!$M$4:$M$85,">=1") -> 3 | F31: =COUNTIFS('Matriz Consolidada'!$G$4:$G$85,"Cláusula 10.1 Mejora continua",'Matriz Consolidada'!$N$4:$N$85,">=1") -> 3 | G31: =COUNTIFS('Matriz Consolidada'!$G$4:$G$85,"Cláusula 10.1 Mejora continua",'Matriz Consolidada'!$O$4:$O$85,">=1") -> 3
B32: A.8.25 Ciclo de vida de desarrollo seguro / A.5.34 | C32: =COUNTIF('Matriz Consolidada'!$G$4:$G$85,"A.8.25 Ciclo de vida de desarrollo seguro / A.5.34") -> 2 | D32: =COUNTIFS('Matriz Consolidada'!$G$4:$G$85,"A.8.25 Ciclo de vida de desarrollo seguro / A.5.34",'Matriz Consolidada'!$L$4:$L$85,">=1") -> 2 | E32: =COUNTIFS('Matriz Consolidada'!$G$4:$G$85,"A.8.25 Ciclo de vida de desarrollo seguro / A.5.34",'Matriz Consolidada'!$M$4:$M$85,">=1") -> 2 | F32: =COUNTIFS('Matriz Consolidada'!$G$4:$G$85,"A.8.25 Ciclo de vida de desarrollo seguro / A.5.34",'Matriz Consolidada'!$N$4:$N$85,">=1") -> 1 | G32: =COUNTIFS('Matriz Consolidada'!$G$4:$G$85,"A.8.25 Ciclo de vida de desarrollo seguro / A.5.34",'Matriz Consolidada'!$O$4:$O$85,">=1") -> 2
B33: A.6.4 Proceso disciplinario | C33: =COUNTIF('Matriz Consolidada'!$G$4:$G$85,"A.6.4 Proceso disciplinario") -> 1 | D33: =COUNTIFS('Matriz Consolidada'!$G$4:$G$85,"A.6.4 Proceso disciplinario",'Matriz Consolidada'!$L$4:$L$85,">=1") -> 1 | E33: =COUNTIFS('Matriz Consolidada'!$G$4:$G$85,"A.6.4 Proceso disciplinario",'Matriz Consolidada'!$M$4:$M$85,">=1") -> 1 | F33: =COUNTIFS('Matriz Consolidada'!$G$4:$G$85,"A.6.4 Proceso disciplinario",'Matriz Consolidada'!$N$4:$N$85,">=1") -> 0 | G33: =COUNTIFS('Matriz Consolidada'!$G$4:$G$85,"A.6.4 Proceso disciplinario",'Matriz Consolidada'!$O$4:$O$85,">=1") -> 1
B34: Cláusula 6.1.3 Tratamiento de riesgos de seguridad de la información | C34: =COUNTIF('Matriz Consolidada'!$G$4:$G$85,"Cláusula 6.1.3 Tratamiento de riesgos de seguridad de la información") -> 1 | D34: =COUNTIFS('Matriz Consolidada'!$G$4:$G$85,"Cláusula 6.1.3 Tratamiento de riesgos de seguridad de la información",'Matriz Consolidada'!$L$4:$L$85,">=1") -> 1 | E34: =COUNTIFS('Matriz Consolidada'!$G$4:$G$85,"Cláusula 6.1.3 Tratamiento de riesgos de seguridad de la información",'Matriz Consolidada'!$M$4:$M$85,">=1") -> 1 | F34: =COUNTIFS('Matriz Consolidada'!$G$4:$G$85,"Cláusula 6.1.3 Tratamiento de riesgos de seguridad de la información",'Matriz Consolidada'!$N$4:$N$85,">=1") -> 1 | G34: =COUNTIFS('Matriz Consolidada'!$G$4:$G$85,"Cláusula 6.1.3 Tratamiento de riesgos de seguridad de la información",'Matriz Consolidada'!$O$4:$O$85,">=1") -> 1
B35: A.8.24 Uso de criptografía / A.8.15 Registro (logging) / A.8.3 Restricción de acceso | C35: =COUNTIF('Matriz Consolidada'!$G$4:$G$85,"A.8.24 Uso de criptografía / A.8.15 Registro (logging) / A.8.3 Restricción de acceso") -> 1 | D35: =COUNTIFS('Matriz Consolidada'!$G$4:$G$85,"A.8.24 Uso de criptografía / A.8.15 Registro (logging) / A.8.3 Restricción de acceso",'Matriz Consolidada'!$L$4:$L$85,">=1") -> 0 | E35: =COUNTIFS('Matriz Consolidada'!$G$4:$G$85,"A.8.24 Uso de criptografía / A.8.15 Registro (logging) / A.8.3 Restricción de acceso",'Matriz Consolidada'!$M$4:$M$85,">=1") -> 1 | F35: =COUNTIFS('Matriz Consolidada'!$G$4:$G$85,"A.8.24 Uso de criptografía / A.8.15 Registro (logging) / A.8.3 Restricción de acceso",'Matriz Consolidada'!$N$4:$N$85,">=1") -> 1 | G35: =COUNTIFS('Matriz Consolidada'!$G$4:$G$85,"A.8.24 Uso de criptografía / A.8.15 Registro (logging) / A.8.3 Restricción de acceso",'Matriz Consolidada'!$O$4:$O$85,">=1") -> 1
B36: A.5.19 Seguridad de la información en las relaciones con proveedores | C36: =COUNTIF('Matriz Consolidada'!$G$4:$G$85,"A.5.19 Seguridad de la información en las relaciones con proveedores") -> 1 | D36: =COUNTIFS('Matriz Consolidada'!$G$4:$G$85,"A.5.19 Seguridad de la información en las relaciones con proveedores",'Matriz Consolidada'!$L$4:$L$85,">=1") -> 0 | E36: =COUNTIFS('Matriz Consolidada'!$G$4:$G$85,"A.5.19 Seguridad de la información en las relaciones con proveedores",'Matriz Consolidada'!$M$4:$M$85,">=1") -> 1 | F36: =COUNTIFS('Matriz Consolidada'!$G$4:$G$85,"A.5.19 Seguridad de la información en las relaciones con proveedores",'Matriz Consolidada'!$N$4:$N$85,">=1") -> 1 | G36: =COUNTIFS('Matriz Consolidada'!$G$4:$G$85,"A.5.19 Seguridad de la información en las relaciones con proveedores",'Matriz Consolidada'!$O$4:$O$85,">=1") -> 1
B37: Cláusula 9.1 Monitoreo, medición, análisis y evaluación | C37: =COUNTIF('Matriz Consolidada'!$G$4:$G$85,"Cláusula 9.1 Monitoreo, medición, análisis y evaluación") -> 2 | D37: =COUNTIFS('Matriz Consolidada'!$G$4:$G$85,"Cláusula 9.1 Monitoreo, medición, análisis y evaluación",'Matriz Consolidada'!$L$4:$L$85,">=1") -> 1 | E37: =COUNTIFS('Matriz Consolidada'!$G$4:$G$85,"Cláusula 9.1 Monitoreo, medición, análisis y evaluación",'Matriz Consolidada'!$M$4:$M$85,">=1") -> 2 | F37: =COUNTIFS('Matriz Consolidada'!$G$4:$G$85,"Cláusula 9.1 Monitoreo, medición, análisis y evaluación",'Matriz Consolidada'!$N$4:$N$85,">=1") -> 2 | G37: =COUNTIFS('Matriz Consolidada'!$G$4:$G$85,"Cláusula 9.1 Monitoreo, medición, análisis y evaluación",'Matriz Consolidada'!$O$4:$O$85,">=1") -> 2
B38: Cláusula 5.2 Política / A.5.1 Políticas de seguridad de la información | C38: =COUNTIF('Matriz Consolidada'!$G$4:$G$85,"Cláusula 5.2 Política / A.5.1 Políticas de seguridad de la información") -> 1 | D38: =COUNTIFS('Matriz Consolidada'!$G$4:$G$85,"Cláusula 5.2 Política / A.5.1 Políticas de seguridad de la información",'Matriz Consolidada'!$L$4:$L$85,">=1") -> 0 | E38: =COUNTIFS('Matriz Consolidada'!$G$4:$G$85,"Cláusula 5.2 Política / A.5.1 Políticas de seguridad de la información",'Matriz Consolidada'!$M$4:$M$85,">=1") -> 1 | F38: =COUNTIFS('Matriz Consolidada'!$G$4:$G$85,"Cláusula 5.2 Política / A.5.1 Políticas de seguridad de la información",'Matriz Consolidada'!$N$4:$N$85,">=1") -> 1 | G38: =COUNTIFS('Matriz Consolidada'!$G$4:$G$85,"Cláusula 5.2 Política / A.5.1 Políticas de seguridad de la información",'Matriz Consolidada'!$O$4:$O$85,">=1") -> 1
B39: Cláusula 4.1-4.4 Contexto de la organización y alcance del SGSI | C39: =COUNTIF('Matriz Consolidada'!$G$4:$G$85,"Cláusula 4.1-4.4 Contexto de la organización y alcance del SGSI") -> 1 | D39: =COUNTIFS('Matriz Consolidada'!$G$4:$G$85,"Cláusula 4.1-4.4 Contexto de la organización y alcance del SGSI",'Matriz Consolidada'!$L$4:$L$85,">=1") -> 0 | E39: =COUNTIFS('Matriz Consolidada'!$G$4:$G$85,"Cláusula 4.1-4.4 Contexto de la organización y alcance del SGSI",'Matriz Consolidada'!$M$4:$M$85,">=1") -> 0 | F39: =COUNTIFS('Matriz Consolidada'!$G$4:$G$85,"Cláusula 4.1-4.4 Contexto de la organización y alcance del SGSI",'Matriz Consolidada'!$N$4:$N$85,">=1") -> 0 | G39: =COUNTIFS('Matriz Consolidada'!$G$4:$G$85,"Cláusula 4.1-4.4 Contexto de la organización y alcance del SGSI",'Matriz Consolidada'!$O$4:$O$85,">=1") -> 1
B40: A.5.9 Inventario de información y otros activos asociados / A.8.19 Instalación de software | C40: =COUNTIF('Matriz Consolidada'!$G$4:$G$85,"A.5.9 Inventario de información y otros activos asociados / A.8.19 Instalación de software") -> 1 | D40: =COUNTIFS('Matriz Consolidada'!$G$4:$G$85,"A.5.9 Inventario de información y otros activos asociados / A.8.19 Instalación de software",'Matriz Consolidada'!$L$4:$L$85,">=1") -> 1 | E40: =COUNTIFS('Matriz Consolidada'!$G$4:$G$85,"A.5.9 Inventario de información y otros activos asociados / A.8.19 Instalación de software",'Matriz Consolidada'!$M$4:$M$85,">=1") -> 1 | F40: =COUNTIFS('Matriz Consolidada'!$G$4:$G$85,"A.5.9 Inventario de información y otros activos asociados / A.8.19 Instalación de software",'Matriz Consolidada'!$N$4:$N$85,">=1") -> 1 | G40: =COUNTIFS('Matriz Consolidada'!$G$4:$G$85,"A.5.9 Inventario de información y otros activos asociados / A.8.19 Instalación de software",'Matriz Consolidada'!$O$4:$O$85,">=1") -> 1
B41: A.5.10 Uso aceptable de los activos / A.5.11 Devolución de activos / A.7.14 Eliminación segura de equipos | C41: =COUNTIF('Matriz Consolidada'!$G$4:$G$85,"A.5.10 Uso aceptable de los activos / A.5.11 Devolución de activos / A.7.14 Eliminación segura de equipos") -> 1 | D41: =COUNTIFS('Matriz Consolidada'!$G$4:$G$85,"A.5.10 Uso aceptable de los activos / A.5.11 Devolución de activos / A.7.14 Eliminación segura de equipos",'Matriz Consolidada'!$L$4:$L$85,">=1") -> 0 | E41: =COUNTIFS('Matriz Consolidada'!$G$4:$G$85,"A.5.10 Uso aceptable de los activos / A.5.11 Devolución de activos / A.7.14 Eliminación segura de equipos",'Matriz Consolidada'!$M$4:$M$85,">=1") -> 1 | F41: =COUNTIFS('Matriz Consolidada'!$G$4:$G$85,"A.5.10 Uso aceptable de los activos / A.5.11 Devolución de activos / A.7.14 Eliminación segura de equipos",'Matriz Consolidada'!$N$4:$N$85,">=1") -> 1 | G41: =COUNTIFS('Matriz Consolidada'!$G$4:$G$85,"A.5.10 Uso aceptable de los activos / A.5.11 Devolución de activos / A.7.14 Eliminación segura de equipos",'Matriz Consolidada'!$O$4:$O$85,">=1") -> 1
B42: A.5.9 / A.8.9 Gestión de la configuración | C42: =COUNTIF('Matriz Consolidada'!$G$4:$G$85,"A.5.9 / A.8.9 Gestión de la configuración") -> 1 | D42: =COUNTIFS('Matriz Consolidada'!$G$4:$G$85,"A.5.9 / A.8.9 Gestión de la configuración",'Matriz Consolidada'!$L$4:$L$85,">=1") -> 0 | E42: =COUNTIFS('Matriz Consolidada'!$G$4:$G$85,"A.5.9 / A.8.9 Gestión de la configuración",'Matriz Consolidada'!$M$4:$M$85,">=1") -> 1 | F42: =COUNTIFS('Matriz Consolidada'!$G$4:$G$85,"A.5.9 / A.8.9 Gestión de la configuración",'Matriz Consolidada'!$N$4:$N$85,">=1") -> 1 | G42: =COUNTIFS('Matriz Consolidada'!$G$4:$G$85,"A.5.9 / A.8.9 Gestión de la configuración",'Matriz Consolidada'!$O$4:$O$85,">=1") -> 1
B43: A.8.9 Gestión de la configuración / A.5.9 | C43: =COUNTIF('Matriz Consolidada'!$G$4:$G$85,"A.8.9 Gestión de la configuración / A.5.9") -> 1 | D43: =COUNTIFS('Matriz Consolidada'!$G$4:$G$85,"A.8.9 Gestión de la configuración / A.5.9",'Matriz Consolidada'!$L$4:$L$85,">=1") -> 1 | E43: =COUNTIFS('Matriz Consolidada'!$G$4:$G$85,"A.8.9 Gestión de la configuración / A.5.9",'Matriz Consolidada'!$M$4:$M$85,">=1") -> 1 | F43: =COUNTIFS('Matriz Consolidada'!$G$4:$G$85,"A.8.9 Gestión de la configuración / A.5.9",'Matriz Consolidada'!$N$4:$N$85,">=1") -> 1 | G43: =COUNTIFS('Matriz Consolidada'!$G$4:$G$85,"A.8.9 Gestión de la configuración / A.5.9",'Matriz Consolidada'!$O$4:$O$85,">=1") -> 1
B44: A.5.15 Control de acceso / A.8.2 Derechos de acceso privilegiado / A.8.3 Restricción de acceso a la información | C44: =COUNTIF('Matriz Consolidada'!$G$4:$G$85,"A.5.15 Control de acceso / A.8.2 Derechos de acceso privilegiado / A.8.3 Restricción de acceso a la información") -> 1 | D44: =COUNTIFS('Matriz Consolidada'!$G$4:$G$85,"A.5.15 Control de acceso / A.8.2 Derechos de acceso privilegiado / A.8.3 Restricción de acceso a la información",'Matriz Consolidada'!$L$4:$L$85,">=1") -> 1 | E44: =COUNTIFS('Matriz Consolidada'!$G$4:$G$85,"A.5.15 Control de acceso / A.8.2 Derechos de acceso privilegiado / A.8.3 Restricción de acceso a la información",'Matriz Consolidada'!$M$4:$M$85,">=1") -> 1 | F44: =COUNTIFS('Matriz Consolidada'!$G$4:$G$85,"A.5.15 Control de acceso / A.8.2 Derechos de acceso privilegiado / A.8.3 Restricción de acceso a la información",'Matriz Consolidada'!$N$4:$N$85,">=1") -> 1 | G44: =COUNTIFS('Matriz Consolidada'!$G$4:$G$85,"A.5.15 Control de acceso / A.8.2 Derechos de acceso privilegiado / A.8.3 Restricción de acceso a la información",'Matriz Consolidada'!$O$4:$O$85,">=1") -> 1
B45: A.8.15 Registro (logging) / A.8.16 Actividades de monitoreo | C45: =COUNTIF('Matriz Consolidada'!$G$4:$G$85,"A.8.15 Registro (logging) / A.8.16 Actividades de monitoreo") -> 1 | D45: =COUNTIFS('Matriz Consolidada'!$G$4:$G$85,"A.8.15 Registro (logging) / A.8.16 Actividades de monitoreo",'Matriz Consolidada'!$L$4:$L$85,">=1") -> 0 | E45: =COUNTIFS('Matriz Consolidada'!$G$4:$G$85,"A.8.15 Registro (logging) / A.8.16 Actividades de monitoreo",'Matriz Consolidada'!$M$4:$M$85,">=1") -> 1 | F45: =COUNTIFS('Matriz Consolidada'!$G$4:$G$85,"A.8.15 Registro (logging) / A.8.16 Actividades de monitoreo",'Matriz Consolidada'!$N$4:$N$85,">=1") -> 1 | G45: =COUNTIFS('Matriz Consolidada'!$G$4:$G$85,"A.8.15 Registro (logging) / A.8.16 Actividades de monitoreo",'Matriz Consolidada'!$O$4:$O$85,">=1") -> 1
B46: A.5.29 Seguridad de la información durante la disrupción / A.5.30 Preparación TIC para la continuidad del negocio | C46: =COUNTIF('Matriz Consolidada'!$G$4:$G$85,"A.5.29 Seguridad de la información durante la disrupción / A.5.30 Preparación TIC para la continuidad del negocio") -> 1 | D46: =COUNTIFS('Matriz Consolidada'!$G$4:$G$85,"A.5.29 Seguridad de la información durante la disrupción / A.5.30 Preparación TIC para la continuidad del negocio",'Matriz Consolidada'!$L$4:$L$85,">=1") -> 0 | E46: =COUNTIFS('Matriz Consolidada'!$G$4:$G$85,"A.5.29 Seguridad de la información durante la disrupción / A.5.30 Preparación TIC para la continuidad del negocio",'Matriz Consolidada'!$M$4:$M$85,">=1") -> 1 | F46: =COUNTIFS('Matriz Consolidada'!$G$4:$G$85,"A.5.29 Seguridad de la información durante la disrupción / A.5.30 Preparación TIC para la continuidad del negocio",'Matriz Consolidada'!$N$4:$N$85,">=1") -> 1 | G46: =COUNTIFS('Matriz Consolidada'!$G$4:$G$85,"A.5.29 Seguridad de la información durante la disrupción / A.5.30 Preparación TIC para la continuidad del negocio",'Matriz Consolidada'!$O$4:$O$85,">=1") -> 1
B47: A.8.13 Respaldo de la información | C47: =COUNTIF('Matriz Consolidada'!$G$4:$G$85,"A.8.13 Respaldo de la información") -> 1 | D47: =COUNTIFS('Matriz Consolidada'!$G$4:$G$85,"A.8.13 Respaldo de la información",'Matriz Consolidada'!$L$4:$L$85,">=1") -> 1 | E47: =COUNTIFS('Matriz Consolidada'!$G$4:$G$85,"A.8.13 Respaldo de la información",'Matriz Consolidada'!$M$4:$M$85,">=1") -> 1 | F47: =COUNTIFS('Matriz Consolidada'!$G$4:$G$85,"A.8.13 Respaldo de la información",'Matriz Consolidada'!$N$4:$N$85,">=1") -> 1 | G47: =COUNTIFS('Matriz Consolidada'!$G$4:$G$85,"A.8.13 Respaldo de la información",'Matriz Consolidada'!$O$4:$O$85,">=1") -> 1
B48: A.8.8 Gestión de vulnerabilidades técnicas / A.8.9 Gestión de la configuración | C48: =COUNTIF('Matriz Consolidada'!$G$4:$G$85,"A.8.8 Gestión de vulnerabilidades técnicas / A.8.9 Gestión de la configuración") -> 1 | D48: =COUNTIFS('Matriz Consolidada'!$G$4:$G$85,"A.8.8 Gestión de vulnerabilidades técnicas / A.8.9 Gestión de la configuración",'Matriz Consolidada'!$L$4:$L$85,">=1") -> 0 | E48: =COUNTIFS('Matriz Consolidada'!$G$4:$G$85,"A.8.8 Gestión de vulnerabilidades técnicas / A.8.9 Gestión de la configuración",'Matriz Consolidada'!$M$4:$M$85,">=1") -> 1 | F48: =COUNTIFS('Matriz Consolidada'!$G$4:$G$85,"A.8.8 Gestión de vulnerabilidades técnicas / A.8.9 Gestión de la configuración",'Matriz Consolidada'!$N$4:$N$85,">=1") -> 1 | G48: =COUNTIFS('Matriz Consolidada'!$G$4:$G$85,"A.8.8 Gestión de vulnerabilidades técnicas / A.8.9 Gestión de la configuración",'Matriz Consolidada'!$O$4:$O$85,">=1") -> 1
B49: A.8.7 Protección contra código malicioso / A.8.20 Seguridad de redes | C49: =COUNTIF('Matriz Consolidada'!$G$4:$G$85,"A.8.7 Protección contra código malicioso / A.8.20 Seguridad de redes") -> 1 | D49: =COUNTIFS('Matriz Consolidada'!$G$4:$G$85,"A.8.7 Protección contra código malicioso / A.8.20 Seguridad de redes",'Matriz Consolidada'!$L$4:$L$85,">=1") -> 1 | E49: =COUNTIFS('Matriz Consolidada'!$G$4:$G$85,"A.8.7 Protección contra código malicioso / A.8.20 Seguridad de redes",'Matriz Consolidada'!$M$4:$M$85,">=1") -> 1 | F49: =COUNTIFS('Matriz Consolidada'!$G$4:$G$85,"A.8.7 Protección contra código malicioso / A.8.20 Seguridad de redes",'Matriz Consolidada'!$N$4:$N$85,">=1") -> 1 | G49: =COUNTIFS('Matriz Consolidada'!$G$4:$G$85,"A.8.7 Protección contra código malicioso / A.8.20 Seguridad de redes",'Matriz Consolidada'!$O$4:$O$85,">=1") -> 1
B50: A.8.22 Segregación de redes / A.8.20 Seguridad de redes | C50: =COUNTIF('Matriz Consolidada'!$G$4:$G$85,"A.8.22 Segregación de redes / A.8.20 Seguridad de redes") -> 1 | D50: =COUNTIFS('Matriz Consolidada'!$G$4:$G$85,"A.8.22 Segregación de redes / A.8.20 Seguridad de redes",'Matriz Consolidada'!$L$4:$L$85,">=1") -> 0 | E50: =COUNTIFS('Matriz Consolidada'!$G$4:$G$85,"A.8.22 Segregación de redes / A.8.20 Seguridad de redes",'Matriz Consolidada'!$M$4:$M$85,">=1") -> 1 | F50: =COUNTIFS('Matriz Consolidada'!$G$4:$G$85,"A.8.22 Segregación de redes / A.8.20 Seguridad de redes",'Matriz Consolidada'!$N$4:$N$85,">=1") -> 1 | G50: =COUNTIFS('Matriz Consolidada'!$G$4:$G$85,"A.8.22 Segregación de redes / A.8.20 Seguridad de redes",'Matriz Consolidada'!$O$4:$O$85,">=1") -> 1
B51: A.8.2 Derechos de acceso privilegiado | C51: =COUNTIF('Matriz Consolidada'!$G$4:$G$85,"A.8.2 Derechos de acceso privilegiado") -> 1 | D51: =COUNTIFS('Matriz Consolidada'!$G$4:$G$85,"A.8.2 Derechos de acceso privilegiado",'Matriz Consolidada'!$L$4:$L$85,">=1") -> 0 | E51: =COUNTIFS('Matriz Consolidada'!$G$4:$G$85,"A.8.2 Derechos de acceso privilegiado",'Matriz Consolidada'!$M$4:$M$85,">=1") -> 0 | F51: =COUNTIFS('Matriz Consolidada'!$G$4:$G$85,"A.8.2 Derechos de acceso privilegiado",'Matriz Consolidada'!$N$4:$N$85,">=1") -> 1 | G51: =COUNTIFS('Matriz Consolidada'!$G$4:$G$85,"A.8.2 Derechos de acceso privilegiado",'Matriz Consolidada'!$O$4:$O$85,">=1") -> 1
B52: A.8.8 Gestión de vulnerabilidades técnicas / A.8.29 Pruebas de seguridad | C52: =COUNTIF('Matriz Consolidada'!$G$4:$G$85,"A.8.8 Gestión de vulnerabilidades técnicas / A.8.29 Pruebas de seguridad") -> 1 | D52: =COUNTIFS('Matriz Consolidada'!$G$4:$G$85,"A.8.8 Gestión de vulnerabilidades técnicas / A.8.29 Pruebas de seguridad",'Matriz Consolidada'!$L$4:$L$85,">=1") -> 1 | E52: =COUNTIFS('Matriz Consolidada'!$G$4:$G$85,"A.8.8 Gestión de vulnerabilidades técnicas / A.8.29 Pruebas de seguridad",'Matriz Consolidada'!$M$4:$M$85,">=1") -> 1 | F52: =COUNTIFS('Matriz Consolidada'!$G$4:$G$85,"A.8.8 Gestión de vulnerabilidades técnicas / A.8.29 Pruebas de seguridad",'Matriz Consolidada'!$N$4:$N$85,">=1") -> 1 | G52: =COUNTIFS('Matriz Consolidada'!$G$4:$G$85,"A.8.8 Gestión de vulnerabilidades técnicas / A.8.29 Pruebas de seguridad",'Matriz Consolidada'!$O$4:$O$85,">=1") -> 1
B53: A.8.32 Gestión de cambios | C53: =COUNTIF('Matriz Consolidada'!$G$4:$G$85,"A.8.32 Gestión de cambios") -> 1 | D53: =COUNTIFS('Matriz Consolidada'!$G$4:$G$85,"A.8.32 Gestión de cambios",'Matriz Consolidada'!$L$4:$L$85,">=1") -> 0 | E53: =COUNTIFS('Matriz Consolidada'!$G$4:$G$85,"A.8.32 Gestión de cambios",'Matriz Consolidada'!$M$4:$M$85,">=1") -> 1 | F53: =COUNTIFS('Matriz Consolidada'!$G$4:$G$85,"A.8.32 Gestión de cambios",'Matriz Consolidada'!$N$4:$N$85,">=1") -> 1 | G53: =COUNTIFS('Matriz Consolidada'!$G$4:$G$85,"A.8.32 Gestión de cambios",'Matriz Consolidada'!$O$4:$O$85,">=1") -> 1
B54: A.5.31 Requisitos legales, estatutarios, regulatorios y contractuales | C54: =COUNTIF('Matriz Consolidada'!$G$4:$G$85,"A.5.31 Requisitos legales, estatutarios, regulatorios y contractuales") -> 1 | D54: =COUNTIFS('Matriz Consolidada'!$G$4:$G$85,"A.5.31 Requisitos legales, estatutarios, regulatorios y contractuales",'Matriz Consolidada'!$L$4:$L$85,">=1") -> 0 | E54: =COUNTIFS('Matriz Consolidada'!$G$4:$G$85,"A.5.31 Requisitos legales, estatutarios, regulatorios y contractuales",'Matriz Consolidada'!$M$4:$M$85,">=1") -> 1 | F54: =COUNTIFS('Matriz Consolidada'!$G$4:$G$85,"A.5.31 Requisitos legales, estatutarios, regulatorios y contractuales",'Matriz Consolidada'!$N$4:$N$85,">=1") -> 1 | G54: =COUNTIFS('Matriz Consolidada'!$G$4:$G$85,"A.5.31 Requisitos legales, estatutarios, regulatorios y contractuales",'Matriz Consolidada'!$O$4:$O$85,">=1") -> 1
B55: A.5.31 Requisitos legales, estatutarios, regulatorios y contractuales / Cláusula 4.2 | C55: =COUNTIF('Matriz Consolidada'!$G$4:$G$85,"A.5.31 Requisitos legales, estatutarios, regulatorios y contractuales / Cláusula 4.2") -> 1 | D55: =COUNTIFS('Matriz Consolidada'!$G$4:$G$85,"A.5.31 Requisitos legales, estatutarios, regulatorios y contractuales / Cláusula 4.2",'Matriz Consolidada'!$L$4:$L$85,">=1") -> 1 | E55: =COUNTIFS('Matriz Consolidada'!$G$4:$G$85,"A.5.31 Requisitos legales, estatutarios, regulatorios y contractuales / Cláusula 4.2",'Matriz Consolidada'!$M$4:$M$85,">=1") -> 1 | F55: =COUNTIFS('Matriz Consolidada'!$G$4:$G$85,"A.5.31 Requisitos legales, estatutarios, regulatorios y contractuales / Cláusula 4.2",'Matriz Consolidada'!$N$4:$N$85,">=1") -> 1 | G55: =COUNTIFS('Matriz Consolidada'!$G$4:$G$85,"A.5.31 Requisitos legales, estatutarios, regulatorios y contractuales / Cláusula 4.2",'Matriz Consolidada'!$O$4:$O$85,">=1") -> 1

Sheet Plan_Institucion_A
B2: PLAN DE CIERRE DE BRECHAS · Institución A (índice global actual: 55.0%)
B4: Prioridad | C4: Plazo | D4: Módulo | E4: ID | F4: Criterio / Dimensión | G4: Estado actual | H4: Control ISO/IEC 27001:2022 | I4: Acción correctiva recomendada | J4: Responsable sugerido
B5: CRÍTICA | C5: 0-3 meses | D5: M1 · Cumplimiento LOPDP/RGLOPDP | E5: B5 | F5: Política de uso de cookies con consentimiento informado | G5: No | H5: A.5.34 Privacidad y protección de datos personales (PII) | I5: Implementar aviso/banner de cookies con opciones de aceptación granular en los sitios y plataformas institucionales. | J5: TI + DPD
B6: CRÍTICA | C6: 0-3 meses | D6: M1 · Cumplimiento LOPDP/RGLOPDP | E6: D2 | F6: Contratos firmados con encargados de tratamiento externos | G6: No | H6: A.5.20 Abordar la seguridad de la información en los acuerdos con proveedores | I6: Incorporar cláusulas de protección de datos en todo contrato con proveedores que traten datos personales; regularizar los vigentes. | J6: Jurídico + DPD
B7: CRÍTICA | C7: 0-3 meses | D7: M1 · Cumplimiento LOPDP/RGLOPDP | E7: E3 | F7: Evaluación de Impacto en Protección de Datos (EIPD) para tratamientos de alto riesgo | G7: No | H7: Cláusula 8.2 Evaluación de riesgos de seguridad de la información | I7: Elaborar EIPD para los tratamientos de mayor riesgo (video-vigilancia, biometría, salud, datos de menores) antes de su implementación o de forma retroactiva. | J7: DPD
B8: CRÍTICA | C8: 0-3 meses | D8: M1 · Cumplimiento LOPDP/RGLOPDP | E8: E5 | F8: Análisis de vulnerabilidades informáticas relacionadas con datos personales | G8: No | H8: A.8.8 Gestión de vulnerabilidades técnicas | I8: Implementar un proceso periódico de identificación y remediación de vulnerabilidades en sistemas que tratan datos personales. | J8: TI
B9: CRÍTICA | C9: 0-3 meses | D9: M1 · Cumplimiento LOPDP/RGLOPDP | E9: F2 | F9: Revisiones periódicas y auditorías de cumplimiento de protección de datos | G9: No | H9: Cláusula 9.2 Auditoría interna | I9: Planificar auditorías internas anuales de cumplimiento LOPDP con informe de hallazgos y seguimiento. | J9: Auditoría interna/Dirección + DPD
B10: CRÍTICA | C10: 0-3 meses | D10: M2 · Madurez Institucional | E10: G1 | F10: Estructura de gobierno de datos con roles y responsabilidades definidos (Responsable, DPD, Encargados) | G10: 1 | H10: A.5.2 Roles y responsabilidades de seguridad de la información | I10: Definir y aprobar formalmente el organigrama de gobierno de datos (RACI) con Responsable, DPD y Encargados. | J10: Dirección
B11: CRÍTICA | C11: 0-3 meses | D11: M2 · Madurez Institucional | E11: P2 | F11: Registro de Actividades de Tratamiento (RAT) actualizado | G11: 1 | H11: A.5.9 Inventario de información y otros activos asociados | I11: Levantar el RAT y establecer una revisión periódica (al menos semestral) para mantenerlo vigente. | J11: DPD
B12: CRÍTICA | C12: 0-3 meses | D12: M2 · Madurez Institucional | E12: P3 | F12: Procedimientos formales para responder derechos ARCO+ de los titulares | G12: 1 | H12: A.5.34 Privacidad y protección de datos personales (PII) | I12: Formalizar el procedimiento único de atención de derechos ARCO+ (ver Módulo 1, sección C). | J12: DPD
B13: CRÍTICA | C13: 0-3 meses | D13: M2 · Madurez Institucional | E13: P5 | F13: Proceso de revisión y mejora continua de los procedimientos de protección de datos | G13: 1 | H13: Cláusula 10.1 Mejora continua | I13: Establecer un ciclo anual de revisión de procedimientos de protección de datos, con responsable y fecha de revisión. | J13: DPD
B14: CRÍTICA | C14: 0-3 meses | D14: M2 · Madurez Institucional | E14: R1 | F14: Análisis de riesgos formal para el tratamiento de datos personales | G14: 1 | H14: Cláusula 6.1 / 8.2 Evaluación de riesgos de seguridad de la información | I14: Formalizar la metodología de análisis de riesgos y aplicarla de forma recurrente (ver Módulo 1, E2). | J14: TI + DPD
B15: CRÍTICA | C15: 0-3 meses | D15: M2 · Madurez Institucional | E15: A1 | F15: Auditorías internas periódicas de cumplimiento en protección de datos | G15: 1 | H15: Cláusula 9.2 Auditoría interna | I15: Ver Módulo 1, F2. | J15: Auditoría/Dirección
B16: CRÍTICA | C16: 0-3 meses | D16: M2 · Madurez Institucional | E16: A3 | F16: Hallazgos de auditoría documentados, priorizados e implementados con seguimiento | G16: 1 | H16: Cláusula 10.1 Mejora continua | I16: Implementar un plan de acción con seguimiento formal para cada hallazgo de auditoría. | J16: DPD + Dirección
B17: CRÍTICA | C17: 0-3 meses | D17: M2 · Madurez Institucional | E17: CC2 | F17: Capacitaciones formales y periódicas sobre protección de datos a todos los niveles | G17: 1 | H17: A.6.3 Concienciación, educación y formación en seguridad de la información | I17: Implementar un plan de capacitación anual, con registro de asistencia y evaluación de efectividad. | J17: Talento Humano + DPD
B18: CRÍTICA | C18: 0-3 meses | D18: M2 · Madurez Institucional | E18: R3 | F18: Evaluaciones de Impacto en Protección de Datos (EIPD) cuando corresponde | G18: 1 | H18: Cláusula 8.2 Evaluación de riesgos de seguridad de la información | I18: Ver Módulo 1, E3. | J18: DPD
B19: CRÍTICA | C19: 0-3 meses | D19: M1 · Cumplimiento LOPDP/RGLOPDP | E19: A4 | F19: Inventario actualizado de flujos de datos (quién recibe, quién envía, con qué propósito) | G19: No | H19: A.5.9 / A.8.1 Dispositivos de usuario final | I19: Elaborar un diagrama de flujos de datos personales (origen, destino, medio, finalidad) y mantenerlo actualizado. | J19: DPD + TI
B20: CRÍTICA | C20: 0-3 meses | D20: M1 · Cumplimiento LOPDP/RGLOPDP | E20: C3 | F20: Mecanismo formal para solicitudes de Cancelación / Supresión de datos | G20: No | H20: A.5.34 Privacidad y protección de datos personales (PII) | I20: Definir el procedimiento y las excepciones legales de conservación aplicables a la supresión de datos. | J20: DPD + Secretaría/Archivo
B21: CRÍTICA | C21: 0-3 meses | D21: M1 · Cumplimiento LOPDP/RGLOPDP | E21: C4 | F21: Mecanismo formal para solicitudes de Oposición al tratamiento | G21: No | H21: A.5.34 Privacidad y protección de datos personales (PII) | I21: Incorporar la oposición como opción explícita en los formatos de consentimiento y en el procedimiento de derechos. | J21: DPD + Secretaría
B22: CRÍTICA | C22: 0-3 meses | D22: M1 · Cumplimiento LOPDP/RGLOPDP | E22: E4 | F22: Procedimiento documentado para notificación de vulneraciones de seguridad | G22: Parcial | H22: A.5.24 Planificación y preparación de la gestión de incidentes / A.6.8 Reporte de eventos | I22: Documentar el procedimiento de gestión y notificación de incidentes/vulneraciones, con roles, plazos y plantillas de notificación. | J22: TI + DPD
B23: CRÍTICA | C23: 0-3 meses | D23: M1 · Cumplimiento LOPDP/RGLOPDP | E23: E6 | F23: Políticas de anonimización, cifrado y eliminación segura de datos | G23: Parcial | H23: A.8.24 Uso de criptografía / A.8.10 Eliminación de la información | I23: Definir estándares de cifrado para datos en reposo/tránsito y un procedimiento de borrado seguro para bajas de equipos y medios. | J23: TI
B24: CRÍTICA | C24: 0-3 meses | D24: M1 · Cumplimiento LOPDP/RGLOPDP | E24: E7 | F24: Señalización visible en zonas con cámaras de seguridad | G24: No | H24: A.7.4 Monitoreo de seguridad física | I24: Instalar señalética visible en todas las zonas con cámaras, indicando finalidad y responsable del tratamiento. | J24: Administrativo + DPD
B25: CRÍTICA | C25: 0-3 meses | D25: M1 · Cumplimiento LOPDP/RGLOPDP | E25: F1 | F25: Capacitaciones periódicas a docentes, autoridades y estudiantes sobre protección de datos | G25: Parcial | H25: A.6.3 Concienciación, educación y formación en seguridad de la información | I25: Implementar un plan anual de capacitación en LOPDP y seguridad de la información para todos los roles. | J25: Talento Humano + DPD
B26: CRÍTICA | C26: 0-3 meses | D26: M1 · Cumplimiento LOPDP/RGLOPDP | E26: F3 | F26: Política de retención y eliminación de datos documentada y aplicada | G26: Parcial | H26: A.5.33 Protección de los registros / A.8.10 Eliminación de la información | I26: Aprobar la política de retención (ver A3) y ejecutar depuraciones periódicas verificables. | J26: DPD + Archivo
B27: CRÍTICA | C27: 0-3 meses | D27: M2 · Madurez Institucional | E27: P1 | F27: Procesos de tratamiento de datos documentados, aprobados y comunicados al personal | G27: 1 | H27: A.5.37 Procedimientos operativos documentados | I27: Documentar y aprobar los procedimientos clave de tratamiento de datos y capacitar al personal en su aplicación. | J27: DPD + dueños de proceso
B28: CRÍTICA | C28: 0-3 meses | D28: M2 · Madurez Institucional | E28: P4 | F28: Procedimientos para gestión de incidentes y brechas de datos | G28: 3 | H28: A.5.24 Planificación y preparación de la gestión de incidentes | I28: Aprobar el procedimiento de gestión de incidentes de seguridad de la información con roles y tiempos de respuesta. | J28: TI + DPD
B29: CRÍTICA | C29: 0-3 meses | D29: M2 · Madurez Institucional | E29: R2 | F29: Controles, responsables y plazos de mitigación asignados a los riesgos identificados | G29: 1 | H29: Cláusula 6.1.3 Tratamiento de riesgos de seguridad de la información | I29: Mantener una matriz de riesgos con controles, responsable y fecha de mitigación, revisada periódicamente. | J29: TI + DPD
B30: CRÍTICA | C30: 0-3 meses | D30: M2 · Madurez Institucional | E30: A2 | F30: Indicadores y métricas de cumplimiento monitoreados regularmente | G30: 2 | H30: Cláusula 9.1 Monitoreo, medición, análisis y evaluación | I30: Definir un tablero de indicadores de cumplimiento LOPDP y revisarlo trimestralmente. | J30: DPD
B31: CRÍTICA | C31: 0-3 meses | D31: M2 · Madurez Institucional | E31: A4 | F31: Aplicación de un ciclo de mejora continua (PHVA) en la gestión de datos personales | G31: 3 | H31: Cláusula 10.1 Mejora continua | I31: Adoptar formalmente el ciclo Planificar-Hacer-Verificar-Actuar como método de gestión del sistema de protección de datos. | J31: DPD + Dirección
B32: CRÍTICA | C32: 0-3 meses | D32: M3 · Gobernanza Tecnológica | E32: TA2 | F32: Inventario actualizado de software y licencias | G32: No | H32: A.5.9 Inventario de información y otros activos asociados / A.8.19 Instalación de software | I32: Levantar y mantener un inventario de software y licencias, con control de instalación autorizada. | J32: TI
B33: CRÍTICA | C33: 0-3 meses | D33: M3 · Gobernanza Tecnológica | E33: SI3 | F33: Controles de acceso basados en roles (RBAC) o perfiles de usuario | G33: Parcial | H33: A.5.15 Control de acceso / A.8.2 Derechos de acceso privilegiado / A.8.3 Restricción de acceso a la información | I33: Implementar perfiles de acceso por rol en todos los sistemas que traten datos personales, con revisión periódica de permisos. | J33: TI
B34: CRÍTICA | C34: 0-3 meses | D34: M3 · Gobernanza Tecnológica | E34: SEC3 | F34: Herramientas de protección perimetral (firewall, antivirus, IDS/IPS) | G34: No | H34: A.8.7 Protección contra código malicioso / A.8.20 Seguridad de redes | I34: Implementar y mantener firewall, antivirus/antimalware centralizado y, cuando el presupuesto lo permita, IDS/IPS. | J34: TI
B35: CRÍTICA | C35: 0-3 meses | D35: M3 · Gobernanza Tecnológica | E35: SEC6 | F35: Pruebas de seguridad (pentesting, ethical hacking) periódicas | G35: No | H35: A.8.8 Gestión de vulnerabilidades técnicas / A.8.29 Pruebas de seguridad | I35: Ver Módulo 1, F4. | J35: TI
B36: CRÍTICA | C36: 0-3 meses | D36: M3 · Gobernanza Tecnológica | E36: CN2 | F36: Aplicación del Esquema Gubernamental de Seguridad de la Información (EGSI) o similar | G36: Parcial | H36: A.5.31 Requisitos legales, estatutarios, regulatorios y contractuales / Cláusula 4.2 | I36: Adoptar los controles del EGSI aplicables a instituciones educativas y mapearlos contra el Anexo A de ISO/IEC 27001:2022. | J36: TI + DPD
B37: CRÍTICA | C37: 0-3 meses | D37: M2 · Madurez Institucional | E37: G3 | F37: Políticas institucionales formalizadas sobre privacidad y protección de datos personales | G37: 1 | H37: A.5.1 Políticas de seguridad de la información | I37: Aprobar y difundir la política institucional de protección de datos personales. | J37: Dirección + DPD
B38: CRÍTICA | C38: 0-3 meses | D38: M1 · Cumplimiento LOPDP/RGLOPDP | E38: D1 | F38: Delegado de Protección de Datos (DPD) formalmente designado | G38: No | H38: A.5.2 Roles y responsabilidades de seguridad de la información | I38: Formalizar por escrito la designación del DPD (o encargado equivalente), notificarla y publicar sus datos de contacto. | J38: Dirección/Rectorado
B39: CRÍTICA | C39: 0-3 meses | D39: M2 · Madurez Institucional | E39: G2 | F39: Liderazgo y compromiso de la alta dirección con el cumplimiento normativo | G39: 3 | H39: Cláusula 5.1 Liderazgo y compromiso | I39: Incluir la protección de datos como punto permanente en la planificación estratégica y en los comités de dirección. | J39: Rectorado/Dirección
B40: CRÍTICA | C40: 0-3 meses | D40: M2 · Madurez Institucional | E40: CC1 | F40: Conocimiento básico del personal sobre la LOPDP y sus obligaciones | G40: 3 | H40: A.6.3 Concienciación, educación y formación en seguridad de la información | I40: Difundir una guía básica de LOPDP a todo el personal como parte de la inducción institucional. | J40: Talento Humano
B41: CRÍTICA | C41: 0-3 meses | D41: M3 · Gobernanza Tecnológica | E41: SI2 | F41: Integración entre los sistemas de información documentada | G41: No | H41: A.8.9 Gestión de la configuración / A.5.9 | I41: Documentar las integraciones existentes (APIs, exportaciones, sincronizaciones) entre sistemas. | J41: TI
B42: CRÍTICA | C42: 0-3 meses | D42: M3 · Gobernanza Tecnológica | E42: CN3 | F42: Sistemas de información con requisitos de protección de datos desde su diseño (privacy by design) | G42: Parcial | H42: A.8.25 Ciclo de vida de desarrollo seguro / A.5.34 | I42: Ver Módulo 2, CC3. | J42: TI + DPD
B43: ALTA | C43: 3-6 meses | D43: M1 · Cumplimiento LOPDP/RGLOPDP | E43: B4 | F43: Información a los titulares sobre cómo ejercer sus derechos ARCO+ | G43: No | H43: A.5.34 Privacidad y protección de datos personales (PII) | I43: Incluir en avisos de privacidad y canales institucionales el procedimiento y medios para ejercer derechos ARCO+. | J43: DPD + Comunicación
B44: ALTA | C44: 3-6 meses | D44: M2 · Madurez Institucional | E44: CC3 | F44: Cultura de privacidad por diseño en el desarrollo de nuevos proyectos o sistemas | G44: 3 | H44: A.8.25 Ciclo de vida de desarrollo seguro / A.5.34 | I44: Incluir una lista de verificación de privacidad por diseño en la adquisición o desarrollo de todo nuevo sistema. | J44: TI + DPD
B45: ALTA | C45: 3-6 meses | D45: M3 · Gobernanza Tecnológica | E45: SI6 | F45: Respaldos periódicos de bases de datos y sistemas con pruebas de restauración | G45: Parcial | H45: A.8.13 Respaldo de la información | I45: Formalizar la política de respaldos (frecuencia, retención) y ejecutar pruebas de restauración periódicas documentadas. | J45: TI
B46: ALTA | C46: 3-6 meses | D46: M3 · Gobernanza Tecnológica | E46: SEC1 | F46: Política de seguridad de la información documentada y vigente | G46: No | H46: A.5.1 Políticas de seguridad de la información | I46: Aprobar y difundir la política de seguridad de la información, revisándola al menos anualmente. | J46: TI + Dirección
B47: ALTA | C47: 3-6 meses | D47: M3 · Gobernanza Tecnológica | E47: CN4 | F47: Revisión periódica del cumplimiento normativo tecnológico (auditorías TI) | G47: No | H47: Cláusula 9.2 Auditoría interna | I47: Incluir el componente tecnológico dentro del plan anual de auditoría interna de cumplimiento (ver Módulo 1, F2). | J47: TI + Auditoría/Dirección
B48: ALTA | C48: 3-6 meses | D48: M1 · Cumplimiento LOPDP/RGLOPDP | E48: B3 | F48: Política de privacidad clara, accesible y revisada periódicamente | G48: Parcial | H48: A.5.1 Políticas de seguridad de la información | I48: Redactar, aprobar y publicar la política institucional de protección de datos personales; revisarla al menos una vez al año. | J48: Dirección + DPD
B49: ALTA | C49: 3-6 meses | D49: M1 · Cumplimiento LOPDP/RGLOPDP | E49: C1 | F49: Mecanismo formal para atender solicitudes de Acceso a datos personales | G49: Parcial | H49: A.5.34 Privacidad y protección de datos personales (PII) | I49: Crear un procedimiento documentado (formulario, canal y plazos) para solicitudes de acceso. | J49: DPD + Secretaría
B50: ALTA | C50: 3-6 meses | D50: M1 · Cumplimiento LOPDP/RGLOPDP | E50: C2 | F50: Mecanismo formal para solicitudes de Rectificación de datos | G50: Parcial | H50: A.5.34 Privacidad y protección de datos personales (PII) | I50: Extender el procedimiento de derechos ARCO+ para incluir rectificación con verificación de identidad y trazabilidad del cambio. | J50: DPD + Secretaría
B51: ALTA | C51: 3-6 meses | D51: M1 · Cumplimiento LOPDP/RGLOPDP | E51: C5 | F51: Cumplimiento de los plazos legales para atender derechos de los titulares | G51: No | H51: A.5.34 / A.9.1 Monitoreo, medición, análisis y evaluación (cláusula 9.1) | I51: Establecer indicadores de tiempo de respuesta y un registro de solicitudes con seguimiento de vencimientos. | J51: DPD
B52: ALTA | C52: 3-6 meses | D52: M2 · Madurez Institucional | E52: CC4 | F52: Consecuencias formales (régimen disciplinario) ante incumplimiento de normas de privacidad | G52: 3 | H52: A.6.4 Proceso disciplinario | I52: Incorporar el incumplimiento de las normas de protección de datos al reglamento interno de trabajo/régimen disciplinario. | J52: Talento Humano + Jurídico
B53: MEDIA | C53: 6-9 meses | D53: M1 · Cumplimiento LOPDP/RGLOPDP | E53: A1 | F53: Identificación y registro de todas las bases de datos que contienen datos personales | G53: Parcial | H53: A.5.9 Inventario de información y otros activos asociados | I53: Levantar y mantener un inventario único de bases de datos con responsable, finalidad, base de legitimación y ubicación (Registro de Actividades de Tratamiento, RAT). | J53: DPD + Secretaría/áreas dueñas de la información

Sheet Plan_Institucion_B
B2: PLAN DE CIERRE DE BRECHAS · Institución B (índice global actual: 35.6%)
B4: Prioridad | C4: Plazo | D4: Módulo | E4: ID | F4: Criterio / Dimensión | G4: Estado actual | H4: Control ISO/IEC 27001:2022 | I4: Acción correctiva recomendada | J4: Responsable sugerido
B5: CRÍTICA | C5: 0-3 meses | D5: M1 · Cumplimiento LOPDP/RGLOPDP | E5: B5 | F5: Política de uso de cookies con consentimiento informado | G5: No | H5: A.5.34 Privacidad y protección de datos personales (PII) | I5: Implementar aviso/banner de cookies con opciones de aceptación granular en los sitios y plataformas institucionales. | J5: TI + DPD
B6: CRÍTICA | C6: 0-3 meses | D6: M1 · Cumplimiento LOPDP/RGLOPDP | E6: D2 | F6: Contratos firmados con encargados de tratamiento externos | G6: No | H6: A.5.20 Abordar la seguridad de la información en los acuerdos con proveedores | I6: Incorporar cláusulas de protección de datos en todo contrato con proveedores que traten datos personales; regularizar los vigentes. | J6: Jurídico + DPD
B7: CRÍTICA | C7: 0-3 meses | D7: M1 · Cumplimiento LOPDP/RGLOPDP | E7: E3 | F7: Evaluación de Impacto en Protección de Datos (EIPD) para tratamientos de alto riesgo | G7: No | H7: Cláusula 8.2 Evaluación de riesgos de seguridad de la información | I7: Elaborar EIPD para los tratamientos de mayor riesgo (video-vigilancia, biometría, salud, datos de menores) antes de su implementación o de forma retroactiva. | J7: DPD
B8: CRÍTICA | C8: 0-3 meses | D8: M1 · Cumplimiento LOPDP/RGLOPDP | E8: E5 | F8: Análisis de vulnerabilidades informáticas relacionadas con datos personales | G8: No | H8: A.8.8 Gestión de vulnerabilidades técnicas | I8: Implementar un proceso periódico de identificación y remediación de vulnerabilidades en sistemas que tratan datos personales. | J8: TI
B9: CRÍTICA | C9: 0-3 meses | D9: M1 · Cumplimiento LOPDP/RGLOPDP | E9: F2 | F9: Revisiones periódicas y auditorías de cumplimiento de protección de datos | G9: No | H9: Cláusula 9.2 Auditoría interna | I9: Planificar auditorías internas anuales de cumplimiento LOPDP con informe de hallazgos y seguimiento. | J9: Auditoría interna/Dirección + DPD
B10: CRÍTICA | C10: 0-3 meses | D10: M2 · Madurez Institucional | E10: G1 | F10: Estructura de gobierno de datos con roles y responsabilidades definidos (Responsable, DPD, Encargados) | G10: 1 | H10: A.5.2 Roles y responsabilidades de seguridad de la información | I10: Definir y aprobar formalmente el organigrama de gobierno de datos (RACI) con Responsable, DPD y Encargados. | J10: Dirección
B11: CRÍTICA | C11: 0-3 meses | D11: M2 · Madurez Institucional | E11: P2 | F11: Registro de Actividades de Tratamiento (RAT) actualizado | G11: 1 | H11: A.5.9 Inventario de información y otros activos asociados | I11: Levantar el RAT y establecer una revisión periódica (al menos semestral) para mantenerlo vigente. | J11: DPD
B12: CRÍTICA | C12: 0-3 meses | D12: M2 · Madurez Institucional | E12: P3 | F12: Procedimientos formales para responder derechos ARCO+ de los titulares | G12: 1 | H12: A.5.34 Privacidad y protección de datos personales (PII) | I12: Formalizar el procedimiento único de atención de derechos ARCO+ (ver Módulo 1, sección C). | J12: DPD
B13: CRÍTICA | C13: 0-3 meses | D13: M2 · Madurez Institucional | E13: P5 | F13: Proceso de revisión y mejora continua de los procedimientos de protección de datos | G13: 1 | H13: Cláusula 10.1 Mejora continua | I13: Establecer un ciclo anual de revisión de procedimientos de protección de datos, con responsable y fecha de revisión. | J13: DPD
B14: CRÍTICA | C14: 0-3 meses | D14: M2 · Madurez Institucional | E14: R1 | F14: Análisis de riesgos formal para el tratamiento de datos personales | G14: 1 | H14: Cláusula 6.1 / 8.2 Evaluación de riesgos de seguridad de la información | I14: Formalizar la metodología de análisis de riesgos y aplicarla de forma recurrente (ver Módulo 1, E2). | J14: TI + DPD
B15: CRÍTICA | C15: 0-3 meses | D15: M2 · Madurez Institucional | E15: A1 | F15: Auditorías internas periódicas de cumplimiento en protección de datos | G15: 1 | H15: Cláusula 9.2 Auditoría interna | I15: Ver Módulo 1, F2. | J15: Auditoría/Dirección
B16: CRÍTICA | C16: 0-3 meses | D16: M2 · Madurez Institucional | E16: A3 | F16: Hallazgos de auditoría documentados, priorizados e implementados con seguimiento | G16: 1 | H16: Cláusula 10.1 Mejora continua | I16: Implementar un plan de acción con seguimiento formal para cada hallazgo de auditoría. | J16: DPD + Dirección
B17: CRÍTICA | C17: 0-3 meses | D17: M2 · Madurez Institucional | E17: CC2 | F17: Capacitaciones formales y periódicas sobre protección de datos a todos los niveles | G17: 1 | H17: A.6.3 Concienciación, educación y formación en seguridad de la información | I17: Implementar un plan de capacitación anual, con registro de asistencia y evaluación de efectividad. | J17: Talento Humano + DPD
B18: CRÍTICA | C18: 0-3 meses | D18: M2 · Madurez Institucional | E18: R3 | F18: Evaluaciones de Impacto en Protección de Datos (EIPD) cuando corresponde | G18: 2 | H18: Cláusula 8.2 Evaluación de riesgos de seguridad de la información | I18: Ver Módulo 1, E3. | J18: DPD
B19: CRÍTICA | C19: 0-3 meses | D19: M1 · Cumplimiento LOPDP/RGLOPDP | E19: A4 | F19: Inventario actualizado de flujos de datos (quién recibe, quién envía, con qué propósito) | G19: No | H19: A.5.9 / A.8.1 Dispositivos de usuario final | I19: Elaborar un diagrama de flujos de datos personales (origen, destino, medio, finalidad) y mantenerlo actualizado. | J19: DPD + TI
B20: CRÍTICA | C20: 0-3 meses | D20: M1 · Cumplimiento LOPDP/RGLOPDP | E20: C3 | F20: Mecanismo formal para solicitudes de Cancelación / Supresión de datos | G20: No | H20: A.5.34 Privacidad y protección de datos personales (PII) | I20: Definir el procedimiento y las excepciones legales de conservación aplicables a la supresión de datos. | J20: DPD + Secretaría/Archivo
B21: CRÍTICA | C21: 0-3 meses | D21: M1 · Cumplimiento LOPDP/RGLOPDP | E21: C4 | F21: Mecanismo formal para solicitudes de Oposición al tratamiento | G21: No | H21: A.5.34 Privacidad y protección de datos personales (PII) | I21: Incorporar la oposición como opción explícita en los formatos de consentimiento y en el procedimiento de derechos. | J21: DPD + Secretaría
B22: CRÍTICA | C22: 0-3 meses | D22: M1 · Cumplimiento LOPDP/RGLOPDP | E22: E4 | F22: Procedimiento documentado para notificación de vulneraciones de seguridad | G22: No | H22: A.5.24 Planificación y preparación de la gestión de incidentes / A.6.8 Reporte de eventos | I22: Documentar el procedimiento de gestión y notificación de incidentes/vulneraciones, con roles, plazos y plantillas de notificación. | J22: TI + DPD
B23: CRÍTICA | C23: 0-3 meses | D23: M1 · Cumplimiento LOPDP/RGLOPDP | E23: E6 | F23: Políticas de anonimización, cifrado y eliminación segura de datos | G23: No | H23: A.8.24 Uso de criptografía / A.8.10 Eliminación de la información | I23: Definir estándares de cifrado para datos en reposo/tránsito y un procedimiento de borrado seguro para bajas de equipos y medios. | J23: TI
B24: CRÍTICA | C24: 0-3 meses | D24: M1 · Cumplimiento LOPDP/RGLOPDP | E24: E7 | F24: Señalización visible en zonas con cámaras de seguridad | G24: No | H24: A.7.4 Monitoreo de seguridad física | I24: Instalar señalética visible en todas las zonas con cámaras, indicando finalidad y responsable del tratamiento. | J24: Administrativo + DPD
B25: CRÍTICA | C25: 0-3 meses | D25: M1 · Cumplimiento LOPDP/RGLOPDP | E25: F1 | F25: Capacitaciones periódicas a docentes, autoridades y estudiantes sobre protección de datos | G25: No | H25: A.6.3 Concienciación, educación y formación en seguridad de la información | I25: Implementar un plan anual de capacitación en LOPDP y seguridad de la información para todos los roles. | J25: Talento Humano + DPD
B26: CRÍTICA | C26: 0-3 meses | D26: M1 · Cumplimiento LOPDP/RGLOPDP | E26: F3 | F26: Política de retención y eliminación de datos documentada y aplicada | G26: No | H26: A.5.33 Protección de los registros / A.8.10 Eliminación de la información | I26: Aprobar la política de retención (ver A3) y ejecutar depuraciones periódicas verificables. | J26: DPD + Archivo
B27: CRÍTICA | C27: 0-3 meses | D27: M2 · Madurez Institucional | E27: P1 | F27: Procesos de tratamiento de datos documentados, aprobados y comunicados al personal | G27: 2 | H27: A.5.37 Procedimientos operativos documentados | I27: Documentar y aprobar los procedimientos clave de tratamiento de datos y capacitar al personal en su aplicación. | J27: DPD + dueños de proceso
B28: CRÍTICA | C28: 0-3 meses | D28: M2 · Madurez Institucional | E28: P4 | F28: Procedimientos para gestión de incidentes y brechas de datos | G28: 1 | H28: A.5.24 Planificación y preparación de la gestión de incidentes | I28: Aprobar el procedimiento de gestión de incidentes de seguridad de la información con roles y tiempos de respuesta. | J28: TI + DPD
B29: CRÍTICA | C29: 0-3 meses | D29: M2 · Madurez Institucional | E29: R2 | F29: Controles, responsables y plazos de mitigación asignados a los riesgos identificados | G29: 2 | H29: Cláusula 6.1.3 Tratamiento de riesgos de seguridad de la información | I29: Mantener una matriz de riesgos con controles, responsable y fecha de mitigación, revisada periódicamente. | J29: TI + DPD
B30: CRÍTICA | C30: 0-3 meses | D30: M2 · Madurez Institucional | E30: A2 | F30: Indicadores y métricas de cumplimiento monitoreados regularmente | G30: 1 | H30: Cláusula 9.1 Monitoreo, medición, análisis y evaluación | I30: Definir un tablero de indicadores de cumplimiento LOPDP y revisarlo trimestralmente. | J30: DPD
B31: CRÍTICA | C31: 0-3 meses | D31: M2 · Madurez Institucional | E31: A4 | F31: Aplicación de un ciclo de mejora continua (PHVA) en la gestión de datos personales | G31: 1 | H31: Cláusula 10.1 Mejora continua | I31: Adoptar formalmente el ciclo Planificar-Hacer-Verificar-Actuar como método de gestión del sistema de protección de datos. | J31: DPD + Dirección
B32: CRÍTICA | C32: 0-3 meses | D32: M3 · Gobernanza Tecnológica | E32: TA2 | F32: Inventario actualizado de software y licencias | G32: Parcial | H32: A.5.9 Inventario de información y otros activos asociados / A.8.19 Instalación de software | I32: Levantar y mantener un inventario de software y licencias, con control de instalación autorizada. | J32: TI
B33: CRÍTICA | C33: 0-3 meses | D33: M3 · Gobernanza Tecnológica | E33: SI3 | F33: Controles de acceso basados en roles (RBAC) o perfiles de usuario | G33: No | H33: A.5.15 Control de acceso / A.8.2 Derechos de acceso privilegiado / A.8.3 Restricción de acceso a la información | I33: Implementar perfiles de acceso por rol en todos los sistemas que traten datos personales, con revisión periódica de permisos. | J33: TI
B34: CRÍTICA | C34: 0-3 meses | D34: M3 · Gobernanza Tecnológica | E34: SEC3 | F34: Herramientas de protección perimetral (firewall, antivirus, IDS/IPS) | G34: Parcial | H34: A.8.7 Protección contra código malicioso / A.8.20 Seguridad de redes | I34: Implementar y mantener firewall, antivirus/antimalware centralizado y, cuando el presupuesto lo permita, IDS/IPS. | J34: TI
B35: CRÍTICA | C35: 0-3 meses | D35: M3 · Gobernanza Tecnológica | E35: SEC6 | F35: Pruebas de seguridad (pentesting, ethical hacking) periódicas | G35: Parcial | H35: A.8.8 Gestión de vulnerabilidades técnicas / A.8.29 Pruebas de seguridad | I35: Ver Módulo 1, F4. | J35: TI
B36: CRÍTICA | C36: 0-3 meses | D36: M3 · Gobernanza Tecnológica | E36: CN2 | F36: Aplicación del Esquema Gubernamental de Seguridad de la Información (EGSI) o similar | G36: No | H36: A.5.31 Requisitos legales, estatutarios, regulatorios y contractuales / Cláusula 4.2 | I36: Adoptar los controles del EGSI aplicables a instituciones educativas y mapearlos contra el Anexo A de ISO/IEC 27001:2022. | J36: TI + DPD
B37: CRÍTICA | C37: 0-3 meses | D37: M2 · Madurez Institucional | E37: G3 | F37: Políticas institucionales formalizadas sobre privacidad y protección de datos personales | G37: 3 | H37: A.5.1 Políticas de seguridad de la información | I37: Aprobar y difundir la política institucional de protección de datos personales. | J37: Dirección + DPD
B38: CRÍTICA | C38: 0-3 meses | D38: M1 · Cumplimiento LOPDP/RGLOPDP | E38: D1 | F38: Delegado de Protección de Datos (DPD) formalmente designado | G38: No | H38: A.5.2 Roles y responsabilidades de seguridad de la información | I38: Formalizar por escrito la designación del DPD (o encargado equivalente), notificarla y publicar sus datos de contacto. | J38: Dirección/Rectorado
B39: CRÍTICA | C39: 0-3 meses | D39: M2 · Madurez Institucional | E39: G2 | F39: Liderazgo y compromiso de la alta dirección con el cumplimiento normativo | G39: 1 | H39: Cláusula 5.1 Liderazgo y compromiso | I39: Incluir la protección de datos como punto permanente en la planificación estratégica y en los comités de dirección. | J39: Rectorado/Dirección
B40: CRÍTICA | C40: 0-3 meses | D40: M2 · Madurez Institucional | E40: CC1 | F40: Conocimiento básico del personal sobre la LOPDP y sus obligaciones | G40: 2 | H40: A.6.3 Concienciación, educación y formación en seguridad de la información | I40: Difundir una guía básica de LOPDP a todo el personal como parte de la inducción institucional. | J40: Talento Humano
B41: CRÍTICA | C41: 0-3 meses | D41: M3 · Gobernanza Tecnológica | E41: SI2 | F41: Integración entre los sistemas de información documentada | G41: Parcial | H41: A.8.9 Gestión de la configuración / A.5.9 | I41: Documentar las integraciones existentes (APIs, exportaciones, sincronizaciones) entre sistemas. | J41: TI
B42: CRÍTICA | C42: 0-3 meses | D42: M3 · Gobernanza Tecnológica | E42: SV1 | F42: Sistema de gestión de incidentes y solicitudes TI (mesa de ayuda / help desk) | G42: No | H42: A.5.24 Planificación y preparación de la gestión de incidentes | I42: Implementar un canal único (mesa de ayuda) para reportar incidentes y solicitudes TI, incluyendo los de seguridad de datos. | J42: TI
B43: CRÍTICA | C43: 0-3 meses | D43: M3 · Gobernanza Tecnológica | E43: SV3 | F43: Acuerdos de Nivel de Servicio (SLA) con proveedores tecnológicos críticos | G43: No | H43: A.5.20 Abordar la seguridad de la información en los acuerdos con proveedores | I43: Formalizar SLA con los proveedores tecnológicos críticos (conectividad, plataforma académica, nube). | J43: TI + Jurídico
B44: CRÍTICA | C44: 0-3 meses | D44: M3 · Gobernanza Tecnológica | E44: SV4 | F44: Gestión de cambios formalizada para modificaciones en sistemas productivos | G44: No | H44: A.8.32 Gestión de cambios | I44: Implementar un procedimiento de gestión de cambios (solicitud, prueba, aprobación, registro) para sistemas productivos. | J44: TI
B45: CRÍTICA | C45: 0-3 meses | D45: M3 · Gobernanza Tecnológica | E45: CN3 | F45: Sistemas de información con requisitos de protección de datos desde su diseño (privacy by design) | G45: No | H45: A.8.25 Ciclo de vida de desarrollo seguro / A.5.34 | I45: Ver Módulo 2, CC3. | J45: TI + DPD
B46: ALTA | C46: 3-6 meses | D46: M2 · Madurez Institucional | E46: G4 | F46: Presupuesto asignado para actividades de cumplimiento y protección de datos | G46: 2 | H46: Cláusula 7.1 Recursos | I46: Asignar una partida presupuestaria anual específica para protección de datos y seguridad de la información. | J46: Dirección/Financiero
B47: ALTA | C47: 3-6 meses | D47: M2 · Madurez Institucional | E47: R4 | F47: Medidas de seguridad técnica (cifrado, control de acceso, logs) implementadas y documentadas | G47: 1 | H47: A.8.24 Uso de criptografía / A.8.15 Registro (logging) / A.8.3 Restricción de acceso | I47: Documentar formalmente los controles técnicos vigentes y las brechas frente al estándar deseado. | J47: TI
B48: ALTA | C48: 3-6 meses | D48: M1 · Cumplimiento LOPDP/RGLOPDP | E48: B1 | F48: Información al titular sobre qué datos se recopilan, cómo se usan y con quién se comparten | G48: No | H48: A.5.34 Privacidad y protección de datos personales (PII) | I48: Publicar avisos de privacidad claros y accesibles (portal web, matrícula, carteleras) para cada finalidad de tratamiento. | J48: DPD + Comunicación/Secretaría
B49: ALTA | C49: 3-6 meses | D49: M1 · Cumplimiento LOPDP/RGLOPDP | E49: B2 | F49: Obtención de consentimiento explícito antes de recopilar o procesar datos personales | G49: No | H49: A.5.34 Privacidad y protección de datos personales (PII) | I49: Implementar un formato de consentimiento informado (físico o digital) con registro de evidencia, diferenciado por finalidad. | J49: DPD + Secretaría
B50: ALTA | C50: 3-6 meses | D50: M1 · Cumplimiento LOPDP/RGLOPDP | E50: D4 | F50: Verificación de que los encargados externos cumplen con la LOPDP | G50: No | H50: A.5.22 Seguimiento, revisión y gestión de cambios en los servicios de proveedores | I50: Establecer una evaluación periódica (cuestionario o auditoría) del cumplimiento de los encargados de tratamiento. | J50: DPD + TI
B51: ALTA | C51: 3-6 meses | D51: M1 · Cumplimiento LOPDP/RGLOPDP | E51: E1 | F51: Medidas de seguridad técnicas y organizativas para proteger datos personales | G51: No | H51: A.5.1 Políticas de seguridad de la información / Cláusula 8 Operación | I51: Definir e implementar un conjunto mínimo de controles técnicos y organizativos alineados a ISO/IEC 27001:2022, priorizados por riesgo. | J51: TI + DPD
B52: ALTA | C52: 3-6 meses | D52: M1 · Cumplimiento LOPDP/RGLOPDP | E52: E2 | F52: Análisis de riesgos que incluya el tratamiento de datos personales | G52: No | H52: Cláusula 6.1 / 8.2 Evaluación de riesgos de seguridad de la información | I52: Ejecutar un análisis de riesgos de protección de datos (activos, amenazas, vulnerabilidades, impacto) y actualizarlo anualmente. | J52: TI + DPD
B53: ALTA | C53: 3-6 meses | D53: M1 · Cumplimiento LOPDP/RGLOPDP | E53: F4 | F53: Pruebas de penetración o análisis de seguridad informática | G53: Parcial | H53: A.8.29 Pruebas de seguridad en el desarrollo y aceptación / A.5.36 Cumplimiento de políticas | I53: Contratar o ejecutar pruebas de seguridad (pentesting/vulnerability assessment) al menos una vez al año sobre sistemas críticos. | J53: TI
B54: ALTA | C54: 3-6 meses | D54: M2 · Madurez Institucional | E54: CC3 | F54: Cultura de privacidad por diseño en el desarrollo de nuevos proyectos o sistemas | G54: 1 | H54: A.8.25 Ciclo de vida de desarrollo seguro / A.5.34 | I54: Incluir una lista de verificación de privacidad por diseño en la adquisición o desarrollo de todo nuevo sistema. | J54: TI + DPD
B55: ALTA | C55: 3-6 meses | D55: M3 · Gobernanza Tecnológica | E55: TG1 | F55: Plan estratégico de tecnología de la información (PETI) vigente y alineado al plan institucional | G55: Parcial | H55: Cláusula 5.2 Política / A.5.1 Políticas de seguridad de la información | I55: Elaborar un PETI a 2-3 años alineado al plan educativo institucional, incluyendo protección de datos como eje. | J55: Dirección + TI
B56: ALTA | C56: 3-6 meses | D56: M3 · Gobernanza Tecnológica | E56: TA3 | F56: Identificación y clasificación de los sistemas de información por criticidad | G56: Parcial | H56: A.5.12 Clasificación de la información | I56: Clasificar los sistemas de información según criticidad e impacto en caso de indisponibilidad o compromiso. | J56: TI
B57: ALTA | C57: 3-6 meses | D57: M3 · Gobernanza Tecnológica | E57: TA4 | F57: Gestión del ciclo de vida de los activos tecnológicos (adquisición, operación, baja) | G57: No | H57: A.5.10 Uso aceptable de los activos / A.5.11 Devolución de activos / A.7.14 Eliminación segura de equipos | I57: Definir el procedimiento de ciclo de vida de activos, incluyendo borrado seguro previo a la baja o reasignación. | J57: TI
B58: ALTA | C58: 3-6 meses | D58: M3 · Gobernanza Tecnológica | E58: SI1 | F58: Sistemas de información documentados (arquitectura, flujos de datos, usuarios) | G58: Parcial | H58: A.5.9 / A.8.9 Gestión de la configuración | I58: Documentar la arquitectura, flujos de datos y usuarios de los sistemas de información institucionales. | J58: TI
B59: ALTA | C59: 3-6 meses | D59: M3 · Gobernanza Tecnológica | E59: SI5 | F59: Planes de continuidad o contingencia para sistemas de información críticos | G59: Parcial | H59: A.5.29 Seguridad de la información durante la disrupción / A.5.30 Preparación TIC para la continuidad del negocio | I59: Elaborar un plan de continuidad/contingencia para los sistemas críticos, con pruebas periódicas. | J59: TI + Dirección
B60: ALTA | C60: 3-6 meses | D60: M3 · Gobernanza Tecnológica | E60: SI6 | F60: Respaldos periódicos de bases de datos y sistemas con pruebas de restauración | G60: Parcial | H60: A.8.13 Respaldo de la información | I60: Formalizar la política de respaldos (frecuencia, retención) y ejecutar pruebas de restauración periódicas documentadas. | J60: TI
B61: ALTA | C61: 3-6 meses | D61: M3 · Gobernanza Tecnológica | E61: SEC4 | F61: Segmentación de redes y control de acceso a la infraestructura | G61: No | H61: A.8.22 Segregación de redes / A.8.20 Seguridad de redes | I61: Segmentar la red (administrativa, académica, invitados/Wi-Fi) y controlar el acceso entre segmentos. | J61: TI
B62: ALTA | C62: 3-6 meses | D62: M3 · Gobernanza Tecnológica | E62: SV2 | F62: Medición de tiempos de respuesta y resolución de incidentes tecnológicos | G62: No | H62: Cláusula 9.1 Monitoreo, medición, análisis y evaluación | I62: Definir y monitorear indicadores de tiempo de respuesta y resolución de incidentes TI. | J62: TI
B63: ALTA | C63: 3-6 meses | D63: M3 · Gobernanza Tecnológica | E63: CN1 | F63: Gestión de TI alineada con la Ley de Comercio Electrónico, Firmas y Mensajes de Datos | G63: No | H63: A.5.31 Requisitos legales, estatutarios, regulatorios y contractuales | I63: Verificar y documentar el cumplimiento de la normativa de comercio electrónico y firma electrónica en los procesos digitales institucionales. | J63: Jurídico + TI
B64: ALTA | C64: 3-6 meses | D64: M2 · Madurez Institucional | E64: R5 | F64: Pruebas periódicas de seguridad (pentesting, análisis de vulnerabilidades) | G64: 3 | H64: A.8.8 Gestión de vulnerabilidades técnicas | I64: Ver Módulo 1, E5 y F4. | J64: TI
B65: ALTA | C65: 3-6 meses | D65: M2 · Madurez Institucional | E65: T2 | F65: Verificación de que los encargados externos cumplen estándares equivalentes de protección de datos | G65: 3 | H65: A.5.22 Seguimiento, revisión y gestión de cambios en los servicios de proveedores | I65: Ver Módulo 1, D4. | J65: DPD + TI
B66: ALTA | C66: 3-6 meses | D66: M2 · Madurez Institucional | E66: T3 | F66: Registro actualizado de encargados de tratamiento externos | G66: 3 | H66: A.5.19 Seguridad de la información en las relaciones con proveedores | I66: Mantener un registro único y actualizado de todos los encargados de tratamiento (plataformas, proveedores TI, aliados). | J66: DPD
B67: ALTA | C67: 3-6 meses | D67: M1 · Cumplimiento LOPDP/RGLOPDP | E67: C5 | F67: Cumplimiento de los plazos legales para atender derechos de los titulares | G67: Parcial | H67: A.5.34 / A.9.1 Monitoreo, medición, análisis y evaluación (cláusula 9.1) | I67: Establecer indicadores de tiempo de respuesta y un registro de solicitudes con seguimiento de vencimientos. | J67: DPD
B68: ALTA | C68: 3-6 meses | D68: M2 · Madurez Institucional | E68: CC4 | F68: Consecuencias formales (régimen disciplinario) ante incumplimiento de normas de privacidad | G68: 2 | H68: A.6.4 Proceso disciplinario | I68: Incorporar el incumplimiento de las normas de protección de datos al reglamento interno de trabajo/régimen disciplinario. | J68: Talento Humano + Jurídico
B69: ALTA | C69: 3-6 meses | D69: M2 · Madurez Institucional | E69: T1 | F69: Cláusulas de protección de datos incluidas en los contratos con proveedores | G69: 3 | H69: A.5.20 Abordar la seguridad de la información en los acuerdos con proveedores | I69: Ver Módulo 1, D2. | J69: Jurídico + DPD
B70: ALTA | C70: 3-6 meses | D70: M3 · Gobernanza Tecnológica | E70: TA1 | F70: Inventario actualizado de hardware (equipos, servidores, dispositivos de red) | G70: Parcial | H70: A.5.9 Inventario de información y otros activos asociados | I70: Levantar y mantener un inventario de hardware con responsable, ubicación y criticidad. | J70: TI
B71: ALTA | C71: 3-6 meses | D71: M3 · Gobernanza Tecnológica | E71: SI4 | F71: Registro de logs de auditoría en los sistemas de información (accesos, cambios, consultas) | G71: Parcial | H71: A.8.15 Registro (logging) / A.8.16 Actividades de monitoreo | I71: Habilitar el registro de logs de acceso y cambios en los sistemas críticos, con retención y revisión periódica. | J71: TI
B72: ALTA | C72: 3-6 meses | D72: M3 · Gobernanza Tecnológica | E72: SEC2 | F72: Gestión de parches y actualizaciones de seguridad en sistemas operativos y aplicaciones | G72: Parcial | H72: A.8.8 Gestión de vulnerabilidades técnicas / A.8.9 Gestión de la configuración | I72: Implementar un proceso formal y calendarizado de gestión de parches y actualizaciones. | J72: TI

Sheet Plan_Institucion_C
B2: PLAN DE CIERRE DE BRECHAS · Institución C (índice global actual: 31.8%)
B4: Prioridad | C4: Plazo | D4: Módulo | E4: ID | F4: Criterio / Dimensión | G4: Estado actual | H4: Control ISO/IEC 27001:2022 | I4: Acción correctiva recomendada | J4: Responsable sugerido
B5: CRÍTICA | C5: 0-3 meses | D5: M1 · Cumplimiento LOPDP/RGLOPDP | E5: B5 | F5: Política de uso de cookies con consentimiento informado | G5: No | H5: A.5.34 Privacidad y protección de datos personales (PII) | I5: Implementar aviso/banner de cookies con opciones de aceptación granular en los sitios y plataformas institucionales. | J5: TI + DPD
B6: CRÍTICA | C6: 0-3 meses | D6: M1 · Cumplimiento LOPDP/RGLOPDP | E6: D2 | F6: Contratos firmados con encargados de tratamiento externos | G6: No | H6: A.5.20 Abordar la seguridad de la información en los acuerdos con proveedores | I6: Incorporar cláusulas de protección de datos en todo contrato con proveedores que traten datos personales; regularizar los vigentes. | J6: Jurídico + DPD
B7: CRÍTICA | C7: 0-3 meses | D7: M1 · Cumplimiento LOPDP/RGLOPDP | E7: E3 | F7: Evaluación de Impacto en Protección de Datos (EIPD) para tratamientos de alto riesgo | G7: No | H7: Cláusula 8.2 Evaluación de riesgos de seguridad de la información | I7: Elaborar EIPD para los tratamientos de mayor riesgo (video-vigilancia, biometría, salud, datos de menores) antes de su implementación o de forma retroactiva. | J7: DPD
B8: CRÍTICA | C8: 0-3 meses | D8: M1 · Cumplimiento LOPDP/RGLOPDP | E8: E5 | F8: Análisis de vulnerabilidades informáticas relacionadas con datos personales | G8: No | H8: A.8.8 Gestión de vulnerabilidades técnicas | I8: Implementar un proceso periódico de identificación y remediación de vulnerabilidades en sistemas que tratan datos personales. | J8: TI
B9: CRÍTICA | C9: 0-3 meses | D9: M1 · Cumplimiento LOPDP/RGLOPDP | E9: F2 | F9: Revisiones periódicas y auditorías de cumplimiento de protección de datos | G9: No | H9: Cláusula 9.2 Auditoría interna | I9: Planificar auditorías internas anuales de cumplimiento LOPDP con informe de hallazgos y seguimiento. | J9: Auditoría interna/Dirección + DPD
B10: CRÍTICA | C10: 0-3 meses | D10: M2 · Madurez Institucional | E10: G1 | F10: Estructura de gobierno de datos con roles y responsabilidades definidos (Responsable, DPD, Encargados) | G10: 1 | H10: A.5.2 Roles y responsabilidades de seguridad de la información | I10: Definir y aprobar formalmente el organigrama de gobierno de datos (RACI) con Responsable, DPD y Encargados. | J10: Dirección
B11: CRÍTICA | C11: 0-3 meses | D11: M2 · Madurez Institucional | E11: P2 | F11: Registro de Actividades de Tratamiento (RAT) actualizado | G11: 1 | H11: A.5.9 Inventario de información y otros activos asociados | I11: Levantar el RAT y establecer una revisión periódica (al menos semestral) para mantenerlo vigente. | J11: DPD
B12: CRÍTICA | C12: 0-3 meses | D12: M2 · Madurez Institucional | E12: P3 | F12: Procedimientos formales para responder derechos ARCO+ de los titulares | G12: 1 | H12: A.5.34 Privacidad y protección de datos personales (PII) | I12: Formalizar el procedimiento único de atención de derechos ARCO+ (ver Módulo 1, sección C). | J12: DPD
B13: CRÍTICA | C13: 0-3 meses | D13: M2 · Madurez Institucional | E13: P5 | F13: Proceso de revisión y mejora continua de los procedimientos de protección de datos | G13: 1 | H13: Cláusula 10.1 Mejora continua | I13: Establecer un ciclo anual de revisión de procedimientos de protección de datos, con responsable y fecha de revisión. | J13: DPD
B14: CRÍTICA | C14: 0-3 meses | D14: M2 · Madurez Institucional | E14: R1 | F14: Análisis de riesgos formal para el tratamiento de datos personales | G14: 1 | H14: Cláusula 6.1 / 8.2 Evaluación de riesgos de seguridad de la información | I14: Formalizar la metodología de análisis de riesgos y aplicarla de forma recurrente (ver Módulo 1, E2). | J14: TI + DPD
B15: CRÍTICA | C15: 0-3 meses | D15: M2 · Madurez Institucional | E15: A1 | F15: Auditorías internas periódicas de cumplimiento en protección de datos | G15: 1 | H15: Cláusula 9.2 Auditoría interna | I15: Ver Módulo 1, F2. | J15: Auditoría/Dirección
B16: CRÍTICA | C16: 0-3 meses | D16: M2 · Madurez Institucional | E16: A3 | F16: Hallazgos de auditoría documentados, priorizados e implementados con seguimiento | G16: 1 | H16: Cláusula 10.1 Mejora continua | I16: Implementar un plan de acción con seguimiento formal para cada hallazgo de auditoría. | J16: DPD + Dirección
B17: CRÍTICA | C17: 0-3 meses | D17: M2 · Madurez Institucional | E17: CC2 | F17: Capacitaciones formales y periódicas sobre protección de datos a todos los niveles | G17: 2 | H17: A.6.3 Concienciación, educación y formación en seguridad de la información | I17: Implementar un plan de capacitación anual, con registro de asistencia y evaluación de efectividad. | J17: Talento Humano + DPD
B18: CRÍTICA | C18: 0-3 meses | D18: M2 · Madurez Institucional | E18: R3 | F18: Evaluaciones de Impacto en Protección de Datos (EIPD) cuando corresponde | G18: 1 | H18: Cláusula 8.2 Evaluación de riesgos de seguridad de la información | I18: Ver Módulo 1, E3. | J18: DPD
B19: CRÍTICA | C19: 0-3 meses | D19: M1 · Cumplimiento LOPDP/RGLOPDP | E19: A4 | F19: Inventario actualizado de flujos de datos (quién recibe, quién envía, con qué propósito) | G19: Parcial | H19: A.5.9 / A.8.1 Dispositivos de usuario final | I19: Elaborar un diagrama de flujos de datos personales (origen, destino, medio, finalidad) y mantenerlo actualizado. | J19: DPD + TI
B20: CRÍTICA | C20: 0-3 meses | D20: M1 · Cumplimiento LOPDP/RGLOPDP | E20: C3 | F20: Mecanismo formal para solicitudes de Cancelación / Supresión de datos | G20: Parcial | H20: A.5.34 Privacidad y protección de datos personales (PII) | I20: Definir el procedimiento y las excepciones legales de conservación aplicables a la supresión de datos. | J20: DPD + Secretaría/Archivo
B21: CRÍTICA | C21: 0-3 meses | D21: M1 · Cumplimiento LOPDP/RGLOPDP | E21: C4 | F21: Mecanismo formal para solicitudes de Oposición al tratamiento | G21: Parcial | H21: A.5.34 Privacidad y protección de datos personales (PII) | I21: Incorporar la oposición como opción explícita en los formatos de consentimiento y en el procedimiento de derechos. | J21: DPD + Secretaría
B22: CRÍTICA | C22: 0-3 meses | D22: M1 · Cumplimiento LOPDP/RGLOPDP | E22: E4 | F22: Procedimiento documentado para notificación de vulneraciones de seguridad | G22: No | H22: A.5.24 Planificación y preparación de la gestión de incidentes / A.6.8 Reporte de eventos | I22: Documentar el procedimiento de gestión y notificación de incidentes/vulneraciones, con roles, plazos y plantillas de notificación. | J22: TI + DPD
B23: CRÍTICA | C23: 0-3 meses | D23: M1 · Cumplimiento LOPDP/RGLOPDP | E23: E6 | F23: Políticas de anonimización, cifrado y eliminación segura de datos | G23: No | H23: A.8.24 Uso de criptografía / A.8.10 Eliminación de la información | I23: Definir estándares de cifrado para datos en reposo/tránsito y un procedimiento de borrado seguro para bajas de equipos y medios. | J23: TI
B24: CRÍTICA | C24: 0-3 meses | D24: M1 · Cumplimiento LOPDP/RGLOPDP | E24: E7 | F24: Señalización visible en zonas con cámaras de seguridad | G24: Parcial | H24: A.7.4 Monitoreo de seguridad física | I24: Instalar señalética visible en todas las zonas con cámaras, indicando finalidad y responsable del tratamiento. | J24: Administrativo + DPD
B25: CRÍTICA | C25: 0-3 meses | D25: M1 · Cumplimiento LOPDP/RGLOPDP | E25: F1 | F25: Capacitaciones periódicas a docentes, autoridades y estudiantes sobre protección de datos | G25: No | H25: A.6.3 Concienciación, educación y formación en seguridad de la información | I25: Implementar un plan anual de capacitación en LOPDP y seguridad de la información para todos los roles. | J25: Talento Humano + DPD
B26: CRÍTICA | C26: 0-3 meses | D26: M1 · Cumplimiento LOPDP/RGLOPDP | E26: F3 | F26: Política de retención y eliminación de datos documentada y aplicada | G26: No | H26: A.5.33 Protección de los registros / A.8.10 Eliminación de la información | I26: Aprobar la política de retención (ver A3) y ejecutar depuraciones periódicas verificables. | J26: DPD + Archivo
B27: CRÍTICA | C27: 0-3 meses | D27: M2 · Madurez Institucional | E27: P1 | F27: Procesos de tratamiento de datos documentados, aprobados y comunicados al personal | G27: 2 | H27: A.5.37 Procedimientos operativos documentados | I27: Documentar y aprobar los procedimientos clave de tratamiento de datos y capacitar al personal en su aplicación. | J27: DPD + dueños de proceso
B28: CRÍTICA | C28: 0-3 meses | D28: M2 · Madurez Institucional | E28: P4 | F28: Procedimientos para gestión de incidentes y brechas de datos | G28: 1 | H28: A.5.24 Planificación y preparación de la gestión de incidentes | I28: Aprobar el procedimiento de gestión de incidentes de seguridad de la información con roles y tiempos de respuesta. | J28: TI + DPD
B29: CRÍTICA | C29: 0-3 meses | D29: M2 · Madurez Institucional | E29: R2 | F29: Controles, responsables y plazos de mitigación asignados a los riesgos identificados | G29: 2 | H29: Cláusula 6.1.3 Tratamiento de riesgos de seguridad de la información | I29: Mantener una matriz de riesgos con controles, responsable y fecha de mitigación, revisada periódicamente. | J29: TI + DPD
B30: CRÍTICA | C30: 0-3 meses | D30: M2 · Madurez Institucional | E30: A2 | F30: Indicadores y métricas de cumplimiento monitoreados regularmente | G30: 2 | H30: Cláusula 9.1 Monitoreo, medición, análisis y evaluación | I30: Definir un tablero de indicadores de cumplimiento LOPDP y revisarlo trimestralmente. | J30: DPD
B31: CRÍTICA | C31: 0-3 meses | D31: M2 · Madurez Institucional | E31: A4 | F31: Aplicación de un ciclo de mejora continua (PHVA) en la gestión de datos personales | G31: 1 | H31: Cláusula 10.1 Mejora continua | I31: Adoptar formalmente el ciclo Planificar-Hacer-Verificar-Actuar como método de gestión del sistema de protección de datos. | J31: DPD + Dirección
B32: CRÍTICA | C32: 0-3 meses | D32: M3 · Gobernanza Tecnológica | E32: TA2 | F32: Inventario actualizado de software y licencias | G32: No | H32: A.5.9 Inventario de información y otros activos asociados / A.8.19 Instalación de software | I32: Levantar y mantener un inventario de software y licencias, con control de instalación autorizada. | J32: TI
B33: CRÍTICA | C33: 0-3 meses | D33: M3 · Gobernanza Tecnológica | E33: SI3 | F33: Controles de acceso basados en roles (RBAC) o perfiles de usuario | G33: No | H33: A.5.15 Control de acceso / A.8.2 Derechos de acceso privilegiado / A.8.3 Restricción de acceso a la información | I33: Implementar perfiles de acceso por rol en todos los sistemas que traten datos personales, con revisión periódica de permisos. | J33: TI
B34: CRÍTICA | C34: 0-3 meses | D34: M3 · Gobernanza Tecnológica | E34: SEC3 | F34: Herramientas de protección perimetral (firewall, antivirus, IDS/IPS) | G34: No | H34: A.8.7 Protección contra código malicioso / A.8.20 Seguridad de redes | I34: Implementar y mantener firewall, antivirus/antimalware centralizado y, cuando el presupuesto lo permita, IDS/IPS. | J34: TI
B35: CRÍTICA | C35: 0-3 meses | D35: M3 · Gobernanza Tecnológica | E35: SEC6 | F35: Pruebas de seguridad (pentesting, ethical hacking) periódicas | G35: No | H35: A.8.8 Gestión de vulnerabilidades técnicas / A.8.29 Pruebas de seguridad | I35: Ver Módulo 1, F4. | J35: TI
B36: CRÍTICA | C36: 0-3 meses | D36: M3 · Gobernanza Tecnológica | E36: CN2 | F36: Aplicación del Esquema Gubernamental de Seguridad de la Información (EGSI) o similar | G36: No | H36: A.5.31 Requisitos legales, estatutarios, regulatorios y contractuales / Cláusula 4.2 | I36: Adoptar los controles del EGSI aplicables a instituciones educativas y mapearlos contra el Anexo A de ISO/IEC 27001:2022. | J36: TI + DPD
B37: CRÍTICA | C37: 0-3 meses | D37: M2 · Madurez Institucional | E37: G3 | F37: Políticas institucionales formalizadas sobre privacidad y protección de datos personales | G37: 2 | H37: A.5.1 Políticas de seguridad de la información | I37: Aprobar y difundir la política institucional de protección de datos personales. | J37: Dirección + DPD
B38: CRÍTICA | C38: 0-3 meses | D38: M1 · Cumplimiento LOPDP/RGLOPDP | E38: D1 | F38: Delegado de Protección de Datos (DPD) formalmente designado | G38: No | H38: A.5.2 Roles y responsabilidades de seguridad de la información | I38: Formalizar por escrito la designación del DPD (o encargado equivalente), notificarla y publicar sus datos de contacto. | J38: Dirección/Rectorado
B39: CRÍTICA | C39: 0-3 meses | D39: M2 · Madurez Institucional | E39: G2 | F39: Liderazgo y compromiso de la alta dirección con el cumplimiento normativo | G39: 2 | H39: Cláusula 5.1 Liderazgo y compromiso | I39: Incluir la protección de datos como punto permanente en la planificación estratégica y en los comités de dirección. | J39: Rectorado/Dirección
B40: CRÍTICA | C40: 0-3 meses | D40: M2 · Madurez Institucional | E40: CC1 | F40: Conocimiento básico del personal sobre la LOPDP y sus obligaciones | G40: 2 | H40: A.6.3 Concienciación, educación y formación en seguridad de la información | I40: Difundir una guía básica de LOPDP a todo el personal como parte de la inducción institucional. | J40: Talento Humano
B41: CRÍTICA | C41: 0-3 meses | D41: M3 · Gobernanza Tecnológica | E41: SI2 | F41: Integración entre los sistemas de información documentada | G41: Parcial | H41: A.8.9 Gestión de la configuración / A.5.9 | I41: Documentar las integraciones existentes (APIs, exportaciones, sincronizaciones) entre sistemas. | J41: TI
B42: CRÍTICA | C42: 0-3 meses | D42: M3 · Gobernanza Tecnológica | E42: SV1 | F42: Sistema de gestión de incidentes y solicitudes TI (mesa de ayuda / help desk) | G42: No | H42: A.5.24 Planificación y preparación de la gestión de incidentes | I42: Implementar un canal único (mesa de ayuda) para reportar incidentes y solicitudes TI, incluyendo los de seguridad de datos. | J42: TI
B43: CRÍTICA | C43: 0-3 meses | D43: M3 · Gobernanza Tecnológica | E43: SV3 | F43: Acuerdos de Nivel de Servicio (SLA) con proveedores tecnológicos críticos | G43: No | H43: A.5.20 Abordar la seguridad de la información en los acuerdos con proveedores | I43: Formalizar SLA con los proveedores tecnológicos críticos (conectividad, plataforma académica, nube). | J43: TI + Jurídico
B44: CRÍTICA | C44: 0-3 meses | D44: M3 · Gobernanza Tecnológica | E44: SV4 | F44: Gestión de cambios formalizada para modificaciones en sistemas productivos | G44: No | H44: A.8.32 Gestión de cambios | I44: Implementar un procedimiento de gestión de cambios (solicitud, prueba, aprobación, registro) para sistemas productivos. | J44: TI
B45: CRÍTICA | C45: 0-3 meses | D45: M3 · Gobernanza Tecnológica | E45: CN3 | F45: Sistemas de información con requisitos de protección de datos desde su diseño (privacy by design) | G45: Parcial | H45: A.8.25 Ciclo de vida de desarrollo seguro / A.5.34 | I45: Ver Módulo 2, CC3. | J45: TI + DPD
B46: ALTA | C46: 3-6 meses | D46: M2 · Madurez Institucional | E46: G4 | F46: Presupuesto asignado para actividades de cumplimiento y protección de datos | G46: 1 | H46: Cláusula 7.1 Recursos | I46: Asignar una partida presupuestaria anual específica para protección de datos y seguridad de la información. | J46: Dirección/Financiero
B47: ALTA | C47: 3-6 meses | D47: M2 · Madurez Institucional | E47: R4 | F47: Medidas de seguridad técnica (cifrado, control de acceso, logs) implementadas y documentadas | G47: 2 | H47: A.8.24 Uso de criptografía / A.8.15 Registro (logging) / A.8.3 Restricción de acceso | I47: Documentar formalmente los controles técnicos vigentes y las brechas frente al estándar deseado. | J47: TI
B48: ALTA | C48: 3-6 meses | D48: M1 · Cumplimiento LOPDP/RGLOPDP | E48: B1 | F48: Información al titular sobre qué datos se recopilan, cómo se usan y con quién se comparten | G48: Parcial | H48: A.5.34 Privacidad y protección de datos personales (PII) | I48: Publicar avisos de privacidad claros y accesibles (portal web, matrícula, carteleras) para cada finalidad de tratamiento. | J48: DPD + Comunicación/Secretaría
B49: ALTA | C49: 3-6 meses | D49: M1 · Cumplimiento LOPDP/RGLOPDP | E49: B2 | F49: Obtención de consentimiento explícito antes de recopilar o procesar datos personales | G49: Parcial | H49: A.5.34 Privacidad y protección de datos personales (PII) | I49: Implementar un formato de consentimiento informado (físico o digital) con registro de evidencia, diferenciado por finalidad. | J49: DPD + Secretaría
B50: ALTA | C50: 3-6 meses | D50: M1 · Cumplimiento LOPDP/RGLOPDP | E50: B4 | F50: Información a los titulares sobre cómo ejercer sus derechos ARCO+ | G50: No | H50: A.5.34 Privacidad y protección de datos personales (PII) | I50: Incluir en avisos de privacidad y canales institucionales el procedimiento y medios para ejercer derechos ARCO+. | J50: DPD + Comunicación
B51: ALTA | C51: 3-6 meses | D51: M1 · Cumplimiento LOPDP/RGLOPDP | E51: D4 | F51: Verificación de que los encargados externos cumplen con la LOPDP | G51: Parcial | H51: A.5.22 Seguimiento, revisión y gestión de cambios en los servicios de proveedores | I51: Establecer una evaluación periódica (cuestionario o auditoría) del cumplimiento de los encargados de tratamiento. | J51: DPD + TI
B52: ALTA | C52: 3-6 meses | D52: M1 · Cumplimiento LOPDP/RGLOPDP | E52: E1 | F52: Medidas de seguridad técnicas y organizativas para proteger datos personales | G52: Parcial | H52: A.5.1 Políticas de seguridad de la información / Cláusula 8 Operación | I52: Definir e implementar un conjunto mínimo de controles técnicos y organizativos alineados a ISO/IEC 27001:2022, priorizados por riesgo. | J52: TI + DPD
B53: ALTA | C53: 3-6 meses | D53: M1 · Cumplimiento LOPDP/RGLOPDP | E53: E2 | F53: Análisis de riesgos que incluya el tratamiento de datos personales | G53: Parcial | H53: Cláusula 6.1 / 8.2 Evaluación de riesgos de seguridad de la información | I53: Ejecutar un análisis de riesgos de protección de datos (activos, amenazas, vulnerabilidades, impacto) y actualizarlo anualmente. | J53: TI + DPD
B54: ALTA | C54: 3-6 meses | D54: M1 · Cumplimiento LOPDP/RGLOPDP | E54: F4 | F54: Pruebas de penetración o análisis de seguridad informática | G54: No | H54: A.8.29 Pruebas de seguridad en el desarrollo y aceptación / A.5.36 Cumplimiento de políticas | I54: Contratar o ejecutar pruebas de seguridad (pentesting/vulnerability assessment) al menos una vez al año sobre sistemas críticos. | J54: TI
B55: ALTA | C55: 3-6 meses | D55: M3 · Gobernanza Tecnológica | E55: TG1 | F55: Plan estratégico de tecnología de la información (PETI) vigente y alineado al plan institucional | G55: No | H55: Cláusula 5.2 Política / A.5.1 Políticas de seguridad de la información | I55: Elaborar un PETI a 2-3 años alineado al plan educativo institucional, incluyendo protección de datos como eje. | J55: Dirección + TI
B56: ALTA | C56: 3-6 meses | D56: M3 · Gobernanza Tecnológica | E56: TA3 | F56: Identificación y clasificación de los sistemas de información por criticidad | G56: No | H56: A.5.12 Clasificación de la información | I56: Clasificar los sistemas de información según criticidad e impacto en caso de indisponibilidad o compromiso. | J56: TI
B57: ALTA | C57: 3-6 meses | D57: M3 · Gobernanza Tecnológica | E57: TA4 | F57: Gestión del ciclo de vida de los activos tecnológicos (adquisición, operación, baja) | G57: Parcial | H57: A.5.10 Uso aceptable de los activos / A.5.11 Devolución de activos / A.7.14 Eliminación segura de equipos | I57: Definir el procedimiento de ciclo de vida de activos, incluyendo borrado seguro previo a la baja o reasignación. | J57: TI
B58: ALTA | C58: 3-6 meses | D58: M3 · Gobernanza Tecnológica | E58: SI1 | F58: Sistemas de información documentados (arquitectura, flujos de datos, usuarios) | G58: No | H58: A.5.9 / A.8.9 Gestión de la configuración | I58: Documentar la arquitectura, flujos de datos y usuarios de los sistemas de información institucionales. | J58: TI
B59: ALTA | C59: 3-6 meses | D59: M3 · Gobernanza Tecnológica | E59: SI5 | F59: Planes de continuidad o contingencia para sistemas de información críticos | G59: No | H59: A.5.29 Seguridad de la información durante la disrupción / A.5.30 Preparación TIC para la continuidad del negocio | I59: Elaborar un plan de continuidad/contingencia para los sistemas críticos, con pruebas periódicas. | J59: TI + Dirección
... B65: ALTA | C65: 3-6 meses | D65: M3 · Gobernanza Tecnológica | E65: CN4 | F65: Revisión periódica del cumplimiento normativo tecnológico (auditorías TI) | G65: Parcial | H65: Cláusula 9.2 Auditoría interna | I65: Incluir el componente tecnológico dentro del plan anual de auditoría interna de cumplimiento (ver Módulo 1, F2). | J65: TI + Auditoría/Dirección
B66: ALTA | C66: 3-6 meses | D66: M2 · Madurez Institucional | E66: R5 | F66: Pruebas periódicas de seguridad (pentesting, análisis de vulnerabilidades) | G66: 2 | H66: A.8.8 Gestión de vulnerabilidades técnicas | I66: Ver Módulo 1, E5 y F4. | J66: TI
B67: ALTA | C67: 3-6 meses | D67: M2 · Madurez Institucional | E67: T2 | F67: Verificación de que los encargados externos cumplen estándares equivalentes de protección de datos | G67: 3 | H67: A.5.22 Seguimiento, revisión y gestión de cambios en los servicios de proveedores | I67: Ver Módulo 1, D4. | J67: DPD + TI
B68: ALTA | C68: 3-6 meses | D68: M2 · Madurez Institucional | E68: T3 | F68: Registro actualizado de encargados de tratamiento externos | G68: 2 | H68: A.5.19 Seguridad de la información en las relaciones con proveedores | I68: Mantener un registro único y actualizado de todos los encargados de tratamiento (plataformas, proveedores TI, aliados). | J68: DPD
B69: ALTA | C69: 3-6 meses | D69: M1 · Cumplimiento LOPDP/RGLOPDP | E69: B3 | F69: Política de privacidad clara, accesible y revisada periódicamente | G69: No | H69: A.5.1 Políticas de seguridad de la información | I69: Redactar, aprobar y publicar la política institucional de protección de datos personales; revisarla al menos una vez al año. | J69: Dirección + DPD
B70: ALTA | C70: 3-6 meses | D70: M1 · Cumplimiento LOPDP/RGLOPDP | E70: C1 | F70: Mecanismo formal para atender solicitudes de Acceso a datos personales | G70: Parcial | H70: A.5.34 Privacidad y protección de datos personales (PII) | I70: Crear un procedimiento documentado (formulario, canal y plazos) para solicitudes de acceso. | J70: DPD + Secretaría
B71: ALTA | C71: 3-6 meses | D71: M1 · Cumplimiento LOPDP/RGLOPDP | E71: C2 | F71: Mecanismo formal para solicitudes de Rectificación de datos | G71: Parcial | H71: A.5.34 Privacidad y protección de datos personales (PII) | I71: Extender el procedimiento de derechos ARCO+ para incluir rectificación con verificación de identidad y trazabilidad del cambio. | J71: DPD + Secretaría
B72: ALTA | C72: 3-6 meses | D72: M1 · Cumplimiento LOPDP/RGLOPDP | E72: C5 | F72: Cumplimiento de los plazos legales para atender derechos de los titulares | G72: Parcial | H72: A.5.34 / A.9.1 Monitoreo, medición, análisis y evaluación (cláusula 9.1) | I72: Establecer indicadores de tiempo de respuesta y un registro de solicitudes con seguimiento de vencimientos. | J72: DPD
B73: ALTA | C73: 3-6 meses | D73: M2 · Madurez Institucional | E73: T1 | F73: Cláusulas de protección de datos incluidas en los contratos con proveedores | G73: 3 | H73: A.5.20 Abordar la seguridad de la información en los acuerdos con proveedores | I73: Ver Módulo 1, D2. | J73: Jurídico + DPD
B74: ALTA | C74: 3-6 meses | D74: M3 · Gobernanza Tecnológica | E74: TG3 | F74: Comité o instancia de toma de decisiones tecnológicas | G74: No | H74: Cláusula 5.1 Liderazgo y compromiso | I74: Crear un comité de TI/seguridad de la información con reuniones periódicas documentadas. | J74: Dirección + TI
B75: ALTA | C75: 3-6 meses | D75: M3 · Gobernanza Tecnológica | E75: TA1 | F75: Inventario actualizado de hardware (equipos, servidores, dispositivos de red) | G75: No | H75: A.5.9 Inventario de información y otros activos asociados | I75: Levantar y mantener un inventario de hardware con responsable, ubicación y criticidad. | J75: TI
B76: ALTA | C76: 3-6 meses | D76: M3 · Gobernanza Tecnológica | E76: SI4 | F76: Registro de logs de auditoría en los sistemas de información (accesos, cambios, consultas) | G76: Parcial | H76: A.8.15 Registro (logging) / A.8.16 Actividades de monitoreo | I76: Habilitar el registro de logs de acceso y cambios en los sistemas críticos, con retención y revisión periódica. | J76: TI
B77: ALTA | C77: 3-6 meses | D77: M3 · Gobernanza Tecnológica | E77: SEC2 | F77: Gestión de parches y actualizaciones de seguridad en sistemas operativos y aplicaciones | G77: Parcial | H77: A.8.8 Gestión de vulnerabilidades técnicas / A.8.9 Gestión de la configuración | I77: Implementar un proceso formal y calendarizado de gestión de parches y actualizaciones. | J77: TI
B78: MEDIA | C78: 6-9 meses | D78: M1 · Cumplimiento LOPDP/RGLOPDP | E78: A3 | F78: Documentación del período de conservación conforme a minimización y proporcionalidad | G78: Parcial | H78: A.5.33 Protección de los registros | I78: Definir y publicar una tabla de retención y eliminación de datos personales por tipo de dato y proceso. | J78: DPD + Archivo/Secretaría
B79: MEDIA | C79: 6-9 meses | D79: M1 · Cumplimiento LOPDP/RGLOPDP | E79: D3 | F79: Acuerdos de confidencialidad firmados con encargados y colaboradores que acceden a datos | G79: Parcial | H79: A.6.6 Acuerdos de confidencialidad o no divulgación | I79: Firmar acuerdos de confidencialidad con todo el personal y terceros con acceso a datos personales. | J79: Talento Humano + Jurídico
B80: MEDIA | C80: 6-9 meses | D80: M3 · Gobernanza Tecnológica | E80: TG2 | F80: Unidad o responsable formal de TI con funciones y presupuesto definidos | G80: Parcial | H80: A.5.2 Roles y responsabilidades de seguridad de la información | I80: Formalizar la unidad o responsable de TI, con funciones, dependencia jerárquica y presupuesto asignado. | J80: Dirección
B81: MEDIA | C81: 6-9 meses | D81: M3 · Gobernanza Tecnológica | E81: SEC5 | F81: Gestión formal del control de accesos privilegiados (administradores de sistemas) | G81: Parcial | H81: A.8.2 Derechos de acceso privilegiado | I81: Formalizar la gestión de cuentas privilegiadas: cuentas nominales, registro de uso y revisión periódica. | J81: TI

Sheet Plan_Institucion_D
B2: PLAN DE CIERRE DE BRECHAS · Institución D (índice global actual: 11.8%)
B4: Prioridad | C4: Plazo | D4: Módulo | E4: ID | F4: Criterio / Dimensión | G4: Estado actual | H4: Control ISO/IEC 27001:2022 | I4: Acción correctiva recomendada | J4: Responsable sugerido
B5: CRÍTICA | C5: 0-3 meses | D5: M1 · Cumplimiento LOPDP/RGLOPDP | E5: B5 | F5: Política de uso de cookies con consentimiento informado | G5: No | H5: A.5.34 Privacidad y protección de datos personales (PII) | I5: Implementar aviso/banner de cookies con opciones de aceptación granular en los sitios y plataformas institucionales. | J5: TI + DPD
B6: CRÍTICA | C6: 0-3 meses | D6: M1 · Cumplimiento LOPDP/RGLOPDP | E6: D2 | F6: Contratos firmados con encargados de tratamiento externos | G6: No | H6: A.5.20 Abordar la seguridad de la información en los acuerdos con proveedores | I6: Incorporar cláusulas de protección de datos en todo contrato con proveedores que traten datos personales; regularizar los vigentes. | J6: Jurídico + DPD
B7: CRÍTICA | C7: 0-3 meses | D7: M1 · Cumplimiento LOPDP/RGLOPDP | E7: E3 | F7: Evaluación de Impacto en Protección de Datos (EIPD) para tratamientos de alto riesgo | G7: No | H7: Cláusula 8.2 Evaluación de riesgos de seguridad de la información | I7: Elaborar EIPD para los tratamientos de mayor riesgo (video-vigilancia, biometría, salud, datos de menores) antes de su implementación o de forma retroactiva. | J7: DPD
B8: CRÍTICA | C8: 0-3 meses | D8: M1 · Cumplimiento LOPDP/RGLOPDP | E8: E5 | F8: Análisis de vulnerabilidades informáticas relacionadas con datos personales | G8: No | H8: A.8.8 Gestión de vulnerabilidades técnicas | I8: Implementar un proceso periódico de identificación y remediación de vulnerabilidades en sistemas que tratan datos personales. | J8: TI
B9: CRÍTICA | C9: 0-3 meses | D9: M1 · Cumplimiento LOPDP/RGLOPDP | E9: F2 | F9: Revisiones periódicas y auditorías de cumplimiento de protección de datos | G9: No | H9: Cláusula 9.2 Auditoría interna | I9: Planificar auditorías internas anuales de cumplimiento LOPDP con informe de hallazgos y seguimiento. | J9: Auditoría interna/Dirección + DPD
B10: CRÍTICA | C10: 0-3 meses | D10: M2 · Madurez Institucional | E10: G1 | F10: Estructura de gobierno de datos con roles y responsabilidades definidos (Responsable, DPD, Encargados) | G10: 1 | H10: A.5.2 Roles y responsabilidades de seguridad de la información | I10: Definir y aprobar formalmente el organigrama de gobierno de datos (RACI) con Responsable, DPD y Encargados. | J10: Dirección
B11: CRÍTICA | C11: 0-3 meses | D11: M2 · Madurez Institucional | E11: P2 | F11: Registro de Actividades de Tratamiento (RAT) actualizado | G11: 1 | H11: A.5.9 Inventario de información y otros activos asociados | I11: Levantar el RAT y establecer una revisión periódica (al menos semestral) para mantenerlo vigente. | J11: DPD
B12: CRÍTICA | C12: 0-3 meses | D12: M2 · Madurez Institucional | E12: P3 | F12: Procedimientos formales para responder derechos ARCO+ de los titulares | G12: 1 | H12: A.5.34 Privacidad y protección de datos personales (PII) | I12: Formalizar el procedimiento único de atención de derechos ARCO+ (ver Módulo 1, sección C). | J12: DPD
B13: CRÍTICA | C13: 0-3 meses | D13: M2 · Madurez Institucional | E13: P5 | F13: Proceso de revisión y mejora continua de los procedimientos de protección de datos | G13: 1 | H13: Cláusula 10.1 Mejora continua | I13: Establecer un ciclo anual de revisión de procedimientos de protección de datos, con responsable y fecha de revisión. | J13: DPD
B14: CRÍTICA | C14: 0-3 meses | D14: M2 · Madurez Institucional | E14: R1 | F14: Análisis de riesgos formal para el tratamiento de datos personales | G14: 1 | H14: Cláusula 6.1 / 8.2 Evaluación de riesgos de seguridad de la información | I14: Formalizar la metodología de análisis de riesgos y aplicarla de forma recurrente (ver Módulo 1, E2). | J14: TI + DPD
B15: CRÍTICA | C15: 0-3 meses | D15: M2 · Madurez Institucional | E15: A1 | F15: Auditorías internas periódicas de cumplimiento en protección de datos | G15: 1 | H15: Cláusula 9.2 Auditoría interna | I15: Ver Módulo 1, F2. | J15: Auditoría/Dirección
B16: CRÍTICA | C16: 0-3 meses | D16: M2 · Madurez Institucional | E16: A3 | F16: Hallazgos de auditoría documentados, priorizados e implementados con seguimiento | G16: 1 | H16: Cláusula 10.1 Mejora continua | I16: Implementar un plan de acción con seguimiento formal para cada hallazgo de auditoría. | J16: DPD + Dirección
B17: CRÍTICA | C17: 0-3 meses | D17: M2 · Madurez Institucional | E17: CC2 | F17: Capacitaciones formales y periódicas sobre protección de datos a todos los niveles | G17: 1 | H17: A.6.3 Concienciación, educación y formación en seguridad de la información | I17: Implementar un plan de capacitación anual, con registro de asistencia y evaluación de efectividad. | J17: Talento Humano + DPD
B18: CRÍTICA | C18: 0-3 meses | D18: M2 · Madurez Institucional | E18: R3 | F18: Evaluaciones de Impacto en Protección de Datos (EIPD) cuando corresponde | G18: 1 | H18: Cláusula 8.2 Evaluación de riesgos de seguridad de la información | I18: Ver Módulo 1, E3. | J18: DPD
B19: CRÍTICA | C19: 0-3 meses | D19: M1 · Cumplimiento LOPDP/RGLOPDP | E19: A4 | F19: Inventario actualizado de flujos de datos (quién recibe, quién envía, con qué propósito) | G19: No | H19: A.5.9 / A.8.1 Dispositivos de usuario final | I19: Elaborar un diagrama de flujos de datos personales (origen, destino, medio, finalidad) y mantenerlo actualizado. | J19: DPD + TI
B20: CRÍTICA | C20: 0-3 meses | D20: M1 · Cumplimiento LOPDP/RGLOPDP | E20: C3 | F20: Mecanismo formal para solicitudes de Cancelación / Supresión de datos | G20: No | H20: A.5.34 Privacidad y protección de datos personales (PII) | I20: Definir el procedimiento y las excepciones legales de conservación aplicables a la supresión de datos. | J20: DPD + Secretaría/Archivo
B21: CRÍTICA | C21: 0-3 meses | D21: M1 · Cumplimiento LOPDP/RGLOPDP | E21: C4 | F21: Mecanismo formal para solicitudes de Oposición al tratamiento | G21: No | H21: A.5.34 Privacidad y protección de datos personales (PII) | I21: Incorporar la oposición como opción explícita en los formatos de consentimiento y en el procedimiento de derechos. | J21: DPD + Secretaría
B22: CRÍTICA | C22: 0-3 meses | D22: M1 · Cumplimiento LOPDP/RGLOPDP | E22: E4 | F22: Procedimiento documentado para notificación de vulneraciones de seguridad | G22: No | H22: A.5.24 Planificación y preparación de la gestión de incidentes / A.6.8 Reporte de eventos | I22: Documentar el procedimiento de gestión y notificación de incidentes/vulneraciones, con roles, plazos y plantillas de notificación. | J22: TI + DPD
B23: CRÍTICA | C23: 0-3 meses | D23: M1 · Cumplimiento LOPDP/RGLOPDP | E23: E6 | F23: Políticas de anonimización, cifrado y eliminación segura de datos | G23: No | H23: A.8.24 Uso de criptografía / A.8.10 Eliminación de la información | I23: Definir estándares de cifrado para datos en reposo/tránsito y un procedimiento de borrado seguro para bajas de equipos y medios. | J23: TI
B24: CRÍTICA | C24: 0-3 meses | D24: M1 · Cumplimiento LOPDP/RGLOPDP | E24: E7 | F24: Señalización visible en zonas con cámaras de seguridad | G24: No | H24: A.7.4 Monitoreo de seguridad física | I24: Instalar señalética visible en todas las zonas con cámaras, indicando finalidad y responsable del tratamiento. | J24: Administrativo + DPD
B25: CRÍTICA | C25: 0-3 meses | D25: M1 · Cumplimiento LOPDP/RGLOPDP | E25: F1 | F25: Capacitaciones periódicas a docentes, autoridades y estudiantes sobre protección de datos | G25: No | H25: A.6.3 Concienciación, educación y formación en seguridad de la información | I25: Implementar un plan anual de capacitación en LOPDP y seguridad de la información para todos los roles. | J25: Talento Humano + DPD
B26: CRÍTICA | C26: 0-3 meses | D26: M1 · Cumplimiento LOPDP/RGLOPDP | E26: F3 | F26: Política de retención y eliminación de datos documentada y aplicada | G26: No | H26: A.5.33 Protección de los registros / A.8.10 Eliminación de la información | I26: Aprobar la política de retención (ver A3) y ejecutar depuraciones periódicas verificables. | J26: DPD + Archivo
B27: CRÍTICA | C27: 0-3 meses | D27: M2 · Madurez Institucional | E27: P1 | F27: Procesos de tratamiento de datos documentados, aprobados y comunicados al personal | G27: 1 | H27: A.5.37 Procedimientos operativos documentados | I27: Documentar y aprobar los procedimientos clave de tratamiento de datos y capacitar al personal en su aplicación. | J27: DPD + dueños de proceso
B28: CRÍTICA | C28: 0-3 meses | D28: M2 · Madurez Institucional | E28: P4 | F28: Procedimientos para gestión de incidentes y brechas de datos | G28: 1 | H28: A.5.24 Planificación y preparación de la gestión de incidentes | I28: Aprobar el procedimiento de gestión de incidentes de seguridad de la información con roles y tiempos de respuesta. | J28: TI + DPD
B29: CRÍTICA | C29: 0-3 meses | D29: M2 · Madurez Institucional | E29: R2 | F29: Controles, responsables y plazos de mitigación asignados a los riesgos identificados | G29: 1 | H29: Cláusula 6.1.3 Tratamiento de riesgos de seguridad de la información | I29: Mantener una matriz de riesgos con controles, responsable y fecha de mitigación, revisada periódicamente. | J29: TI + DPD
B30: CRÍTICA | C30: 0-3 meses | D30: M2 · Madurez Institucional | E30: A2 | F30: Indicadores y métricas de cumplimiento monitoreados regularmente | G30: 1 | H30: Cláusula 9.1 Monitoreo, medición, análisis y evaluación | I30: Definir un tablero de indicadores de cumplimiento LOPDP y revisarlo trimestralmente. | J30: DPD
B31: CRÍTICA | C31: 0-3 meses | D31: M2 · Madurez Institucional | E31: A4 | F31: Aplicación de un ciclo de mejora continua (PHVA) en la gestión de datos personales | G31: 1 | H31: Cláusula 10.1 Mejora continua | I31: Adoptar formalmente el ciclo Planificar-Hacer-Verificar-Actuar como método de gestión del sistema de protección de datos. | J31: DPD + Dirección
B32: CRÍTICA | C32: 0-3 meses | D32: M3 · Gobernanza Tecnológica | E32: TA2 | F32: Inventario actualizado de software y licencias | G32: No | H32: A.5.9 Inventario de información y otros activos asociados / A.8.19 Instalación de software | I32: Levantar y mantener un inventario de software y licencias, con control de instalación autorizada. | J32: TI
B33: CRÍTICA | C33: 0-3 meses | D33: M3 · Gobernanza Tecnológica | E33: SI3 | F33: Controles de acceso basados en roles (RBAC) o perfiles de usuario | G33: No | H33: A.5.15 Control de acceso / A.8.2 Derechos de acceso privilegiado / A.8.3 Restricción de acceso a la información | I33: Implementar perfiles de acceso por rol en todos los sistemas que traten datos personales, con revisión periódica de permisos. | J33: TI
B34: CRÍTICA | C34: 0-3 meses | D34: M3 · Gobernanza Tecnológica | E34: SEC3 | F34: Herramientas de protección perimetral (firewall, antivirus, IDS/IPS) | G34: No | H34: A.8.7 Protección contra código malicioso / A.8.20 Seguridad de redes | I34: Implementar y mantener firewall, antivirus/antimalware centralizado y, cuando el presupuesto lo permita, IDS/IPS. | J34: TI
B35: CRÍTICA | C35: 0-3 meses | D35: M3 · Gobernanza Tecnológica | E35: SEC6 | F35: Pruebas de seguridad (pentesting, ethical hacking) periódicas | G35: No | H35: A.8.8 Gestión de vulnerabilidades técnicas / A.8.29 Pruebas de seguridad | I35: Ver Módulo 1, F4. | J35: TI
B36: CRÍTICA | C36: 0-3 meses | D36: M3 · Gobernanza Tecnológica | E36: CN2 | F36: Aplicación del Esquema Gubernamental de Seguridad de la Información (EGSI) o similar | G36: No | H36: A.5.31 Requisitos legales, estatutarios, regulatorios y contractuales / Cláusula 4.2 | I36: Adoptar los controles del EGSI aplicables a instituciones educativas y mapearlos contra el Anexo A de ISO/IEC 27001:2022. | J36: TI + DPD
B37: CRÍTICA | C37: 0-3 meses | D37: M2 · Madurez Institucional | E37: G3 | F37: Políticas institucionales formalizadas sobre privacidad y protección de datos personales | G37: 1 | H37: A.5.1 Políticas de seguridad de la información | I37: Aprobar y difundir la política institucional de protección de datos personales. | J37: Dirección + DPD
B38: CRÍTICA | C38: 0-3 meses | D38: M2 · Madurez Institucional | E38: G2 | F38: Liderazgo y compromiso de la alta dirección con el cumplimiento normativo | G38: 2 | H38: Cláusula 5.1 Liderazgo y compromiso | I38: Incluir la protección de datos como punto permanente en la planificación estratégica y en los comités de dirección. | J38: Rectorado/Dirección
B39: CRÍTICA | C39: 0-3 meses | D39: M2 · Madurez Institucional | E39: CC1 | F39: Conocimiento básico del personal sobre la LOPDP y sus obligaciones | G39: 1 | H39: A.6.3 Concienciación, educación y formación en seguridad de la información | I39: Difundir una guía básica de LOPDP a todo el personal como parte de la inducción institucional. | J39: Talento Humano
B40: CRÍTICA | C40: 0-3 meses | D40: M3 · Gobernanza Tecnológica | E40: SI2 | F40: Integración entre los sistemas de información documentada | G40: No | H40: A.8.9 Gestión de la configuración / A.5.9 | I40: Documentar las integraciones existentes (APIs, exportaciones, sincronizaciones) entre sistemas. | J40: TI
B41: CRÍTICA | C41: 0-3 meses | D41: M3 · Gobernanza Tecnológica | E41: SV1 | F41: Sistema de gestión de incidentes y solicitudes TI (mesa de ayuda / help desk) | G41: No | H41: A.5.24 Planificación y preparación de la gestión de incidentes | I41: Implementar un canal único (mesa de ayuda) para reportar incidentes y solicitudes TI, incluyendo los de seguridad de datos. | J41: TI
B42: CRÍTICA | C42: 0-3 meses | D42: M3 · Gobernanza Tecnológica | E42: SV3 | F42: Acuerdos de Nivel de Servicio (SLA) con proveedores tecnológicos críticos | G42: No | H42: A.5.20 Abordar la seguridad de la información en los acuerdos con proveedores | I42: Formalizar SLA con los proveedores tecnológicos críticos (conectividad, plataforma académica, nube). | J42: TI + Jurídico
B43: CRÍTICA | C43: 0-3 meses | D43: M3 · Gobernanza Tecnológica | E43: SV4 | F43: Gestión de cambios formalizada para modificaciones en sistemas productivos | G43: No | H43: A.8.32 Gestión de cambios | I43: Implementar un procedimiento de gestión de cambios (solicitud, prueba, aprobación, registro) para sistemas productivos. | J43: TI
B44: CRÍTICA | C44: 0-3 meses | D44: M3 · Gobernanza Tecnológica | E44: CN3 | F44: Sistemas de información con requisitos de protección de datos desde su diseño (privacy by design) | G44: No | H44: A.8.25 Ciclo de vida de desarrollo seguro / A.5.34 | I44: Ver Módulo 2, CC3. | J44: TI + DPD
B45: ALTA | C45: 3-6 meses | D45: M2 · Madurez Institucional | E45: G4 | F45: Presupuesto asignado para actividades de cumplimiento y protección de datos | G45: 1 | H45: Cláusula 7.1 Recursos | I45: Asignar una partida presupuestaria anual específica para protección de datos y seguridad de la información. | J45: Dirección/Financiero
B46: ALTA | C46: 3-6 meses | D46: M2 · Madurez Institucional | E46: R4 | F46: Medidas de seguridad técnica (cifrado, control de acceso, logs) implementadas y documentadas | G46: 1 | H46: A.8.24 Uso de criptografía / A.8.15 Registro (logging) / A.8.3 Restricción de acceso | I46: Documentar formalmente los controles técnicos vigentes y las brechas frente al estándar deseado. | J46: TI
B47: ALTA | C47: 3-6 meses | D47: M1 · Cumplimiento LOPDP/RGLOPDP | E47: B1 | F47: Información al titular sobre qué datos se recopilan, cómo se usan y con quién se comparten | G47: No | H47: A.5.34 Privacidad y protección de datos personales (PII) | I47: Publicar avisos de privacidad claros y accesibles (portal web, matrícula, carteleras) para cada finalidad de tratamiento. | J47: DPD + Comunicación/Secretaría
B48: ALTA | C48: 3-6 meses | D48: M1 · Cumplimiento LOPDP/RGLOPDP | E48: B2 | F48: Obtención de consentimiento explícito antes de recopilar o procesar datos personales | G48: No | H48: A.5.34 Privacidad y protección de datos personales (PII) | I48: Implementar un formato de consentimiento informado (físico o digital) con registro de evidencia, diferenciado por finalidad. | J48: DPD + Secretaría
B49: ALTA | C49: 3-6 meses | D49: M1 · Cumplimiento LOPDP/RGLOPDP | E49: B4 | F49: Información a los titulares sobre cómo ejercer sus derechos ARCO+ | G49: Parcial | H49: A.5.34 Privacidad y protección de datos personales (PII) | I49: Incluir en avisos de privacidad y canales institucionales el procedimiento y medios para ejercer derechos ARCO+. | J49: DPD + Comunicación
B50: ALTA | C50: 3-6 meses | D50: M1 · Cumplimiento LOPDP/RGLOPDP | E50: D4 | F50: Verificación de que los encargados externos cumplen con la LOPDP | G50: No | H50: A.5.22 Seguimiento, revisión y gestión de cambios en los servicios de proveedores | I50: Establecer una evaluación periódica (cuestionario o auditoría) del cumplimiento de los encargados de tratamiento. | J50: DPD + TI
B51: ALTA | C51: 3-6 meses | D51: M1 · Cumplimiento LOPDP/RGLOPDP | E51: E1 | F51: Medidas de seguridad técnicas y organizativas para proteger datos personales | G51: No | H51: A.5.1 Políticas de seguridad de la información / Cláusula 8 Operación | I51: Definir e implementar un conjunto mínimo de controles técnicos y organizativos alineados a ISO/IEC 27001:2022, priorizados por riesgo. | J51: TI + DPD
B52: ALTA | C52: 3-6 meses | D52: M1 · Cumplimiento LOPDP/RGLOPDP | E52: E2 | F52: Análisis de riesgos que incluya el tratamiento de datos personales | G52: No | H52: Cláusula 6.1 / 8.2 Evaluación de riesgos de seguridad de la información | I52: Ejecutar un análisis de riesgos de protección de datos (activos, amenazas, vulnerabilidades, impacto) y actualizarlo anualmente. | J52: TI + DPD
B53: ALTA | C53: 3-6 meses | D53: M1 · Cumplimiento LOPDP/RGLOPDP | E53: F4 | F53: Pruebas de penetración o análisis de seguridad informática | G53: No | H53: A.8.29 Pruebas de seguridad en el desarrollo y aceptación / A.5.36 Cumplimiento de políticas | I53: Contratar o ejecutar pruebas de seguridad (pentesting/vulnerability assessment) al menos una vez al año sobre sistemas críticos. | J53: TI
B54: ALTA | C54: 3-6 meses | D54: M2 · Madurez Institucional | E54: CC3 | F54: Cultura de privacidad por diseño en el desarrollo de nuevos proyectos o sistemas | G54: 1 | H54: A.8.25 Ciclo de vida de desarrollo seguro / A.5.34 | I54: Incluir una lista de verificación de privacidad por diseño en la adquisición o desarrollo de todo nuevo sistema. | J54: TI + DPD
B55: ALTA | C55: 3-6 meses | D55: M3 · Gobernanza Tecnológica | E55: TG1 | F55: Plan estratégico de tecnología de la información (PETI) vigente y alineado al plan institucional | G55: No | H55: Cláusula 5.2 Política / A.5.1 Políticas de seguridad de la información | I55: Elaborar un PETI a 2-3 años alineado al plan educativo institucional, incluyendo protección de datos como eje. | J55: Dirección + TI
B56: ALTA | C56: 3-6 meses | D56: M3 · Gobernanza Tecnológica | E56: TA3 | F56: Identificación y clasificación de los sistemas de información por criticidad | G56: No | H56: A.5.12 Clasificación de la información | I56: Clasificar los sistemas de información según criticidad e impacto en caso de indisponibilidad o compromiso. | J56: TI
B57: ALTA | C57: 3-6 meses | D57: M3 · Gobernanza Tecnológica | E57: TA4 | F57: Gestión del ciclo de vida de los activos tecnológicos (adquisición, operación, baja) | G57: No | H57: A.5.10 Uso aceptable de los activos / A.5.11 Devolución de activos / A.7.14 Eliminación segura de equipos | I57: Definir el procedimiento de ciclo de vida de activos, incluyendo borrado seguro previo a la baja o reasignación. | J57: TI
B58: ALTA | C58: 3-6 meses | D58: M3 · Gobernanza Tecnológica | E58: SI1 | F58: Sistemas de información documentados (arquitectura, flujos de datos, usuarios) | G58: No | H58: A.5.9 / A.8.9 Gestión de la configuración | I58: Documentar la arquitectura, flujos de datos y usuarios de los sistemas de información institucionales. | J58: TI
B59: ALTA | C59: 3-6 meses | D59: M3 · Gobernanza Tecnológica | E59: SI5 | F59: Planes de continuidad o contingencia para sistemas de información críticos | G59: No | H59: A.5.29 Seguridad de la información durante la disrupción / A.5.30 Preparación TIC para la continuidad del negocio | I59: Elaborar un plan de continuidad/contingencia para los sistemas críticos, con pruebas periódicas. | J59: TI + Dirección
B60: ALTA | C60: 3-6 meses | D60: M3 · Gobernanza Tecnológica | E60: SI6 | F60: Respaldos periódicos de bases de datos y sistemas con pruebas de restauración | G60: No | H60: A.8.13 Respaldo de la información | I60: Formalizar la política de respaldos (frecuencia, retención) y ejecutar pruebas de restauración periódicas documentadas. | J60: TI
B61: ALTA | C61: 3-6 meses | D61: M3 · Gobernanza Tecnológica | E61: SEC1 | F61: Política de seguridad de la información documentada y vigente | G61: No | H61: A.5.1 Políticas de seguridad de la información | I61: Aprobar y difundir la política de seguridad de la información, revisándola al menos anualmente. | J61: TI + Dirección
B62: ALTA | C62: 3-6 meses | D62: M3 · Gobernanza Tecnológica | E62: SEC4 | F62: Segmentación de redes y control de acceso a la infraestructura | G62: No | H62: A.8.22 Segregación de redes / A.8.20 Seguridad de redes | I62: Segmentar la red (administrativa, académica, invitados/Wi-Fi) y controlar el acceso entre segmentos. | J62: TI
B63: ALTA | C63: 3-6 meses | D63: M3 · Gobernanza Tecnológica | E63: SV2 | F63: Medición de tiempos de respuesta y resolución de incidentes tecnológicos | G63: No | H63: Cláusula 9.1 Monitoreo, medición, análisis y evaluación | I63: Definir y monitorear indicadores de tiempo de respuesta y resolución de incidentes TI. | J63: TI
B64: ALTA | C64: 3-6 meses | D64: M3 · Gobernanza Tecnológica | E64: CN1 | F64: Gestión de TI alineada con la Ley de Comercio Electrónico, Firmas y Mensajes de Datos | G64: No | H64: A.5.31 Requisitos legales, estatutarios, regulatorios y contractuales | I64: Verificar y documentar el cumplimiento de la normativa de comercio electrónico y firma electrónica en los procesos digitales institucionales. | J64: Jurídico + TI
B65: ALTA | C65: 3-6 meses | D65: M3 · Gobernanza Tecnológica | E65: CN4 | F65: Revisión periódica del cumplimiento normativo tecnológico (auditorías TI) | G65: No | H65: Cláusula 9.2 Auditoría interna | I65: Incluir el componente tecnológico dentro del plan anual de auditoría interna de cumplimiento (ver Módulo 1, F2). | J65: TI + Auditoría/Dirección
B66: ALTA | C66: 3-6 meses | D66: M2 · Madurez Institucional | E66: R5 | F66: Pruebas periódicas de seguridad (pentesting, análisis de vulnerabilidades) | G66: 1 | H66: A.8.8 Gestión de vulnerabilidades técnicas | I66: Ver Módulo 1, E5 y F4. | J66: TI
B67: ALTA | C67: 3-6 meses | D67: M2 · Madurez Institucional | E67: T2 | F67: Verificación de que los encargados externos cumplen estándares equivalentes de protección de datos | G67: 1 | H67: A.5.22 Seguimiento, revisión y gestión de cambios en los servicios de proveedores | I67: Ver Módulo 1, D4. | J67: DPD + TI
B68: ALTA | C68: 3-6 meses | D68: M2 · Madurez Institucional | E68: T3 | F68: Registro actualizado de encargados de tratamiento externos | G68: 1 | H68: A.5.19 Seguridad de la información en las relaciones con proveedores | I68: Mantener un registro único y actualizado de todos los encargados de tratamiento (plataformas, proveedores TI, aliados). | J68: DPD
B69: ALTA | C69: 3-6 meses | D69: M1 · Cumplimiento LOPDP/RGLOPDP | E69: B3 | F69: Política de privacidad clara, accesible y revisada periódicamente | G69: Parcial | H69: A.5.1 Políticas de seguridad de la información | I69: Redactar, aprobar y publicar la política institucional de protección de datos personales; revisarla al menos una vez al año. | J69: Dirección + DPD
B70: ALTA | C70: 3-6 meses | D70: M1 · Cumplimiento LOPDP/RGLOPDP | E70: C1 | F70: Mecanismo formal para atender solicitudes de Acceso a datos personales | G70: No | H70: A.5.34 Privacidad y protección de datos personales (PII) | I70: Crear un procedimiento documentado (formulario, canal y plazos) para solicitudes de acceso. | J70: DPD + Secretaría
B71: ALTA | C71: 3-6 meses | D71: M1 · Cumplimiento LOPDP/RGLOPDP | E71: C2 | F71: Mecanismo formal para solicitudes de Rectificación de datos | G71: No | H71: A.5.34 Privacidad y protección de datos personales (PII) | I71: Extender el procedimiento de derechos ARCO+ para incluir rectificación con verificación de identidad y trazabilidad del cambio. | J71: DPD + Secretaría
B72: ALTA | C72: 3-6 meses | D72: M2 · Madurez Institucional | E72: CC4 | F72: Consecuencias formales (régimen disciplinario) ante incumplimiento de normas de privacidad | G72: 2 | H72: A.6.4 Proceso disciplinario | I72: Incorporar el incumplimiento de las normas de protección de datos al reglamento interno de trabajo/régimen disciplinario. | J72: Talento Humano + Jurídico
B73: ALTA | C73: 3-6 meses | D73: M2 · Madurez Institucional | E73: T1 | F73: Cláusulas de protección de datos incluidas en los contratos con proveedores | G73: 1 | H73: A.5.20 Abordar la seguridad de la información en los acuerdos con proveedores | I73: Ver Módulo 1, D2. | J73: Jurídico + DPD
B74: ALTA | C74: 3-6 meses | D74: M3 · Gobernanza Tecnológica | E74: TG3 | F74: Comité o instancia de toma de decisiones tecnológicas | G74: No | H74: Cláusula 5.1 Liderazgo y compromiso | I74: Crear un comité de TI/seguridad de la información con reuniones periódicas documentadas. | J74: Dirección + TI
B75: ALTA | C75: 3-6 meses | D75: M3 · Gobernanza Tecnológica | E75: TA1 | F75: Inventario actualizado de hardware (equipos, servidores, dispositivos de red) | G75: Parcial | H75: A.5.9 Inventario de información y otros activos asociados | I75: Levantar y mantener un inventario de hardware con responsable, ubicación y criticidad. | J75: TI
B76: ALTA | C76: 3-6 meses | D76: M3 · Gobernanza Tecnológica | E76: SI4 | F76: Registro de logs de auditoría en los sistemas de información (accesos, cambios, consultas) | G76: No | H76: A.8.15 Registro (logging) / A.8.16 Actividades de monitoreo | I76: Habilitar el registro de logs de acceso y cambios en los sistemas críticos, con retención y revisión periódica. | J76: TI
B77: ALTA | C77: 3-6 meses | D77: M3 · Gobernanza Tecnológica | E77: SEC2 | F77: Gestión de parches y actualizaciones de seguridad en sistemas operativos y aplicaciones | G77: No | H77: A.8.8 Gestión de vulnerabilidades técnicas / A.8.9 Gestión de la configuración | I77: Implementar un proceso formal y calendarizado de gestión de parches y actualizaciones. | J77: TI
B78: MEDIA | C78: 6-9 meses | D78: M1 · Cumplimiento LOPDP/RGLOPDP | E78: A1 | F78: Identificación y registro de todas las bases de datos que contienen datos personales | G78: No | H78: A.5.9 Inventario de información y otros activos asociados | I78: Levantar y mantener un inventario único de bases de datos con responsable, finalidad, base de legitimación y ubicación (Registro de Actividades de Tratamiento, RAT). | J78: DPD + Secretaría/áreas dueñas de la información
B79: MEDIA | C79: 6-9 meses | D79: M1 · Cumplimiento LOPDP/RGLOPDP | E79: A3 | F79: Documentación del período de conservación conforme a minimización y proporcionalidad | G79: No | H79: A.5.33 Protección de los registros | I79: Definir y publicar una tabla de retención y eliminación de datos personales por tipo de dato y proceso. | J79: DPD + Archivo/Secretaría
B80: MEDIA | C80: 6-9 meses | D80: M1 · Cumplimiento LOPDP/RGLOPDP | E80: D3 | F80: Acuerdos de confidencialidad firmados con encargados y colaboradores que acceden a datos | G80: No | H80: A.6.6 Acuerdos de confidencialidad o no divulgación | I80: Firmar acuerdos de confidencialidad con todo el personal y terceros con acceso a datos personales. | J80: Talento Humano + Jurídico
B81: MEDIA | C81: 6-9 meses | D81: M3 · Gobernanza Tecnológica | E81: TG2 | F81: Unidad o responsable formal de TI con funciones y presupuesto definidos | G81: No | H81: A.5.2 Roles y responsabilidades de seguridad de la información | I81: Formalizar la unidad o responsable de TI, con funciones, dependencia jerárquica y presupuesto asignado. | J81: Dirección
B82: MEDIA | C82: 6-9 meses | D82: M3 · Gobernanza Tecnológica | E82: SEC5 | F82: Gestión formal del control de accesos privilegiados (administradores de sistemas) | G82: No | H82: A.8.2 Derechos de acceso privilegiado | I82: Formalizar la gestión de cuentas privilegiadas: cuentas nominales, registro de uso y revisión periódica. | J82: TI
B83: MEDIA | C83: 6-9 meses | D83: M3 · Gobernanza Tecnológica | E83: TG4 | F83: Aplicación de un marco de referencia de gobernanza TI (COBIT, ITIL, ISO 38500, ISO/IEC 27001 u otro) | G83: No | H83: Cláusula 4.1-4.4 Contexto de la organización y alcance del SGSI | I83: Adoptar ISO/IEC 27001:2022 como marco de referencia principal y mapear controles existentes contra su Anexo A. | J83: TI + DPD
B84: BAJA | C84: 9-12 meses | D84: M1 · Cumplimiento LOPDP/RGLOPDP | E84: A2 | F84: Finalidad específica definida para cada tratamiento | G84: Parcial | H84: A.5.12 Clasificación de la información | I84: Documentar la finalidad de cada tratamiento en el RAT y en los avisos de privacidad correspondientes. | J84: DPD + áreas dueñas de la información
